Workbook
Name BI: #REF!
Name BI: #REF!
Name COBERTURAS: #REF!
Name COBERTURAS: #REF!
Name COBRC: #REF!
Name COBRC: #REF!
Name complejitos: #REF!
Name SUBLIMITES: #REF!
Name SUBLIMITES: #REF!
Name TC: #REF!
Name UBCINEMEX: 'Ubicaciones total (2)'!$A$1:$M$368
Name UBIC: #REF!

Sheet COASEGURP
A1: Tipo de Operación: | B1:  Coaseguro Suscrip. No Líder
A2: (Coaseguro con otra Compañía). | B2:  Coaseguro Suscrip. Líder
A4: Participación Propia: | B4: 0.7
A5: Compañía Líder: | B5: GRUPO MEXICANO DE SEGUROS, S.A. DE C.V.
A7: Compañías Participantes: | B7: % Participación
A8: GREAT AMERICA = EL AGUILA COMPAÑÍA DE SEGUROS, S.A. DE C.V. | B8: 0.15
A9: SEGUROS ATLAS, S.A. | B9: 0.15
A15: Total, Participación | B15: 100%%
A17: Facturación (Coaseguro Líder): | B17:  Parte de la Compañía.
B18:  Total de la Operación.
A21: Facturación (Coaseguro No Líder) Pagador:
A27: Las COASEGURADORAS acuerdan que la distribución de la participación en el riesgo por sección/ramo es el siguiente:
A30: MONEDA DE LA PÓLIZA.
A32:  Pesos Mexicanos (MXP)
A33:  Dólares (USD)
A36: FORMA DE PAGO DEL ASEGURADO.
A38:  Anual.
A39:  Contado.
A40:  Semestral.
A41:  Trimestral.
A42:  Mensual.
A44: PERIODO DE GRACIA PARA EL PAGO DE LA PRIMA POR PARTE DEL ASEGURADO.
... A64: 
A65: Prima Neta. | B65: ______%
A66:  Recargos por pago fraccionado. ____%
A67:  Sobre comisión. _____%
A69: Se incluye detalle de comisiones por cobertura y/o ramo contable.
A71: COMISIÓN POR ADMINISTRACIÓN DE COASEGURO.
A73: La comisión por administración para la COASEGURADORA LIDER será de: ____0___% sobre la participación de cada COASEGURADORA SEGUIDORA.
A75: SINIESTROS E INDEMNIZACIONES.
A77: Las COASEGURADORAS acuerdan que los ajustes de los siniestros se lleven a cabo a través del panel de ajustadores de la COASEGURADORA LÍDER, asimismo, las indemnizaciones que corresponda a los siniestros procedentes, sea realizado por la COASEGURADORA LÍDER sin la previa autorización de las COASEGURADORAS SEGUIDORAS dentro de los límites siguientes:
A79:  Hasta el __0_% del límite de responsabilidad.
A80:  Hasta un límite máximo de $_____________ (MXP) o (USD).

Sheet Hoja4
G2: COMISION | H2: 0.08
A3: GLOBAL | B3: 1632592.5 | C3: 100.00 | D3: 17,223.85 | E3: 263,986.62 | F3: 1,913,902.97 | H3: =B3*H2 -> 130607.4 | I3: =H9+H16 -> 130607.4
B4: PRIMA NETA | C4: DERECHOS | D4: RECARGOS | E4: IVA | F4: TOTAL
A9: POLIZA 12 MESES | B9: 1088395 | C9: 100.00 | D9: 11,482.57 | E9: 175,996.41 | F9: 1,275,973.98 | H9: =B9*H2 -> 87071.6
B10: PRIMA NETA | C10: DERECHOS | D10: RECARGOS | E10: IVA | F10: TOTAL
A16: ENDOSO 6 MESES | B16: 544197.5 | C16: - | D16: 5,741.28 | E16: 87,990.21 | F16: 637,928.99 | H16: =B16*H2 -> 43535.8
B17: PRIMA NETA | C17: DERECHOS | D17: RECARGOS | E17: IVA | F17: TOTAL

Sheet DESGLOSE DE RECIBOS
A2: RAZON SOCIAL | B2: RFC | C2: DIRECCION | D2: PORCENTAJE | E2: PRIMA TOTAL | F2: CUOTA | H2: CLIENTES
A3: ARENA DE JUEGOS | B3: AJU161030UF9 | C3: BOSQUE DE CIRUELOS No. 99 PISO 4 BOSQUES DE LAS LOMAS C.P.11700 DELEGACIÓN MIGUEL HIDALGO | D3: 0.010413701 | E3: =E58*D3 -> 13287.615 | F3: 1 | G3: =(E3/366)*93 -> 3376.3611
F4: 2 | G4: =(E3/366)*91 -> 3303.7512
F5: 3 | G5: =G4 -> 3303.7512
F6: 4 | G6: =G5 -> 3303.7512 | H6: 569936
F7: TOTAL | G7: =SUM(G3:G6) -> 13287.615
A8: BOUTIQUE BOWLING | B8: BBM110328PB2 | C8: BOSQUE DE CIRUELOS No. 99 PISO 4 BOSQUES DE LAS LOMAS C.P.11700 DELEGACIÓN MIGUEL HIDALGO | D8: 0.042021581 | E8: =$E$58*D8 -> 53618.456 | F8: 1 | G8: =E8/366*93 -> 13624.362
F9: 2 | G9: =E8/366*91 -> 13331.365 | H9: 119192
F10: 3 | G10: =G9 -> 13331.365
F11: 4 | G11: =G10 -> 13331.365
F12: TOTAL | G12: =SUM(G8:G11) -> 53618.456
A13: CINEMAS LUMIERE S.A. DE C.V. | B13: CLU9408151M9 | C13: AV. JAVIER BARROS SIERRA No. 540 TORRE 1 PH1 COLONIA SANTA FE C.P. 01210 DELEGACIÓN ÁLVARO OBREGÓN | D13: 0.19155136 | E13: =$E$58*D13 -> 244414.61 | F13: 1 | G13: =E13/366*93 -> 62105.351 | H13: 302649
F14: 2 | G14: =E13/366*91 -> 60769.752
F15: 3 | G15: =G14 -> 60769.752
F16: 4 | G16: =G15 -> 60769.752
F17: TOTAL | G17: =SUM(G13:G16) -> 244414.61
A18: CINEMEX MORELIA S.A DE C.V. | B18: CMO040512BX5 | C18: AV. JAVIER BARROS SIERRA No. 540 TORRE 1 PH1 COLONIA SANTA FE C.P. 01210 DELEGACIÓN ÁLVARO OBREGÓN | D18: 0.19713715 | E18: =$E$58*D18 -> 251541.93 | F18: 1 | G18: =E18/366*93 -> 63916.393
F19: 2 | G19: =E18/366*91 -> 62541.847 | H19: 302621
F20: 3 | G20: =G19 -> 62541.847
F21: 4 | G21: =G20 -> 62541.847
F22: TOTAL | G22: =SUM(G18:G21) -> 251541.93
A23: CINEMEX SAN ANTONIO S.A. DE C.V. | B23: CSA970723LT7 | C23: AV. JAVIER BARROS SIERRA No. 540 TORRE 1 PH1 COLONIA SANTA FE C.P. 01210 DELEGACIÓN ÁLVARO OBREGÓN | D23: 0.16845506 | E23: =$E$58*D23 -> 214944.32 | F23: 1 | G23: =E23/366*93 -> 54617
F24: 2 | G24: =E23/366*91 -> 53442.441 | H24: 302638
F25: 3 | G25: =G24 -> 53442.441
F26: 4 | G26: =G25 -> 53442.441
F27: TOTAL | G27: =SUM(G23:G26) -> 214944.32
A28: CINEMEX TOLUCA II S.A. DE C.V. | B28: CTI000411AA3 | C28: AV. JAVIER BARROS SIERRA No. 540 TORRE 1 PH1 COLONIA SANTA FE C.P. 01210 DELEGACIÓN ÁLVARO OBREGÓN | D28: 0.18339164 | E28: =$E$58*D28 -> 234003.02 | F28: 1 | G28: =E28/366*93 -> 59459.783
F29: 2 | G29: =E28/366*91 -> 58181.078
F30: 3 | G30: =G29 -> 58181.078 | H30: 302639
F31: 4 | G31: =G30 -> 58181.078
F32: TOTAL | G32: =SUM(G28:G31) -> 234003.02
A33: CINEMEX WTC S.A. DE C.V. | B33: CWT97121519A | C33: AV. JAVIER BARROS SIERRA No. 540 TORRE 1 PH1 COLONIA SANTA FE C.P. 01210 DELEGACIÓN ÁLVARO OBREGÓN | D33: 0.18452693 | E33: =$E$58*D33 -> 235451.61 | F33: 1 | G33: =E33/366*93 -> 59827.869
F34: 2 | G34: =E33/366*91 -> 58541.248 | H34: 569941
F35: 3 | G35: =G34 -> 58541.248
F36: 4 | G36: =G35 -> 58541.248
F37: TOTAL | G37: =SUM(G33:G36) -> 235451.61
A38: ENTRETENIMIENTO ALTERNO S.A. DE C.V. | B38: EAL030815ICA | C38: AV. JAVIER BARROS SIERRA No. 540 TORRE 1 PH1 COLONIA SANTA FE C.P. 01210 DELEGACIÓN ÁLVARO OBREGÓN | D38: 0.0001058619 | E38: =$E$58*D38 -> 135.07705 | F38: 1 | G38: =E38/366*93 -> 34.322858
F39: 2 | G39: =E38/366*91 -> 33.584732 | H39: 343424
F40: 3 | G40: =G39 -> 33.584732
F41: 4 | G41: =G40 -> 33.584732
F42: TOTAL | G42: =SUM(G38:G41) -> 135.07705
A43: GRUPO VINO POR TI S.A. DE C.V. | B43: GVT110328KW1 | C43: BOSQUE DE CIRUELOS No. 99 PISO 4 BOSQUES DE LAS LOMAS C.P.11700 DELEGACIÓN MIGUEL HIDALGO | D43: 0.0027435317 | E43: =$E$58*D43 -> 3500.6759 | F43: 1 | G43: =E43/366*93 -> 889.516
F44: 2 | G44: =E43/366*91 -> 870.38662
F45: 3 | G45: =G44 -> 870.38662 | H45: 343425
F46: 4 | G46: =G45 -> 870.38662
F47: TOTAL | G47: =SUM(G43:G46) -> 3500.6759
A48: OPERADORA DE CINEMAS S.A. DE C.V. | B48: OCI970818KX9 | C48: AV. JAVIER BARROS SIERRA No. 540 TORRE 1 PH1 COLONIA SANTA FE C.P. 01210 DELEGACIÓN ÁLVARO OBREGÓN | D48: 0.0072002242 | E48: =$E$58*D48 -> 9187.3007 | F48: 1 | G48: =E48/366*93 -> 2334.478
F49: 2 | G49: =E48/366*91 -> 2284.2742
F50: 3 | G50: =G49 -> 2284.2742 | H50: 302653
F51: 4 | G51: =G50 -> 2284.2742
F52: TOTAL | G52: =SUM(G48:G51) -> 9187.3007
A53: TEATRO POLANCO S.A. DE C.V. | B53: TPO970717R93 | C53: AV. JAVIER BARROS SIERRA No. 540 TORRE 1 PH1 COLONIA SANTA FE C.P. 01210 DELEGACIÓN ÁLVARO OBREGÓN | D53: 0.012452942 | E53: =$E$58*D53 -> 15889.634 | F53: 1 | G53: =E53/366*93 -> 4037.53
F54: 2 | G54: =E53/366*91 -> 3950.7014 | H54: 302655
F55: 3 | G55: =G54 -> 3950.7014
F56: 4 | G56: =G55 -> 3950.7014
F57: TOTAL | G57: =SUM(G53:G56) -> 15889.634
E58: ='Hoja Contable'!L411 -> 1275974.3 | G58: =G7+G12+G17+G22+G27+G32+G37+G42+G47+G52+G57 -> 1275974.3

Sheet Ubicaciones total (2)
A1: CONSECUTIVO | B1: SEGÚN CONTRATO DE ARRENDAMIENTO | C1: ESTADO | D1: CIUDAD O DELEGACION | E1: DIRECCION COMPLETA POR COMPLEJO | F1: CODIGO POSTAL | G1: DIRECCION COMPLETA | H1: VALOR EDIFICIOS | I1: VALOR CONTENIDOS USD | J1: EQUIPO ELECTRONICO USD | K1: INTERRUPCIÓN DE NEGOCIOS USD
A2: 1 | B2: Cinemas Lumiere S.A. de C.V. | C2: AGUASCALIENTES | D2: AGUASCALIENTES | E2: AV. INDEPENDENCIA #2351 TROJES DE ALONSO CENTRO COMERCIAL GALERIAS | F2: 20130 | G2: =CONCATENATE(E2,C2,D2,F2) -> AV. INDEPENDENCIA #2351 TROJES DE ALONSO CENTRO COMERCIAL GALERIASAGUASCALIENTESAGUASCALIENTES20130 | H2: 0 | I2: 2914531.1 | J2: 2437607.8 | K2: 1577355.4
A3: =+A2+1 -> 2 | B3: Cinemex San Antonio S.A de C.V. | C3: BAJA CALIFORNIA NORTE | D3: TIJUANA | E3: BLVD.AGUA AZUL No.7200 COL. LOMA BONITA NORTE LOCAL A-6 C.C. PLAZA LOMA BONITA TIJUANA, BAJA CALIFORNIA | F3: 22180 | G3: =CONCATENATE(E3,C3,D3,F3) -> BLVD.AGUA AZUL No.7200 COL. LOMA BONITA NORTE LOCAL A-6 C.C. PLAZA LOMA BONITA TIJUANA, BAJA CALIFORNIABAJA CALIFORNIA NORTETIJUANA22180 | H3: 0 | I3: 2210135 | J3: 1848476.5 | K3: 970304.07
A4: =+A3+1 -> 3 | B4: Cinemex Toluca II S.A de C.V. | C4: BAJA CALIFORNIA SUR | D4: LOS CABOS | E4: BOULEVARD LAZARO CARDENAS S/N LOCAL 301 Y 302 INTERIOR PLAZA PUERTO PARAISO COL. EL MEDANO CABO SAN LUCAS | F4: 23410 | G4: =CONCATENATE(E4,C4,D4,F4) -> BOULEVARD LAZARO CARDENAS S/N LOCAL 301 Y 302 INTERIOR PLAZA PUERTO PARAISO COL. EL MEDANO CABO SAN LUCASBAJA CALIFORNIA SUR LOS CABOS 23410 | H4: 0 | I4: 2914531.1 | J4: 2437607.8 | K4: 1251126.4
A5: =+A4+1 -> 4 | B5: Cinemex San Antonio S.A de C.V. | C5: BAJA CALIFORNIA NORTE | D5: TIJUANA | E5: BLVD. INSURGENTES #18015 ENTRE BLVD.MANUEL J. CLOUTHIER Y CALLE PASEO DEL PARQUE. TERCERA ETAPA RIO TIJUANA. CCMACROPLA | F5: 22110 | G5: =CONCATENATE(E5,C5,D5,F5) -> BLVD. INSURGENTES #18015 ENTRE BLVD.MANUEL J. CLOUTHIER Y CALLE PASEO DEL PARQUE. TERCERA ETAPA RIO TIJUANA. CCMACROPLABAJA CALIFORNIA NORTETIJUANA22110 | H5: 0 | I5: 4144003 | J5: 3465893.5 | K5: 1911967
A6: =+A5+1 -> 5 | B6: Cinemex San Antonio S.A de C.V. | C6: CAMPECHE | D6: CIUDAD DEL CARMEN | E6: PREDIO URBANO S/N LOCAL 35 AV.PERIFERICA NORTE X AV.CONCORDIA COL.ASA PONIENTE CD.DEL CARMEN, CAMPECHE | F6: 24170 | G6: =CONCATENATE(E6,C6,D6,F6) -> PREDIO URBANO S/N LOCAL 35 AV.PERIFERICA NORTE X AV.CONCORDIA COL.ASA PONIENTE CD.DEL CARMEN, CAMPECHECAMPECHECIUDAD DEL CARMEN24170 | H6: 0 | I6: 1885394.8 | J6: 1576875.6 | K6: 974495.44
A7: =+A6+1 -> 6 | B7: Cinemas Lumiere S.A. de C.V. | C7: CAMPECHE | D7: CIUDAD DEL CARMEN | E7: CARRETERA PUERTO REAL KM 2.5, COL. PALMIRA CIUDAD DEL CARMEN CAMPECHE | F7: 24154 | G7: =CONCATENATE(E7,C7,D7,F7) -> CARRETERA PUERTO REAL KM 2.5, COL. PALMIRA CIUDAD DEL CARMEN CAMPECHECAMPECHECIUDAD DEL CARMEN24154 | H7: 0 | I7: 2762668.7 | J7: 2310595.6 | K7: 1638130.3
A8: =+A7+1 -> 7 | B8: Cinemex Morelia S.A. de C.V. | C8: CHIHUAHUA | D8: CIUDAD DELICIAS | E8: AVE. DEL PARQUE ORIENTE #1000 LOCAL C SECTOR ORIENTE PLAZA OASIS | F8: 33000 | G8: =CONCATENATE(E8,C8,D8,F8) -> AVE. DEL PARQUE ORIENTE #1000 LOCAL C SECTOR ORIENTE PLAZA OASISCHIHUAHUACIUDAD DELICIAS33000 | H8: 0 | I8: 2210135 | J8: 1848476.5 | K8: 883682.25
A9: =+A8+1 -> 8 | B9: Cinemex Morelia S.A. de C.V. | C9: CHIHUAHUA | D9: CIUDAD DELICIAS | E9: BLVD. JOSE FUENTES MARES # 300, COL. STA. ROSA, CD. DELICIAS, CHIH. | F9: 31060 | G9: =CONCATENATE(E9,C9,D9,F9) -> BLVD. JOSE FUENTES MARES # 300, COL. STA. ROSA, CD. DELICIAS, CHIH.CHIHUAHUACIUDAD DELICIAS31060 | H9: 0 | I9: 1657601.2 | J9: 1386357.4 | K9: 718821.37
A10: =+A9+1 -> 9 | B10: Cinemas Lumiere S.A. de C.V. | C10: CHIHUAHUA | D10: CIUDAD DELICIAS | E10: BLVD. ORTIZ MENA y C. INDIANA # 3300-D, COL. LAS AGUILAS, CD DELICIAS, CHIH. | F10: 31267 | G10: =CONCATENATE(E10,C10,D10,F10) -> BLVD. ORTIZ MENA y C. INDIANA # 3300-D, COL. LAS AGUILAS, CD DELICIAS, CHIH.CHIHUAHUACIUDAD DELICIAS31267 | H10: 0 | I10: 2762668.7 | J10: 2310595.6 | K10: 1123289.4
A11: =+A10+1 -> 10 | B11: Cinemas Lumiere S.A. de C.V. | C11: CHIHUAHUA | D11: CIUDAD JUAREZ | E11: AVE.TECNOLOGICO # 1770 COL. FUENTES DEL VALLE, CD. JUAREZ, CHIH | F11: 32500 | G11: =CONCATENATE(E11,C11,D11,F11) -> AVE.TECNOLOGICO # 1770 COL. FUENTES DEL VALLE, CD. JUAREZ, CHIHCHIHUAHUACIUDAD JUAREZ32500 | H11: 0 | I11: 3867736.2 | J11: 3234833.9 | K11: 1596915.1
A12: =+A11+1 -> 11 | B12: Cinemas Lumiere S.A. de C.V. | C12: CHIHUAHUA | D12: CIUDAD JUAREZ | E12: PASEO TRIUNFO DE LA REPUBLICA # 5298, COL. SAN LORENZO, CD JUAREZ, CHIH | F12: 32320 | G12: =CONCATENATE(E12,C12,D12,F12) -> PASEO TRIUNFO DE LA REPUBLICA # 5298, COL. SAN LORENZO, CD JUAREZ, CHIHCHIHUAHUACIUDAD JUAREZ32320 | H12: 0 | I12: 2762668.7 | J12: 2310595.6 | K12: 949347.18
A13: =+A12+1 -> 12 | B13: Cinemas Lumiere S.A. de C.V. | C13: CHIHUAHUA | D13: CIUDAD JUAREZ | E13: EDUARDO SANDER`S # 1551, COL. EL BARREAL, CD. JUAREZ, CHIH | F13: 32040 | G13: =CONCATENATE(E13,C13,D13,F13) -> EDUARDO SANDER`S # 1551, COL. EL BARREAL, CD. JUAREZ, CHIHCHIHUAHUACIUDAD JUAREZ32040 | H13: 0 | I13: 1657601.2 | J13: 1386357.4 | K13: 685988.91
A14: =+A13+1 -> 13 | B14: Cinemex Morelia S.A. de C.V. | C14: COAHUILA | D14: MONCLOVA | E14: AV. HUEMAC ESQ. BRASIL, COL. ANAHUAC, MONCLOVA, COAH | F14: 27750 | G14: =CONCATENATE(E14,C14,D14,F14) -> AV. HUEMAC ESQ. BRASIL, COL. ANAHUAC, MONCLOVA, COAHCOAHUILAMONCLOVA27750 | H14: 0 | I14: 2210135 | J14: 1848476.5 | K14: 1072992.8
... A132: =+A131+1 -> 131 | B132: Cinemex San Antonio S.A de C.V. | C132: JALISCO | D132: TONALA | E132: PROLONGACION PABLO VALDEZ No. 350, COL. CAMICHINES I , TONALA JALISCO | F132: 45403 | G132: =CONCATENATE(E132,C132,D132,F132) -> PROLONGACION PABLO VALDEZ No. 350, COL. CAMICHINES I , TONALA JALISCOJALISCOTONALA45403 | H132: 0 | I132: 2762668.7 | J132: 2310595.6 | K132: 1371279.3
A133: =+A132+1 -> 132 | B133: Cinemex Toluca II S.A de C.V. | C133: CDMX | D133: ALVARO OBREGON | E133: AV. JAVIER BARRIOS SIERRA No. 540, COL. SANTA FE, DELEG. ALVARO OBREGON, MEXICO D.F. | F133: 01210 | G133: =CONCATENATE(E133,C133,D133,F133) -> AV. JAVIER BARRIOS SIERRA No. 540, COL. SANTA FE, DELEG. ALVARO OBREGON, MEXICO D.F.CDMXALVARO OBREGON01210 | H133: 0 | I133: 1256929.9 | J133: 1051250.4 | K133: 157875.25
A134: =+A133+1 -> 133 | B134: Cinemex San Antonio S.A de C.V. | C134: TAMAULIPAS | D134: TAMAULIPAS | E134: AV. FRANCISCO I. MADERO NO. 2000, ESQ. CALLE URSULA GALVAN, COL. INFONAVIT LA PAZ TAMAULIPAS | F134: 88990 | G134: =CONCATENATE(E134,C134,D134,F134) -> AV. FRANCISCO I. MADERO NO. 2000, ESQ. CALLE URSULA GALVAN, COL. INFONAVIT LA PAZ TAMAULIPASTAMAULIPASTAMAULIPAS88990 | H134: 0 | I134: 1933868.1 | J134: 1617416.9 | K134: 80334.75
A135: =+A134+1 -> 134 | B135: Cinemex Toluca II S.A de C.V. | C135: QUINTANA ROO | D135: CANCUN | E135: Supermanzana 248 manzana 11lt 111016 , esquina Av Kabah y Av De los tules S7N Region Benito Juarez 248 , cp 77519 Quintana Roo | F135: 77519 | G135: =CONCATENATE(E135,C135,D135,F135) -> Supermanzana 248 manzana 11lt 111016 , esquina Av Kabah y Av De los tules S7N Region Benito Juarez 248 , cp 77519 Quintana RooQUINTANA ROOCANCUN77519 | H135: 0 | I135: 2762668.7 | J135: 2310595.6 | K135: 1147040.5
A136: =+A135+1 -> 135 | B136: Cinemex San Antonio S.A de C.V. | C136: OAXACA | D136: OAXACA | E136: Monte Alban 1462 entre Monte Tacaña y Monte Carlo, Montoya Oaxaca de Juarez C.P. 68036 | F136: 68143 | G136: =CONCATENATE(E136,C136,D136,F136) -> Monte Alban 1462 entre Monte Tacaña y Monte Carlo, Montoya Oaxaca de Juarez C.P. 68036OAXACAOAXACA68143 | H136: 0 | I136: 3038935.6 | J136: 2541655.2 | K136: 1321681.3
A137: =+A136+1 -> 136 | B137: Teatro Polanco S.A. de C.V. | C137: TORREON | D137: COAHUILA | E137: Calzada Jose Vasconcelos 1955, L1010 Colonia Residencial Tecnologico Torreon Coahuila | F137: 27272 | G137: =CONCATENATE(E137,C137,D137,F137) -> Calzada Jose Vasconcelos 1955, L1010 Colonia Residencial Tecnologico Torreon CoahuilaTORREONCOAHUILA27272 | H137: 0 | I137: 3467064.8 | J137: 2899726.9 | K137: 1391537.6
A138: =+A137+1 -> 137 | B138: Cinemex San Antonio S.A de C.V. | C138: JALISCO | D138: PUERTO VALLARTA | E138: Av. Francisco Villa 526 esquina con Gonzalez Gallo Fraccionamiento Sauces Puerto Vallarta Jalisco | F138: 48328 | G138: =CONCATENATE(E138,C138,D138,F138) -> Av. Francisco Villa 526 esquina con Gonzalez Gallo Fraccionamiento Sauces Puerto Vallarta JaliscoJALISCOPUERTO VALLARTA48328 | H138: 0 | I138: 3591469.3 | J138: 3003774.3 | K138: 1568274
A139: =+A138+1 -> 138 | B139: Cinemex Toluca II S.A de C.V. | C139: ESTADO DE MEXICO | D139: ECATEPEC | E139: Av. Central manzana 632 numero 50 local D-01 Colonia Ciudad Azteca Ecatepec C.P. 55120 | F139: 55120 | G139: =CONCATENATE(E139,C139,D139,F139) -> Av. Central manzana 632 numero 50 local D-01 Colonia Ciudad Azteca Ecatepec C.P. 55120ESTADO DE MEXICOECATEPEC55120 | H139: 0 | I139: 3315202.4 | J139: 2772714.8 | K139: 1814866.8
A140: =+A139+1 -> 139 | B140: Cinemex Toluca II S.A de C.V. | C140: BAJA CALIFORNIA | D140: LA PAZ | E140: Blvd. Constituyentes de 1975 numero 4120 esquina calle algodón COLONIA SECTOR INALAPA municipio de la paz local SA 02 | F140: 23098 | G140: =CONCATENATE(E140,C140,D140,F140) -> Blvd. Constituyentes de 1975 numero 4120 esquina calle algodón COLONIA SECTOR INALAPA municipio de la paz local SA 02BAJA CALIFORNIALA PAZ23098 | H140: 0 | I140: 2876565.5 | J140: 2405854.8 | K140: 939567.29
A141: =+A140+1 -> 140 | B141: Cinemex Toluca II S.A de C.V. | C141: LEON | D141: LEON GUANAJUATO | E141: Blvd. Adolfo López Mateos No. 1702 Colonia La Martinica C.P. 37500 León Guanajuato | F141: 37500 | G141: =CONCATENATE(E141,C141,D141,F141) -> Blvd. Adolfo López Mateos No. 1702 Colonia La Martinica C.P. 37500 León GuanajuatoLEONLEON GUANAJUATO37500 | H141: 0 | I141: 2809204.5 | J141: 2349516.5 | K141: 1182667.2
A142: =+A141+1 -> 141 | B142: Cinemex WTC S.A. de C.V. | C142: TABASCO | D142: VILLAHERMOSA | E142: Periferico Carlos Pellicer y avenida Cesar Sandino Camara #1290 Colonia 1° de Mayo Municipio del Centro Villahermosa Tabasco C.P. 86190 | F142: 86190 | G142: =CONCATENATE(E142,C142,D142,F142) -> Periferico Carlos Pellicer y avenida Cesar Sandino Camara #1290 Colonia 1° de Mayo Municipio del Centro Villahermosa Tabasco C.P. 86190TABASCOVILLAHERMOSA86190 | H142: 0 | I142: 4333831 | J142: 3624658.7 | K142: 1633939
A143: =+A142+1 -> 142 | B143: Cinemex Morelia S.A. de C.V. | C143: CDMX | D143: CUAJIMALPA | E143: Av. Vasco de Quiroga 3800 Colonia SANTA FE CUAJIMALPA Delegacion Cuajimalpa | F143: 5348 | G143: =CONCATENATE(E143,C143,D143,F143) -> Av. Vasco de Quiroga 3800 Colonia SANTA FE CUAJIMALPA Delegacion CuajimalpaCDMXCUAJIMALPA5348 | H143: 0 | I143: 6769309.6 | J143: 5661604.4 | K143: 2638472.6
A144: =+A143+1 -> 143 | B144: Cinemas Lumiere S.A. de C.V. | C144: CDMX | D144: BENITO JUAREZ | E144: Av. División del norte 2462 piso 1 colonia Portales Benito Juarez Mexico D.F. C.P. 03300 | F144: 03300 | G144: =CONCATENATE(E144,C144,D144,F144) -> Av. División del norte 2462 piso 1 colonia Portales Benito Juarez Mexico D.F. C.P. 03300CDMXBENITO JUAREZ03300 | H144: 0 | I144: 2762668.7 | J144: 2310595.6 | K144: 1089758.3
A145: =+A144+1 -> 144 | B145: Cinemas Lumiere S.A. de C.V. | C145: CDMX | D145: CUAUHTEMOC | E145: Río Guadalquivir 104 Pb Mezzanine y piso 1 Colonia Cuauhtemoc , delegacion Cuauhtemoc D.F. C.P. 06500 | F145: 06500 | G145: =CONCATENATE(E145,C145,D145,F145) -> Río Guadalquivir 104 Pb Mezzanine y piso 1 Colonia Cuauhtemoc , delegacion Cuauhtemoc D.F. C.P. 06500CDMXCUAUHTEMOC06500 | H145: 0 | I145: 1151603.3 | J145: 963159.13 | K145: 435903.34
A146: =+A145+1 -> 145 | B146: Cinemas Lumiere S.A. de C.V. | C146: ESTADO DE MEXICO | D146: CHALCO | E146: Vicente Guerrero 25 Centro Chalco Estado de México C.P. 56600 | F146: 56600 | G146: =CONCATENATE(E146,C146,D146,F146) -> Vicente Guerrero 25 Centro Chalco Estado de México C.P. 56600ESTADO DE MEXICOCHALCO56600 | H146: 0 | I146: 2762668.7 | J146: 2310595.6 | K146: 1525661.7
A147: =+A146+1 -> 146 | B147: Cinemas Lumiere S.A. de C.V. | C147: ESTADO DE MEXICO | D147: COACALCO | E147: Via López Portillo 105 Local H Col. Villa de las flores Coacalco de Berriozabal estado de México C.P. 57700 | F147: 57700 | G147: =CONCATENATE(E147,C147,D147,F147) -> Via López Portillo 105 Local H Col. Villa de las flores Coacalco de Berriozabal estado de México C.P. 57700ESTADO DE MEXICOCOACALCO57700 | H147: 0 | I147: 3038935.6 | J147: 2541655.2 | K147: 1490035
A148: =+A147+1 -> 147 | B148: Cinemas Lumiere S.A. de C.V. | C148: ESTADO DE MEXICO | D148: CUAUTITLAN IZCALLI | E148: Av. Prolongacion Morelos s/n Esq. Ferrocarril Central Paseo Santa Maria Huerto Cuautitlan Izcalli Edo de Mexico C.P. 54820 | F148: 54800 | G148: =CONCATENATE(E148,C148,D148,F148) -> Av. Prolongacion Morelos s/n Esq. Ferrocarril Central Paseo Santa Maria Huerto Cuautitlan Izcalli Edo de Mexico C.P. 54820ESTADO DE MEXICOCUAUTITLAN IZCALLI54800 | H148: 0 | I148: 2762668.7 | J148: 2310595.6 | K148: 1066007.2
A149: =+A148+1 -> 148 | B149: Cinemas Lumiere S.A. de C.V. | C149: ESTADO DE MEXICO | D149: TEXCOCO | E149: Juarez 304 local 0 Centro , Texcoco Estado de México C.P. 56177 | F149: 56100 | G149: =CONCATENATE(E149,C149,D149,F149) -> Juarez 304 local 0 Centro , Texcoco Estado de México C.P. 56177ESTADO DE MEXICOTEXCOCO56100 | H149: 0 | I149: 2762668.7 | J149: 2310595.6 | K149: 948648.61
A150: =+A149+1 -> 149 | B150: Cinemas Lumiere S.A. de C.V. | C150: JALISCO | D150: ZAPOPAN | E150: Acueducto 6050 Col. Lomas del Bosque Zapopan Jalisco C.P. 45118 | F150: 45118 | G150: =CONCATENATE(E150,C150,D150,F150) -> Acueducto 6050 Col. Lomas del Bosque Zapopan Jalisco C.P. 45118JALISCOZAPOPAN45118 | H150: 0 | I150: 3937539.9 | J150: 3293215.2 | K150: 1547317.1
A151: =+A150+1 -> 150 | B151: Cinemas Lumiere S.A. de C.V. | C151: CDMX | D151: TLALPAN | E151: Av. Prolongacion Division del norte 4515 Col. Residencial Chimali , Tlalpan Distrito Federal C.P. 14370 | F151: 14370 | G151: =CONCATENATE(E151,C151,D151,F151) -> Av. Prolongacion Division del norte 4515 Col. Residencial Chimali , Tlalpan Distrito Federal C.P. 14370CDMXTLALPAN14370 | H151: 0 | I151: 2762668.7 | J151: 2310595.6 | K151: 1080677
A152: =+A151+1 -> 151 | B152: Cinemas Lumiere S.A. de C.V. | C152: CDMX | D152: TLALPAN | E152: Calzada de Tlalpan 4085 Bosques de Tetlameya Coyoacán D.F. C.P. 04730 | F152: 04730 | G152: =CONCATENATE(E152,C152,D152,F152) -> Calzada de Tlalpan 4085 Bosques de Tetlameya Coyoacán D.F. C.P. 04730CDMXTLALPAN04730 | H152: 0 | I152: 2210135 | J152: 1848476.5 | K152: 871806.68
A153: =+A152+1 -> 152 | B153: Cinemas Lumiere S.A. de C.V. | C153: PUEBLA | D153: PUEBLA | E153: Boulevard Heroes del 5 de mayo 3126 Zona Dorada huexotitla Puebla Puebla C.P. 72420 | F153: 72534 | G153: =CONCATENATE(E153,C153,D153,F153) -> Boulevard Heroes del 5 de mayo 3126 Zona Dorada huexotitla Puebla Puebla C.P. 72420PUEBLAPUEBLA72534 | H153: 0 | I153: 2762668.7 | J153: 2310595.6 | K153: 1108619.5
A154: =+A153+1 -> 153 | B154: Cinemas Lumiere S.A. de C.V. | C154: ESTADO DE MEXICO | D154: IXTAPALUCA | E154: Carretera federal Mexico-Cuautla , Plaza comercial el cortijo Km 37 Mz 1 Colonia Santa Barbara Ixtapaluca Estado de Mexico C.P. 56538 | F154: 56538 | G154: =CONCATENATE(E154,C154,D154,F154) -> Carretera federal Mexico-Cuautla , Plaza comercial el cortijo Km 37 Mz 1 Colonia Santa Barbara Ixtapaluca Estado de Mexico C.P. 56538ESTADO DE MEXICOIXTAPALUCA56538 | H154: 0 | I154: 3315202.4 | J154: 2772714.8 | K154: 1282561.7
A155: =+A154+1 -> 154 | B155: Cinemas Lumiere S.A. de C.V. | C155: ESTADO DE MEXICO | D155: TEXCOCO | E155: Carretera federal México-Texcoco Km 30.5 Colonia Santiago Cuautlalpan Plaza comercial Puerta Texcoco , Texcoco Estado de México C.P. 56370 | F155: 56255 | G155: =CONCATENATE(E155,C155,D155,F155) -> Carretera federal México-Texcoco Km 30.5 Colonia Santiago Cuautlalpan Plaza comercial Puerta Texcoco , Texcoco Estado de México C.P. 56370ESTADO DE MEXICOTEXCOCO56255 | H155: 0 | I155: 3038935.6 | J155: 2541655.2 | K155: 1114208.1
A156: =+A155+1 -> 155 | B156: Cinemas Lumiere S.A. de C.V. | C156: PACHUCA | D156: HIDALGO | E156: Blvd. Luis Donaldo Colosio Local J02 Mz 1 Fracc 1 No 2009 Ex Hacienda de Coscotitlan Plaza Comercial Pachuca de Soto Hidalgo C.P. 42064 | F156: 42064 | G156: =CONCATENATE(E156,C156,D156,F156) -> Blvd. Luis Donaldo Colosio Local J02 Mz 1 Fracc 1 No 2009 Ex Hacienda de Coscotitlan Plaza Comercial Pachuca de Soto Hidalgo C.P. 42064PACHUCAHIDALGO42064 | H156: 0 | I156: 2762668.7 | J156: 2310595.6 | K156: 1026887.7
A157: =+A156+1 -> 156 | B157: Cinemas Lumiere S.A. de C.V. | C157: ESTADO DE MEXICO | D157: CUAUTITLAN | E157: Carretera Cuautitlan Melchor Ocampo 29 esq libramiento la Joya colonia VILLAS DE CUAUTITLAN Cuautitlan Estado de México C.P. 54800 | F157: 54857 | G157: =CONCATENATE(E157,C157,D157,F157) -> Carretera Cuautitlan Melchor Ocampo 29 esq libramiento la Joya colonia VILLAS DE CUAUTITLAN Cuautitlan Estado de México C.P. 54800ESTADO DE MEXICOCUAUTITLAN54857 | H157: 0 | I157: 2762668.7 | J157: 2310595.6 | K157: 1106523.9
A158: =+A157+1 -> 157 | B158: Cinemex Morelia S.A. de C.V. | C158: CHIHUAHUA | D158: CHIHUAHUA | E158: Av. De la Juventud esquina con Av. Tecnologico Fraccionamiento paseos de Chihuahua , Chihuahua Ch. | F158: 31125 | G158: =CONCATENATE(E158,C158,D158,F158) -> Av. De la Juventud esquina con Av. Tecnologico Fraccionamiento paseos de Chihuahua , Chihuahua Ch.CHIHUAHUACHIHUAHUA31125 | H158: 0 | I158: 1381334.4 | J158: 1155297.8 | K158: 497376.89
A159: =+A158+1 -> 158 | B159: Cinemex Morelia S.A. de C.V. | C159: GUANAJUATO | D159: IRAPUATO | E159: Av. Enrique Colunga 1184 Colonia 18 de Agosto C.P. 36590 , Irapuato Guanajuato | F159: 36590 | G159: =CONCATENATE(E159,C159,D159,F159) -> Av. Enrique Colunga 1184 Colonia 18 de Agosto C.P. 36590 , Irapuato GuanajuatoGUANAJUATOIRAPUATO36590 | H159: 0 | I159: 2210135 | J159: 1848476.5 | K159: 769117.91
A160: =+A159+1 -> 159 | B160: Cinemex Morelia S.A. de C.V. | C160: DURANGO | D160: GOMEZ PALACIO | E160: Av. Periferico esquina con Av Francisco y Madero del fraccionamiento Rinconada Hamburgo Gomez Palacio Durango | F160: 35018 | G160: =CONCATENATE(E160,C160,D160,F160) -> Av. Periferico esquina con Av Francisco y Madero del fraccionamiento Rinconada Hamburgo Gomez Palacio DurangoDURANGOGOMEZ PALACIO35018 | H160: 0 | I160: 1381334.4 | J160: 1155297.8 | K160: 769117.91
A161: =+A160+1 -> 160 | B161: Cinemex Morelia S.A. de C.V. | C161: QUINTANA ROO | D161: CHETUMAL | E161: Av. Erick Paolo Martínez No. 120, Col. EL Sol, Chetumal, Quintana Roo | F161: 77026 | G161: =CONCATENATE(E161,C161,D161,F161) -> Av. Erick Paolo Martínez No. 120, Col. EL Sol, Chetumal, Quintana RooQUINTANA ROOCHETUMAL77026 | H161: 0 | I161: 2210135 | J161: 1848476.5 | K161: 510649.58
A162: =+A161+1 -> 161 | B162: Cinemex Toluca II S.A de C.V. | C162: CDMX | D162: AZCAPOTZALCO | E162: Av. El Rosario 901 y avenida de las culturas colonia unidad habitacional El Rosario delegacion Azcapotzalco México D.F. C.P. 02100 | F162: 2100 | G162: =CONCATENATE(E162,C162,D162,F162) -> Av. El Rosario 901 y avenida de las culturas colonia unidad habitacional El Rosario delegacion Azcapotzalco México D.F. C.P. 02100CDMXAZCAPOTZALCO2100 | H162: 0 | I162: 2762668.7 | J162: 2310595.6 | K162: 1047844.6
A163: =+A162+1 -> 162 | B163: Cinemex Toluca II S.A de C.V. | C163: ESTADO DE MEXICO | D163: ECATEPEC | E163: 1° de Mayo esquina con avenida central las Américas SANTA CLARA , Seccion II Ecatepec , Estado de México | F163: 55459 | G163: =CONCATENATE(E163,C163,D163,F163) -> 1° de Mayo esquina con avenida central las Américas SANTA CLARA , Seccion II Ecatepec , Estado de MéxicoESTADO DE MEXICOECATEPEC55459 | H163: 0 | I163: 3315202.4 | J163: 2772714.8 | K163: 707644.36
A164: =+A163+1 -> 163 | B164: Cinemex Toluca II S.A de C.V. | C164: ESTADO DE MEXICO | D164: TULTITLAN | E164: Av. Mexiquense S/N Lote 4 Colonia Ex Hacienda Los Portales , Tultitlan Estado de México C.P. 54910 | F164: 54910 | G164: =CONCATENATE(E164,C164,D164,F164) -> Av. Mexiquense S/N Lote 4 Colonia Ex Hacienda Los Portales , Tultitlan Estado de México C.P. 54910ESTADO DE MEXICOTULTITLAN54910 | H164: 0 | I164: 1381334.4 | J164: 1155297.8 | K164: 303874.92
... A168: =+A167+1 -> 167 | B168: Cinemex WTC S.A. de C.V. | C168: SAN LUIS POTOSI | D168: SAN LUIS POTOSI | E168: Av. Doctor Salvador Nava Martinez No. 3125 Col. Fraccionamiento Colinas del Parque S.L.P. | F168: 78294 | G168: =CONCATENATE(E168,C168,D168,F168) -> Av. Doctor Salvador Nava Martinez No. 3125 Col. Fraccionamiento Colinas del Parque S.L.P.SAN LUIS POTOSISAN LUIS POTOSI78294 | H168: 0 | I168: 3190797.9 | J168: 2668667.4 | K168: 978686.82
A169: =+A168+1 -> 168 | B169: Cinemex Toluca II S.A de C.V. | C169: CDMX | D169: BENITO JUAREZ | E169: Félix Cuevas No 374 Colonia del Valle delegación Benito Juárez C.P. 03100 México D.F. | F169: 03100 | G169: =CONCATENATE(E169,C169,D169,F169) -> Félix Cuevas No 374 Colonia del Valle delegación Benito Juárez C.P. 03100 México D.F.CDMXBENITO JUAREZ03100 | H169: 0 | I169: 2199627.2 | J169: 1839688.2 | K169: 247989.88
A170: =+A169+1 -> 169 | B170: Cinemex Morelia S.A. de C.V. | C170: ESTADO DE MEXICO | D170: TOLUCA | E170: Av. De la marina y avenida delfin dentro del desarrollo residencial turistico Marina Mazatlan C.P. 82103 SANCHEZ CELIS | F170: 82120 | G170: =CONCATENATE(E170,C170,D170,F170) -> Av. De la marina y avenida delfin dentro del desarrollo residencial turistico Marina Mazatlan C.P. 82103 SANCHEZ CELISESTADO DE MEXICOTOLUCA82120 | H170: 0 | I170: 3743331.7 | J170: 3130786.5 | K170: 1086964.1
A171: =+A170+1 -> 170 | B171: Cinemex Toluca II S.A de C.V. | C171: ESTADO DE MEXICO | D171: METEPEC | E171: Hacienda la Quemada Num 500 Norte , Barrio de San Mateo Municipio de Metepec, Estado de México C.P. 52140 | F171: 52140 | G171: =CONCATENATE(E171,C171,D171,F171) -> Hacienda la Quemada Num 500 Norte , Barrio de San Mateo Municipio de Metepec, Estado de México C.P. 52140ESTADO DE MEXICOMETEPEC52140 | H171: 0 | I171: 1381334.4 | J171: 1155297.8 | K171: 491788.38
A172: =+A171+1 -> 171 | B172: Cinemas Lumiere S.A. de C.V. | C172: VERACRUZ | D172: CORDOBA | E172: Av.1 número 3511 Col. Zona Industrial Córdoba Veracruz C.P. 94690 | F172: 94690 | G172: =CONCATENATE(E172,C172,D172,F172) -> Av.1 número 3511 Col. Zona Industrial Córdoba Veracruz C.P. 94690VERACRUZCORDOBA94690 | H172: 0 | I172: 1933868.1 | J172: 1617416.9 | K172: 648266.5
A173: =+A172+1 -> 172 | B173: Cinemex Toluca II S.A de C.V. | C173: VERACRUZ | D173: JALAPA | E173: Km. 435.3 Carretera Mexico Jalapa Veracruz s/n Col. NUEVO VERACRUZ Plaza Nuevo Veracruz | F173: 91726 | G173: =CONCATENATE(E173,C173,D173,F173) -> Km. 435.3 Carretera Mexico Jalapa Veracruz s/n Col. NUEVO VERACRUZ Plaza Nuevo VeracruzVERACRUZJALAPA91726 | H173: 0 | I173: 3467064.8 | J173: 2899726.9 | K173: 968906.94
A174: =+A173+1 -> 173 | B174: Cinemex Morelia S.A. de C.V. | C174: OAXACA | D174: SALINA CRUZ | E174: Super Carretera Transistmica numero 10 Colonia Granadillo Salina Cruz Oaxaca , Pabellon Salina Cruz | F174: 70613 | G174: =CONCATENATE(E174,C174,D174,F174) -> Super Carretera Transistmica numero 10 Colonia Granadillo Salina Cruz Oaxaca , Pabellon Salina CruzOAXACASALINA CRUZ70613 | H174: 0 | I174: 2762668.7 | J174: 2310595.6 | K174: 1072992.8
A175: =+A174+1 -> 174 | B175: Cinemex Morelia S.A. de C.V. | C175: LEON | D175: GUANAJUATO | E175: Blvd. Juan Alonso de Torres 2002 Colonia Valle del Campestre Leon Guanajuato , C.P. 37150 Plaza Mayor | F175: 37150 | G175: =CONCATENATE(E175,C175,D175,F175) -> Blvd. Juan Alonso de Torres 2002 Colonia Valle del Campestre Leon Guanajuato , C.P. 37150 Plaza MayorLEONGUANAJUATO37150 | H175: 0 | I175: 4572132.3 | J175: 3823965.2 | K175: 1390140.5
A176: =+A175+1 -> 175 | B176: Teatro Polanco S.A. de C.V. | C176: YUCATAN | D176: MERIDA | E176: AV. JACINTO CANEK Y CALLE 128 NO 277 COL YUCALTEPEC MERIDA YUCATÁN | F176: 97238 | G176: =CONCATENATE(E176,C176,D176,F176) -> AV. JACINTO CANEK Y CALLE 128 NO 277 COL YUCALTEPEC MERIDA YUCATÁNYUCATANMERIDA97238 | H176: 0 | I176: 3315202.4 | J176: 2772714.8 | K176: 1269987.6
A177: =+A176+1 -> 176 | B177: Cinemex Morelia S.A. de C.V. | C177: MICHOACAN | D177: LÁZARO CÁRDENAS | E177: AV. TULIPANES #548 COLONIA UNIDAD 7.4 Siderúrgica Lázaro Cárdenas Las Truchas MICHOACÁN | F177: 60950 | G177: =CONCATENATE(E177,C177,D177,F177) -> AV. TULIPANES #548 COLONIA UNIDAD 7.4 Siderúrgica Lázaro Cárdenas Las Truchas MICHOACÁNMICHOACANLÁZARO CÁRDENAS60950 | H177: 0 | I177: 1657601.2 | J177: 1386357.4 | K177: 728601.25
A178: =+A177+1 -> 177 | B178: Cinemex Morelia S.A. de C.V. | C178: MICHOACAN | D178: MORELIA | E178: Paseo de la República No. 3380 El Lago I | F178: 58115 | G178: =CONCATENATE(E178,C178,D178,F178) -> Paseo de la República No. 3380 El Lago IMICHOACANMORELIA58115 | H178: 0 | I178: 2762668.7 | J178: 2310595.6 | K178: 1098839.7
A179: =+A178+1 -> 178 | B179: Cinemex WTC S.A. de C.V. | C179: Chihuahua | D179: Chihuahua | E179: Hacienda Esperanza y Periférico Juventud 7301 Chihuahua Chihuahua RINCON DE LAS LOMAS I | F179: 31216 | G179: =CONCATENATE(E179,C179,D179,F179) -> Hacienda Esperanza y Periférico Juventud 7301 Chihuahua Chihuahua RINCON DE LAS LOMAS IChihuahuaChihuahua31216 | H179: 0 | I179: 3467064.8 | J179: 2899726.9 | K179: 1740819.1
A180: =+A179+1 -> 179 | B180: Cinemex WTC S.A. de C.V. | C180: Sonora | D180: Hermosillo | E180: Blvd. Colosio esquina periferico poniente s/n Col. Villa Satelite Hermosillo Sonora | F180: 83200 | G180: =CONCATENATE(E180,C180,D180,F180) -> Blvd. Colosio esquina periferico poniente s/n Col. Villa Satelite Hermosillo SonoraSonoraHermosillo83200 | H180: 0 | I180: 2838599.9 | J180: 2374101.7 | K180: 1425767.2
A181: =+A180+1 -> 180 | B181: Cinemex WTC S.A. de C.V. | C181: CDMX | D181: Tlalpan | E181: Av. Canal de Miramontes No 3163 Col. Vergel Coapa Del. Tlalpan Mexico Distrito Federal | F181: 14320 | G181: =CONCATENATE(E181,C181,D181,F181) -> Av. Canal de Miramontes No 3163 Col. Vergel Coapa Del. Tlalpan Mexico Distrito FederalCDMXTlalpan14320 | H181: 0 | I181: 3038935.6 | J181: 2541655.2 | K181: 2180215.3
A182: =+A181+1 -> 181 | B182: Operadora de Cinemas S.A. de C.V. | C182: CDMX | D182: Tlalpan | E182: Colonia Contry Club lateral de Rio Churubusco Esq. Canal de Miramontes. CAMPESTRE CHURUBUSCO | F182: 04200 | G182: =CONCATENATE(E182,C182,D182,F182) -> Colonia Contry Club lateral de Rio Churubusco Esq. Canal de Miramontes. CAMPESTRE CHURUBUSCOCDMXTlalpan04200 | H182: 0 | I182: 3315202.4 | J182: 2772714.8 | K182: 1625556.2
A183: =+A182+1 -> 182 | B183: Cinemex WTC S.A. de C.V. | C183: Irapuato | D183: Guanajuato | E183: Avenida Arboledas No. 1200, Colonia San Miguelito, 36557 Irapuato, Guanajuato | F183: 36557 | G183: =CONCATENATE(E183,C183,D183,F183) -> Avenida Arboledas No. 1200, Colonia San Miguelito, 36557 Irapuato, GuanajuatoIrapuatoGuanajuato36557 | H183: 0 | I183: 2762668.7 | J183: 2310595.6 | K183: 1254619.2
A184: =+A183+1 -> 183 | B184: Cinemex WTC S.A. de C.V. | C184: Chihuahua | D184: Cd. Juarez | E184: Avenida Ejército Nacional No. 7695, Colonia El Marquis, 32530 Cd. Juárez, Chihuahua | F184: 32536 | G184: =CONCATENATE(E184,C184,D184,F184) -> Avenida Ejército Nacional No. 7695, Colonia El Marquis, 32530 Cd. Juárez, ChihuahuaChihuahuaCd. Juarez32536 | H184: 0 | I184: 2762668.7 | J184: 2310595.6 | K184: 1315394.2
A185: =+A184+1 -> 184 | B185: Cinemex WTC S.A. de C.V. | C185: Mexicali | D185: Baja California | E185: Boulevard Adolfo López Mateos No. 856, Colonia Bellavista, 21150 Mexicali, Baja California | F185: 21150 | G185: =CONCATENATE(E185,C185,D185,F185) -> Boulevard Adolfo López Mateos No. 856, Colonia Bellavista, 21150 Mexicali, Baja CaliforniaMexicaliBaja California21150 | H185: 0 | I185: 1933868.1 | J185: 1617416.9 | K185: 1161710.3
A186: =+A185+1 -> 185 | B186: Cinemex WTC S.A. de C.V. | C186: CDMX | D186: Miguel Hidalgo | E186: Bosques de Duraznos No.39 Col Bosques de Las Lomas | F186: 11700 | G186: =CONCATENATE(E186,C186,D186,F186) -> Bosques de Duraznos No.39 Col Bosques de Las LomasCDMXMiguel Hidalgo11700 | H186: 0 | I186: 3142324.6 | J186: 2628126 | K186: 1209212.6
A187: =+A186+1 -> 186 | B187: Cinemex WTC S.A. de C.V. | C187: Coahuila | D187: Saltillo | E187: Periférico Luis Echeverría No. 851, Sub-ancla 5, Colonia República Norte, 25280 Saltillo, Coahuila | F187: 25280 | G187: =CONCATENATE(E187,C187,D187,F187) -> Periférico Luis Echeverría No. 851, Sub-ancla 5, Colonia República Norte, 25280 Saltillo, CoahuilaCoahuilaSaltillo25280 | H187: 0 | I187: 1381334.4 | J187: 1155297.8 | K187: 1068102.9
A188: =+A187+1 -> 187 | B188: Cinemex WTC S.A. de C.V. | C188: Baja California | D188: Tijuana | E188: Via Rápida Poniente No. 15035,Río Tijuana 3a etapa, 22610 Tijuana, Baja California | F188: 22226 | G188: =CONCATENATE(E188,C188,D188,F188) -> Via Rápida Poniente No. 15035,Río Tijuana 3a etapa, 22610 Tijuana, Baja CaliforniaBaja CaliforniaTijuana22226 | H188: 0 | I188: 3315202.4 | J188: 2772714.8 | K188: 2127823
A189: =+A188+1 -> 188 | B189: Cinemex WTC S.A. de C.V. | C189: Chiapas | D189: Tuxtla Gutierrez | E189: Boulevard Dr.Belisario Domínguez #1861 BELISARIO DOMINGUEZ, 29060 Tuxtla Gtz. Chiapas | F189: 29059 | G189: =CONCATENATE(E189,C189,D189,F189) -> Boulevard Dr.Belisario Domínguez #1861 BELISARIO DOMINGUEZ, 29060 Tuxtla Gtz. ChiapasChiapasTuxtla Gutierrez29059 | H189: 0 | I189: 2210135 | J189: 1848476.5 | K189: 1315394.2
A190: =+A189+1 -> 189 | B190: Cinemex WTC S.A. de C.V. | C190: CDMX | D190: Cuauhtemoc | E190: Paseo de la Reforma #222, Col. Juárez, 06600, México, Distrito Federal | F190: 06600 | G190: =CONCATENATE(E190,C190,D190,F190) -> Paseo de la Reforma #222, Col. Juárez, 06600, México, Distrito FederalCDMXCuauhtemoc06600 | H190: 0 | I190: 3038935.6 | J190: 2541655.2 | K190: 1517278.9
A191: =+A190+1 -> 190 | B191: Cinemex WTC S.A. de C.V. | C191: Jalisco | D191: Puerto Vallarta | E191: Av. De los Tules #178 Interior plaza Caracol. Fracc. Las Glorias, 48310, Puerto Vallarta Jalisco | F191: 48333 | G191: =CONCATENATE(E191,C191,D191,F191) -> Av. De los Tules #178 Interior plaza Caracol. Fracc. Las Glorias, 48310, Puerto Vallarta JaliscoJaliscoPuerto Vallarta48333 | H191: 0 | I191: 2210135 | J191: 1848476.5 | K191: 1372676.4
A192: =+A191+1 -> 191 | B192: Cinemex WTC S.A. de C.V. | C192: Puebla | D192: Puebla | E192: 39 Poniente No. 3515, 2o piso. Centro Comercial Triángulo Las Animas, Col. Las Animas C.P. 72400, Puebla,Puebla | F192: 72400 | G192: =CONCATENATE(E192,C192,D192,F192) -> 39 Poniente No. 3515, 2o piso. Centro Comercial Triángulo Las Animas, Col. Las Animas C.P. 72400, Puebla,Puebla PueblaPuebla72400 | H192: 0 | I192: 2762668.7 | J192: 2310595.6 | K192: 1521470.3
A193: =+A192+1 -> 192 | B193: Cinemex WTC S.A. de C.V. | C193: CDMX | D193: Iztapalapa | E193: Av. Canal de Tezontle 1512, Col. Dr. Alfonso Ortíz Tirado. Del. Iztapalapa, 09020 México Distrito Federal. | F193: 09020 | G193: =CONCATENATE(E193,C193,D193,F193) -> Av. Canal de Tezontle 1512, Col. Dr. Alfonso Ortíz Tirado. Del. Iztapalapa, 09020 México Distrito Federal.CDMXIztapalapa09020 | H193: 0 | I193: 2762668.7 | J193: 2310595.6 | K193: 1595518
A194: =+A193+1 -> 193 | B194: Cinemex WTC S.A. de C.V. | C194: Baja California | D194: Tijuana | E194: Boulevard Sánchez Taboada No. 4555, Colonia Zona URBANA del Río, 22320 Tijuana, Baja California | F194: 22010 | G194: =CONCATENATE(E194,C194,D194,F194) -> Boulevard Sánchez Taboada No. 4555, Colonia Zona URBANA del Río, 22320 Tijuana, Baja CaliforniaBaja CaliforniaTijuana22010 | H194: 0 | I194: 2762668.7 | J194: 2310595.6 | K194: 1508896.2
A195: =+A194+1 -> 194 | B195: Cinemex WTC S.A. de C.V. | C195: CDMX | D195: Iztapalapa | E195: Avenida Canal del Tezontle No. 1520, Colonia Dr. Alfonso Ortíz Tirado, 09020 México, Distrito Federal | F195: 09020 | G195: =CONCATENATE(E195,C195,D195,F195) -> Avenida Canal del Tezontle No. 1520, Colonia Dr. Alfonso Ortíz Tirado, 09020 México, Distrito FederalCDMXIztapalapa09020 | H195: 0 | I195: 2762668.7 | J195: 2310595.6 | K195: 1750599
A196: =+A195+1 -> 195 | B196: Cinemex WTC S.A. de C.V. | C196: Sonora | D196: Hermosillo | E196: Boulevard José López Portillo y Juárez No. 549, Colonia Bachoco, 83148 Hermosillo, Sonora | F196: 83148 | G196: =CONCATENATE(E196,C196,D196,F196) -> Boulevard José López Portillo y Juárez No. 549, Colonia Bachoco, 83148 Hermosillo, SonoraSonoraHermosillo83148 | H196: 0 | I196: 2486401.8 | J196: 2079536.1 | K196: 1886818.8
A197: =+A196+1 -> 196 | B197: Cinemex WTC S.A. de C.V. | C197: Queretaro | D197: Queretaro | E197: Boulevard Bernardo Quintana No. 502, Colonia Centro Sur, 76090 Querétaro, Querétaro | F197: 76090 | G197: =CONCATENATE(E197,C197,D197,F197) -> Boulevard Bernardo Quintana No. 502, Colonia Centro Sur, 76090 Querétaro, QuerétaroQueretaroQueretaro76090 | H197: 0 | I197: 3315202.4 | J197: 2772714.8 | K197: 1387346.2
A198: =+A197+1 -> 197 | B198: Cinemex WTC S.A. de C.V. | C198: CDMX | D198: Gustavo A. Madero | E198: Calle Colector 13 # 280, Col. Magdalena de las Salinas. G.A. Madero, 07760 México, Distrito Federal | F198: 07760 | G198: =CONCATENATE(E198,C198,D198,F198) -> Calle Colector 13 # 280, Col. Magdalena de las Salinas. G.A. Madero, 07760 México, Distrito FederalCDMXGustavo A. Madero07760 | H198: 0 | I198: 3038935.6 | J198: 2541655.2 | K198: 1469078.1
A199: =+A198+1 -> 198 | B199: Cinemex WTC S.A. de C.V. | C199: Quintana Roo | D199: Cancun | E199: Lote 18-10, Manzana 52, Sección A del Boulevard Kukulcán COL ZONA HOTELERA, Benito Juárez, Cancún, Estado de Quintana Roo | F199: 77500 | G199: =CONCATENATE(E199,C199,D199,F199) -> Lote 18-10, Manzana 52, Sección A del Boulevard Kukulcán COL ZONA HOTELERA, Benito Juárez, Cancún, Estado de Quintana RooQuintana RooCancun77500 | H199: 0 | I199: 1657601.2 | J199: 1386357.4 | K199: 868313.86
A200: =+A199+1 -> 199 | B200: Cinemex WTC S.A. de C.V. | C200: CDMX | D200: Tlahuac | E200: Avenida Tláhuac No. 5662, Colonia San Lorenzo Tezonco, 09790 México, Distrito Federal | F200: 09790 | G200: =CONCATENATE(E200,C200,D200,F200) -> Avenida Tláhuac No. 5662, Colonia San Lorenzo Tezonco, 09790 México, Distrito FederalCDMXTlahuac09790 | H200: 0 | I200: 2762668.7 | J200: 2310595.6 | K200: 1608790.7
A201: =+A200+1 -> 200 | B201: Cinemex WTC S.A. de C.V. | C201: Estado de México | D201: Naucalpan | E201: Colina de la Paz No. 25, Col. Fraccionamiento Residencial Boulevares LOMAS VERDES 1A SECCION, 53120 Naucalpan Edo. de México | F201: 53120 | G201: =CONCATENATE(E201,C201,D201,F201) -> Colina de la Paz No. 25, Col. Fraccionamiento Residencial Boulevares LOMAS VERDES 1A SECCION, 53120 Naucalpan Edo. de MéxicoEstado de MéxicoNaucalpan53120 | H201: 0 | I201: 2876565.5 | J201: 2405854.8 | K201: 1418083
A202: =+A201+1 -> 201 | B202: Cinemex WTC S.A. de C.V. | C202: Yucatán | D202: Mérida | E202: Calle 30 No. 185 Manzana 474 Sección 16, Col. San Ramón Norte, 97117 Mérida Yucatán | F202: 97117 | G202: =CONCATENATE(E202,C202,D202,F202) -> Calle 30 No. 185 Manzana 474 Sección 16, Col. San Ramón Norte, 97117 Mérida YucatánYucatánMérida97117 | H202: 0 | I202: 2286066.1 | J202: 1911982.6 | K202: 1187557.2
A203: =+A202+1 -> 202 | B203: Cinemex Toluca II S.A de C.V. | C203: CDMX | D203: AZCAPOTZALCO | E203: Avenida Egipto 142 Colonia Clavería Delegacion Azcapotzalco México D.F. | F203: 02080 | G203: =CONCATENATE(E203,C203,D203,F203) -> Avenida Egipto 142 Colonia Clavería Delegacion Azcapotzalco México D.F.CDMXAZCAPOTZALCO02080 | H203: 0 | I203: 1657601.2 | J203: 1386357.4 | K203: 713931.43
A204: =+A203+1 -> 203 | B204: Cinemas Lumiere S.A. de C.V. | C204: VERACRUZ | D204: MINATITLAN | E204: Blvd Instituto Tecnologicos No 24 Col Insurgentes Norte Minatitlan Veracruz | F204: 96710 | G204: =CONCATENATE(E204,C204,D204,F204) -> Blvd Instituto Tecnologicos No 24 Col Insurgentes Norte Minatitlan Veracruz VERACRUZMINATITLAN96710 | H204: 0 | I204: 1933868.1 | J204: 1617416.9 | K204: 716027.12
A205: =+A204+1 -> 204 | B205: Cinemex Toluca II S.A de C.V. | C205: MORELOS | D205: CUERNAVACA | E205: Av. Rio Balsas S/N Calzada Leandro Valle y Vicente Guerrero Colonia Lomas de la Selva Cuernavaca Morelos | F205: 62400 | G205: =CONCATENATE(E205,C205,D205,F205) -> Av. Rio Balsas S/N Calzada Leandro Valle y Vicente Guerrero Colonia Lomas de la Selva Cuernavaca MorelosMORELOSCUERNAVACA62400 | H205: 0 | I205: 4687044.5 | J205: 3920073.5 | K205: 1616474.9
A206: =+A205+1 -> 205 | B206: Cinemex Toluca II S.A de C.V. | C206: BAJA CALIFORNIA | D206: TIJUANA | E206: Paseo Heroes No. 9111 Manzana 075 Esquina Manuel M. Marquez Tijuana Baja California | F206: 22320 | G206: =CONCATENATE(E206,C206,D206,F206) -> Paseo Heroes No. 9111 Manzana 075 Esquina Manuel M. Marquez Tijuana Baja CaliforniaBAJA CALIFORNIATIJUANA22320 | H206: 0 | I206: 1933868.1 | J206: 1617416.9 | K206: 655950.7
A207: =+A206+1 -> 206 | B207: Cinemex Toluca II S.A de C.V. | C207: OAXACA | D207: OAXACA | E207: Carretera internacional Cristobal Colon No. 2002 Municipio de Santa Lucía del Camino Oaxaca | F207: 71288 | G207: =CONCATENATE(E207,C207,D207,F207) -> Carretera internacional Cristobal Colon No. 2002 Municipio de Santa Lucía del Camino OaxacaOAXACAOAXACA71288 | H207: 0 | I207: 3038935.6 | J207: 2541655.2 | K207: 1005930.8
A208: =+A207+1 -> 207 | B208: Cinemex Toluca II S.A de C.V. | C208: PUEBLA | D208: PUEBLA | E208: Blvd. Hermanos Serdán No. 630 Col. Pino Suarez Puebla Puebla , C.P. 72020 | F208: 72020 | G208: =CONCATENATE(E208,C208,D208,F208) -> Blvd. Hermanos Serdán No. 630 Col. Pino Suarez Puebla Puebla , C.P. 72020PUEBLAPUEBLA72020 | H208: 0 | I208: 1933868.1 | J208: 1617416.9 | K208: 724409.88
A209: =+A208+1 -> 208 | B209: Cinemas Lumiere S.A. de C.V. | C209: VERACRUZ | D209: VERACRUZ | E209: Predio Mocambo , Collado o Boticaria , Boca del Río , Veracruz | F209: 94293 | G209: =CONCATENATE(E209,C209,D209,F209) -> Predio Mocambo , Collado o Boticaria , Boca del Río , VeracruzVERACRUZVERACRUZ94293 | H209: 0 | I209: 3038935.6 | J209: 2541655.2 | K209: 1301422.9
A210: =+A209+1 -> 209 | B210: Cinemex San Antonio S.A de C.V. | C210: PUEBLA | D210: PUEBLA | E210: Paseo Sinfonía no. 4 Grand Boulevard Lomas no. 301 Lomas de Angelopolis II Periferico Ecologico , San Andrés Cholula Puebla C.P. 17002 | F210: 17002 | G210: =CONCATENATE(E210,C210,D210,F210) -> Paseo Sinfonía no. 4 Grand Boulevard Lomas no. 301 Lomas de Angelopolis II Periferico Ecologico , San Andrés Cholula Puebla C.P. 17002PUEBLAPUEBLA17002 | H210: 0 | I210: 2199627.2 | J210: 1839688.2 | K210: 245894.19
A211: =+A210+1 -> 210 | B211: Cinemex Toluca II S.A de C.V. | C211: QUINTANA ROO | D211: CANCUN | E211: Boulevard Cumbres esquina con Luis Donaldo Colosio sm 310 mz 109 lt 01 Residencial Cumbres Cancun Quintana Roo , C.P. 77580 | F211: 77580 | G211: =CONCATENATE(E211,C211,D211,F211) -> Boulevard Cumbres esquina con Luis Donaldo Colosio sm 310 mz 109 lt 01 Residencial Cumbres Cancun Quintana Roo , C.P. 77580QUINTANA ROOCANCUN77580 | H211: 0 | I211: 2303206.6 | J211: 1926318.3 | K211: 578410.2
A212: =+A211+1 -> 211 | B212: Cinemex Toluca II S.A de C.V. | C212: Chiapas | D212: TAPACHULA | E212: Avenida de la Juventud Esquina con Boulevard Díaz Ordaz O. 182 Colonia Coapante Tapachula Chiapas | F212: 30740 | G212: =CONCATENATE(E212,C212,D212,F212) -> Avenida de la Juventud Esquina con Boulevard Díaz Ordaz O. 182 Colonia Coapante Tapachula ChiapasChiapasTAPACHULA30740 | H212: 0 | I212: 1933868.1 | J212: 1617416.9 | K212: 716027.12
A213: =+A212+1 -> 212 | B213: Cinemex Toluca II S.A de C.V. | C213: QUINTANA ROO | D213: CANCUN | E213: Avenida 20 de Noviembre Manzana 1 Lote 158 04 Los Héroes Cancun , Municipio de Benito Juarez Quintana Roo | F213: 77518 | G213: =CONCATENATE(E213,C213,D213,F213) -> Avenida 20 de Noviembre Manzana 1 Lote 158 04 Los Héroes Cancun , Municipio de Benito Juarez Quintana RooQUINTANA ROOCANCUN77518 | H213: 0 | I213: 1657601.2 | J213: 1386357.4 | K213: 711835.74
A214: =+A213+1 -> 213 | B214: Cinemex Toluca II S.A de C.V. | C214: ESTADO DE MEXICO | D214: TECAMAC | E214: Manzana 126 Lote 1 Sector 39 , Seccion III Los Heroes Ejido de Santo Tomas Chiconautla , Tecámac Estado de México | F214: 55764 | G214: =CONCATENATE(E214,C214,D214,F214) -> Manzana 126 Lote 1 Sector 39 , Seccion III Los Heroes Ejido de Santo Tomas Chiconautla , Tecámac Estado de MéxicoESTADO DE MEXICOTECAMAC55764 | H214: 0 | I214: 1381334.4 | J214: 1155297.8 | K214: 370238.41
A215: =+A214+1 -> 214 | B215: Cinemex Toluca II S.A de C.V. | C215: ESTADO DE MEXICO | D215: TLALNEPANTLA | E215: Sor Juana Ines de la Cruz No. 280 esquina vía Dr. Gustavo Baz Tlalnepantla Estado de México | F215: 54000 | G215: =CONCATENATE(E215,C215,D215,F215) -> Sor Juana Ines de la Cruz No. 280 esquina vía Dr. Gustavo Baz Tlalnepantla Estado de MéxicoESTADO DE MEXICOTLALNEPANTLA54000 | H215: 0 | I215: 5527479 | J215: 4622982.5 | K215: 1453709.7
... A221: =+A220+1 -> 220 | B221: Cinemex WTC S.A. de C.V. | C221: GUANAJUATO | D221: SALAMANCA | E221: Macrolote Comercial del Fraccionamiento Residencial Las Glorias , Salamanca Guanajuato | F221: 36766 | G221: =CONCATENATE(E221,C221,D221,F221) -> Macrolote Comercial del Fraccionamiento Residencial Las Glorias , Salamanca GuanajuatoGUANAJUATOSALAMANCA36766 | H221: 0 | I221: 3361738.3 | J221: 2811635.6 | K221: 1300724.4
A222: =+A221+1 -> 221 | B222: Cinemex Toluca II S.A de C.V. | C222: CDMX | D222: Iztapalapa | E222: Ignacio Zaragoza No 1433 y 2717 esquina con calle Guadalupe Victoria , Colonia Tepalcates C.P. 09210 Delegación Iztapalapa México D.F. | F222: 09210 | G222: =CONCATENATE(E222,C222,D222,F222) -> Ignacio Zaragoza No 1433 y 2717 esquina con calle Guadalupe Victoria , Colonia Tepalcates C.P. 09210 Delegación Iztapalapa México D.F.CDMXIztapalapa09210 | H222: 0 | I222: 1933868.1 | J222: 1617416.9 | K222: 539989.23
A223: =+A222+1 -> 222 | B223: Cinemex WTC S.A. de C.V. | C223: SINALOA | D223: LOS MOCHIS | E223: Calle Gabriel Leyva #700 sur , C.P. 81200 en la ciudad de los Mochis Sinaloa | F223: 81200 | G223: =CONCATENATE(E223,C223,D223,F223) -> Calle Gabriel Leyva #700 sur , C.P. 81200 en la ciudad de los Mochis SinaloaSINALOALOS MOCHIS81200 | H223: 0 | I223: 1381334.4 | J223: 1155297.8 | K223: 414247.88
A224: =+A223+1 -> 223 | B224: Cinemex Toluca II S.A de C.V. | C224: JALISCO | D224: GUADALAJARA | E224: Av. López Mateos Sur No.1710, Zona El Palomar, C.P. 45645, Guadalajara, Jalisco. | F224: 45645 | G224: =CONCATENATE(E224,C224,D224,F224) -> Av. López Mateos Sur No.1710, Zona El Palomar, C.P. 45645, Guadalajara, Jalisco.JALISCOGUADALAJARA45645 | H224: 0 | I224: 1933868.1 | J224: 1617416.9 | K224: 523922.28
A225: =+A224+1 -> 224 | B225: Cinemex San Antonio S.A de C.V. | C225: Nuevo Leon | D225: Monterrey | E225: Carretera Nacional No. 500-1 al 500-12 en Monterrey N.L. | F225: 64989 | G225: =CONCATENATE(E225,C225,D225,F225) -> Carretera Nacional No. 500-1 al 500-12 en Monterrey N.L.Nuevo LeonMonterrey64989 | H225: 0 | I225: 4423839 | J225: 3699938 | K225: 914419.02
...

Sheet COTIZACIÓN M.N.
B4: GRUPO MEXICANO DE SEGUROS, S.A.DE C.V.
B5: COTIZACIÓN MÚLTIPLE EMPRESARIAL
B7: DATOS GENERALES
B8: Asegurado | C8: OPERADORA DE CINEMAS SA DE CV
B9: R.F.C.: | C9: PENDIENTE
B10: Dirección Fiscal:
B11: Dirección del Riesgo: | C11: =C10 -> 0 | F11: C.P. | G11: 77500
B12: Giro: | C12: HOTEL CON ESTACIONAMIENTO, LOCALES COMERCIALES, SERVICIOS RECREATIVOS Y LO RELACIONADO AL GIRO DEL ASEGURADO | F12: No. Días | G12: =D16-C16 -> 366
F13: Zona TEV AMIS | G13: A
B14: Tipos Constructivos: | C14: CONSTRUCCION MACIZA, MUROS, TECHOS Y ENTREPISOS DE CONCRETO, CONSTA DE P.B. Y 12 PISOS ALTOS | F14: Coaseguro T.E.V. | G14: 0
B15: Protecciones: | C15: Minimo debera tener extintores suficientes uno cada 15 Mts. Del otro, con recarga vigente, libres de obstaculos de acuerdo a la Norma Oficial Mexicana, vigilancia las 24 Hrs. Y los 365 días al año, en caso de que algunas de las medidas anteriores, no exista y/o se encuentre fuera de servicio, GMX Seguros quedara liberada de cualquier Responsabilidad en caso de siniestro Indemnizable. | F15: % de Remoción Esc. | G15: 0.2
B16: Vigencia | C16: 45107 | D16: 45473 | F16: Inflación | G16: 0
B17: Siniestralidad | C17: SIN SINIESTROS EN LOS ULTIMOS 5 AÑOS | F17: Zona F.H.M. ALFA | G17: A1PS
B18: Moneda: | C18: DOLARES | D18: USD | F18: Coaseguro F.H.M. | G18: 0
B19: Agente: | C19: MARSH | F19: Coaseguro Convenido para Edificio y/o Contenidos | G19: 1
F20: =F97 -> 1088395.2 | H20: 1088395 | N20: ='Hoja Contable'!N413 -> 0.080011672
B21: DETALLE DE COBERTURAS Y PRIMAS
B22: Sección | C22: Ramo | D22: valores al 100% | E22: Cuota al 100% | F22: Prima al 100% | G22: Comisión %
B24: EDIFICIO | C24: Incendio y/o Rayo | D24: ='Ubicaciones total (2)'!H366 -> 155549.7 | E24: 0.236781 | F24: =(D24*E24/1000)/365*$G$12 -> 36.932121 | G24: 0.25 | H24: =G24*F24 -> 9.2330302
C25: Extensión de Cubierta | D25: =D24 -> 155549.7 | E25: =+E24*10% -> 0.0236781 | F25: =(D25*E25/1000)/365*$G$12 -> 3.6932121 | G25: =$G$24 -> 0.25 | H25: =G25*F25 -> 0.92330302
B26: 1 | C26: Todo Riesgo | D26: =D24*B26 -> 155549.7 | E26: =(E24*20%)*B26 -> 0.0473562 | F26: =(D26*E26/1000)/365*$G$12 -> 7.3864242 | G26: =$G$24 -> 0.25 | H26: =G26*F26 -> 1.846606
B27: =G16 -> 0 | C27: Inflación | D27: =D24*B27 -> 0 | E27: =(E24+E25+E26)*35% -> 0.10773536 | F27: =(D27*E27/1000)/365*$G$12 -> 0 | G27: =G24 -> 0.25 | H27: =G27*F27 -> 0
B28: =100%-G18 -> 1 | C28: F.H.M. | D28: =(D24/G19)*B28 -> 155549.7 | E28: 0.25 | F28: =(D24*E28/1000)/365*$G$12 -> 38.993966 | G28: 0.05 | H28: =G28*F28 -> 1.9496983
B29: =B27 -> 0 | C29: Inflación | D29: =(D28)*B27 -> 0 | E29: =E28*35% -> 0.0875 | F29: =(D29*E29/1000)/365*$G$12 -> 0 | G29: =+G28 -> 0.05 | H29: =G29*F29 -> 0
B30: =100%-G14 -> 1 | C30: T.E.V. | D30: =(D24/G19)*B30 -> 155549.7 | E30: 0.4 | F30: =(D30*E30/1000)/365*$G$12 -> 62.390345 | G30: =G28 -> 0.05 | H30: =G30*F30 -> 3.1195173
B31: =B27 -> 0 | C31: =C29 -> Inflación | D31: =D30*B27 -> 0 | E31: =E30*35% -> 0.14 | F31: =(D31*E31/1000)/365*$G$12 -> 0 | G31: =G28 -> 0.05 | H31: =G31*F31 -> 0
B33: CONTENIDOS | C33: Incendio | D33: ='Ubicaciones total (2)'!I366 -> 8.6921645e+08 | E33: =E24 -> 0.236781 | F33: =(D33*E33/1000)/365*$G$12 -> 206377.81 | G33: =$G$24 -> 0.25 | H33: =G33*F33 -> 51594.454
C34: =C25 -> Extensión de Cubierta | D34: =D33 -> 8.6921645e+08 | E34: =E25 -> 0.0236781 | F34: =(D34*E34/1000)/365*$G$12 -> 20637.781 | G34: =$G$24 -> 0.25 | H34: =G34*F34 -> 5159.4454
C35: Todo Riesgo | D35: =D33*B26 -> 8.6921645e+08 | E35: =+E26 -> 0.0473562 | F35: =(D35*E35/1000)/365*$G$12 -> 41275.563 | G35: =$G$24 -> 0.25 | H35: =G35*F35 -> 10318.891
B36: =G16 -> 0 | C36: =C27 -> Inflación | D36: =D33*B36 -> 0 | E36: =(E33+E34+E35)*35% -> 0.10773536 | F36: =(D36*E36/1000)/365*$G$12 -> 0 | G36: =G24 -> 0.25 | H36: =G36*F36 -> 0
B37: =100%-G18 -> 1 | C37: =C28 -> F.H.M. | D37: =(D33/G19)*B37 -> 8.6921645e+08 | E37: =E28 -> 0.25 | F37: =(D33*E37/1000)/365*$G$12 -> 217899.47 | G37: =$G$28 -> 0.05 | H37: =G37*F37 -> 10894.973
B38: =B36 -> 0 | C38: =C29 -> Inflación | D38: =(D33/G19)*B36 -> 0 | E38: =E37*35% -> 0.0875 | F38: =(D38*E38/1000)/365*$G$12 -> 0 | G38: =G28 -> 0.05 | H38: =G38*F38 -> 0
B39: =B30 -> 1 | C39: =C30 -> T.E.V. | D39: =(D33/G19)*B30 -> 8.6921645e+08 | E39: =E30*0.5 -> 0.2 | F39: =(D39*E39/1000)/365*$G$12 -> 174319.57 | G39: =$G$28 -> 0.05 | H39: =G39*F39 -> 8715.9787
B40: =B36 -> 0 | C40: =C29 -> Inflación | D40: =D39*B36 -> 0 | E40: =E39*35% -> 0.07 | F40: =(D40*E40/1000)/365*$G$12 -> 0 | G40: =$G$28 -> 0.05 | H40: =G40*F40 -> 0
B42: PERDIDAS CONSECUENCIALES | D42: ='Ubicaciones total (2)'!K366 -> 3.2429902e+08 | E42: =(E24+E25+E26)*80% -> 0.24625224 | F42: =(D42*E42/1000)/365*$G$12 -> 80078.153 | G42: =G24 -> 0.25 | H42: =G42*F42 -> 20019.538
B43: FHM ( Gastos Fijos y Salarios) Opera como Sublimite | D43: =D42 -> 3.2429902e+08 | E43: =E28*80% -> 0.2 | F43: =(D43*E43/1000)/365*$G$12 -> 65037.502 | G43: =$G$28 -> 0.05 | H43: =G43*F43 -> 3251.8751 | K43: 0.8 | M43: 0.7
B44: TEV ( Gastos Fijos y Salarios) Opera como Sublimite | D44: =+D43 -> 3.2429902e+08 | E44: =(E30*B39)*80% -> 0.32 | F44: =(D44*E44/1000)/365*$G$12 -> 104060 | G44: =$G$28 -> 0.05 | H44: =G44*F44 -> 5203.0002 | K44: 1 | M44: 0.64
B46: VALORES TOTALES | D46: =SUM(D24+D33+D42+D27+D36) -> 1.193671e+09
B47: LIMITE MÁXIMO DE RESPONSABILIDAD | D47: 20000000
D49: DETALLE DE PRIMAS
D50: Total | E50: Incendio | F50: =+F24+F33+F25+F34+F27+F36 -> 227056.22
D51: Total | E51: Hidro | F51: =+F28+F37+F29+F38 -> 217938.46
D52: Total | E52: Todo Riesgo | F52: =SUM(F26+F35) -> 41282.949
D53: Total | E53: T.E.V. | F53: =+F30+F31+F39+F40 -> 174381.96
D54: Pérdidas consecuenciales | F54: =F42+F43+F44 -> 249175.66 | N54: 517864.19
D55: Subtotal | F55: =SUM(F50:F54) -> 909835.25
N56: =F97 -> 1088395.2
B57: SUBLIMITES:
B58: Gastos Extraordinarios | C58: 0.1 | D58: =(D24+D33)*C58 -> 86937200 | E58: =((F24+F25+F26+F27+F33+F34+F35+F36)/D46)*500 -> 0.11240081 | F58: =(D58*E58/1000)/365*$G$12 -> 9798.5835 | G58: =$G$24 -> 0.25 | H58: =G58*F58 -> 2449.6459
B59: Gastos Extraordinarios por FHM | C59: =C58 -> 0.1 | D59: =D58*B28 -> 86937200 | E59: =((F28+F29+F37+F38)/D46)*500 -> 0.091289165 | F59: =(D59*E59/1000)/365*$G$12 -> 7958.168 | G59: 0.05 | H59: =G59*F59 -> 397.9084
B60: Gastos Extraordinarios por TEV | C60: =C58 -> 0.1 | D60: =D58*B30 -> 86937200 | E60: =((F30+F31+F39+F40)/D46)*500 -> 0.073044399 | F60: =(D60*E60/1000)/365*$G$12 -> 6367.6735 | G60: 0.05 | H60: =G60*F60 -> 318.38367
B61: Rem. Escombros Edificio I.O.R. | C61: =+$G$15 -> 0.2 | D61: =SUM(D24*C61) -> 31109.94 | E61: =((E24+E25+E26+E28)*0.1) -> 0.05578153 | F61: =(D61*E61/1000)/365*$G$12 -> 1.7401145 | G61: =$G$24 -> 0.25 | H61: =G61*F61 -> 0.43502862
B62: Rem. Escombros Edificio T.E.V. | C62: =+$G$15 -> 0.2 | D62: =SUM(D30*C62) -> 31109.94 | E62: =((E30)*0.1) -> 0.04 | F62: =(D62*E62/1000)/365*$G$12 -> 1.2478069 | G62: =G28 -> 0.05 | H62: =G62*F62 -> 0.062390345
B63: Rem. Escombros Contenidos I.O.R. | C63: =+$G$15 -> 0.2 | D63: =SUM(D33*C63) -> 1.7384329e+08 | E63: =((E33+E34+E35+E37)*0.1) -> 0.05578153 | F63: =(D63*E63/1000)/365*$G$12 -> 9723.8125 | G63: =$G$24 -> 0.25 | H63: =G63*F63 -> 2430.9531
B64: Rem. Escombros Contenidos T.E.V. | C64: =+$G$15 -> 0.2 | D64: =SUM(D39*C64) -> 1.7384329e+08 | E64: =((E39)*0.1) -> 0.02 | F64: =(D64*E64/1000)/365*$G$12 -> 3486.3915 | G64: =$G$28 -> 0.05 | H64: =G64*F64 -> 174.31957
B65: Bienes a intemperie (incluye jardines, áreas verdes) | D65: 3000000 | E65: =E28*1 -> 0.25 | F65: =(D65*E65/1000)/365*$G$12 -> 752.05479 | G65: =$G$28 -> 0.05 | H65: =G65*F65 -> 37.60274
B66: Cámaras Refrigeradoras | D66: 150000 | E66: 0.2 | F66: =(D66*E66/1000)/365*$G$12 -> 30.082192 | G66: =$G$24 -> 0.25 | H66: =G66*F66 -> 7.5205479
B67: Incisos Conocidos | D67: 5000000 | E67: 0.0022 | F67: =(D67*E67/1000)/365*$G$12 -> 11.030137 | G67: =$G$24 -> 0.25 | H67: =G67*F67 -> 2.7575342 | N67: 11.03
B68: Incisos Nuevos o no Conocidos | D68: 5000000 | E68: =E67 -> 0.0022 | F68: =(D68*E68/1000)/365*$G$12 -> 11.030137 | G68: =$G$24 -> 0.25 | H68: =G68*F68 -> 2.7575342 | N68: 11.03
B69: Flotante | C69: Hasta | D69: 0 | E69: =SUM(E32+E33+E34+E36+E38)*1.2 -> 0.54683335 | F69: =(D69*E69/1000)/365*$G$12 -> 0 | G69: =$G$24 -> 0.25 | H69: =G69*F69 -> 0
C71: TOTAL SECCIÓN DE INCENDIO: | F71: =SUM(F55+F58+F59+F60+F61+F62+F63+F64+F65+F66+F67+F68+F69) -> 947977.07
B73: Rotura de Maquinaria | D73: 250000 | E73: 5 | F73: =(D73*E73/1000)/365*$G$12 -> 1253.4247 | G73: 0.15 | H73: =G73*F73 -> 188.0137
B74: Inflación | C74: =+$G$16 -> 0 | D74: =D73*C74 -> 0 | E74: =(E73*35%) -> 1.75 | F74: =(D74*E74/1000)/365*$G$12 -> 0 | G74: =$G$73 -> 0.15 | H74: =G74*F74 -> 0
B75: Calderas | D75: 0 | E75: 1.6 | F75: =(D75*E75/1000)/365*$G$12 -> 0 | G75: =$G$73 -> 0.15 | H75: =G75*F75 -> 0
B76: =B74 -> Inflación | C76: =+$G$16 -> 0 | E76: =(E75*35%) -> 0.56 | F76: =(D76*E76/1000)/365*$G$12 -> 0 | G76: =G73 -> 0.15 | H76: =G76*F76 -> 0
B77: Eq. De Contratistas | D77: 0 | E77: 0 | F77: =(D77*E77/100)/365*$G$12 -> 0 | G77: =$G$73 -> 0.15 | H77: =G77*F77 -> 0
B78: =B74 -> Inflación | C78: =+$G$16 -> 0 | E78: =(E77*0.35) -> 0 | F78: =(D78*E78/100)/365*$G$12 -> 0 | G78: =G73 -> 0.15 | H78: =G78*F78 -> 0
B79: Obra Civil | E79: 0 | F79: =(D79*E79/1000)/365*$G$12 -> 0 | G79: =G73 -> 0.15 | H79: =G79*F79 -> 0
B80: Eq, Electrónico fijo | D80: 6500000 | E80: 18 | F80: =(D80*E80/1000)/365*$G$12 -> 117320.55 | G80: =$G$73 -> 0.15 | H80: =G80*F80 -> 17598.082 | N80: 117240 | O80: =F80-N80 -> 80.547945
B81: * Eq, electrónico móvil | D81: 785000 | E81: 10 | F81: =(D81*E81/1000)/365*$G$12 -> 7871.5068 | G81: =$G$73 -> 0.15 | H81: =G81*F81 -> 1180.726
B82: * Incremento en el Costo de Operación | E82: 0 | F82: =(D82*E82/1000)/365*$G$12 -> 0 | G82: =G73 -> 0.15 | H82: =G82*F82 -> 0
B83: * Portadores Externos de Datos | E83: 0 | F83: =(D83*E83/1000)/365*$G$12 -> 0 | G83: =G73 -> 0.15 | H83: =G83*F83 -> 0
B84: =B74 -> Inflación | C84: =C74 -> 0 | D84: =(D80+D81+D82+D83)*C84 -> 0 | E84: =(E80+E81+E82+E83)*35% -> 9.8 | F84: =(D84*E84/1000)/365*$G$12 -> 0 | G84: =$G$73 -> 0.15 | H84: =G84*F84 -> 0
B85: Robo | D85: 270000 | E85: 2.3276 | F85: =(D85*E85/100)/365*$G$12 -> 6301.7379 | G85: 0.15 | H85: =G85*F85 -> 945.26068
B86: Cristales | D86: 13000 | E86: 5 | F86: =(D86*E86/100)/365*$G$12 -> 651.78082 | G86: =$G$85 -> 0.15 | H86: =G86*F86 -> 97.767123
B87: =B74 -> Inflación | C87: =+$G$16 -> 0 | E87: =(E86*35%) -> 1.75 | F87: =(D87*E87/100)/365*$G$12 -> 0 | G87: =$G$85 -> 0.15 | H87: =G87*F87 -> 0
B88: Dinero y Valores | D88: 54000 | E88: 12 | F88: =(D88*E88/100)/365*$G$12 -> 6497.7534 | G88: =$G$85 -> 0.15 | H88: =G88*F88 -> 974.66301
B89: Anuncios Luminosos | D89: 13000 | E89: 4 | F89: =(D89*E89/100)/365*$G$12 -> 521.42466 | G89: =$G$85 -> 0.15 | H89: =G89*F89 -> 78.213699
B90: =B74 -> Inflación | C90: =+$G$16 -> 0 | E90: =(E89*35%) -> 1.4 | F90: =(D90*E90/100)/365*$G$12 -> 0 | G90: =$G$85 -> 0.15 | H90: =G90*F90 -> 0
B91: Resp. Civil Actividades y Adicionales | D91: 0 | E91: 1.896 | F91: =SUM(D91*E91/1000)/365*G12 -> 0 | G91: 0.1 | H91: =G91*F91 -> 0
B92: Resp. Civil Arrendatario | D92: 0 | E92: =E33*35% -> 0.08287335 | F92: =(D92*E92/1000)/365*$G$12 -> 0 | G92: =G91 -> 0.1 | H92: =G92*F92 -> 0
B93: Transportes | D93: 0 | E93: 0 | F93: =(D93*E93/100)/365*$G$12 -> 0 | G93: 0.15 | H93: =G93*F93 -> 0
C95: TOTAL RESTO DE LAS SECCIONES: | F95: =SUM(F73:F94) -> 140418.18 | H95: =SUM(H24:H89) -> 142060.3
G96: =H95/F97 -> 0.13052271
D97: Prima Neta | F97: =+F95+F71 -> 1088395.2 | H97: 518887.31
B98: FORMA DE PAGO: | C98: OPCIÓN | D98: C / Descuentos | F98: 0
B99: CONTADO 0 | C99: 0 | D99: Prima Neta con Descuento | F99: =(F97-(F97*F98)) -> 1088395.2 | I99: 0 | J99: CONTADO | L99: 0-10000 | M99: 350
B100: SEMESTRAL 1 | C100: =IF(C99=0,J99,IF(C99=1,J100,IF(C99=2,J101,IF(C99=3,J102)))) -> CONTADO | D100: Recargo de Pago Fraccionado | F100: =(F99*G100) -> 0 | G100: 0 | I100: 4.2 | J100: SEMESTRAL | L100: 10001- 50000 | M100: 500
B101: TRIMESTRAL 2 | D101: Derechos de Póliza | F101: 100 | I101: 6.4 | J101: TRIMESTRAL | L101: 50001- 150000 | M101: 750
B102: MENSUAL 3 | D102: I.V.A | F102: =(F99+F100+F101)*G102 -> 174159.24 | G102: 0.16 | I102: 7.7 | J102: MENSUAL | L102: >150001 | M102: 1000
D103: Prima Total | F103: =F99+F100+F101+F102 -> 1262654.5 | G103: =D18 -> USD
B106: RESUMEN DE TÉRMINOS Y CONDICIONES:
B107: Aclarando que las Coberturas que no tengan monto en el cuadro superior no se encuentran amparadas.
B109: Asegurado: | C109: =C8 -> OPERADORA DE CINEMAS SA DE CV
B111: Asegurado Adicionales: | C111: " BANCO SANTANDER (MEXICO), S.A., INSTITUCION DE BANCA MULTIPLE, GRUPO FINANCIERO SANTANDER"
B114: Ubicación del Riesgo | C114: =C11 -> 0
B116: Giro: | C116: =C12 -> HOTEL CON ESTACIONAMIENTO, LOCALES COMERCIALES, SERVICIOS RECREATIVOS Y LO RELACIONADO AL GIRO DEL ASEGURADO
B119: CLAUSULA DE BENEFICIARIO PREFERENTE | C119: EN CASO DE SINIESTRO QUE AMERITE INDEMNIZACION, ESTA SERA PAGADERA A FAVOR DE METLIFE MEXICO, S.A., UBICADO EN BLVD. MANUEL AVILA CAMACHO NO. 32 SKL, PISO 14-20 Y PH. LOMAS DE CHAPULTEPEC, MEXICO, D.F. C.P. 11000, HASTA EL INTERES QUE LE CORRESPONDA. ASI MISMO NO SE PODRA CANCELAR NI MODIFICAR LA POLIZA PREVIA AUTORIZACION POR ESCRITO DE METLIFE MEXICO, S.A.
B121: Vigencia: | C121: DEL | D121: =C16 -> 45107 | E121: AL | F121: =D16 -> 45473 | G121: =G12 -> 366
B123: Moneda: | C123: =C18 -> DOLARES | D123: =D18 -> USD
...

Sheet HOJA PRIMER RIESGO
P1: SUSCRIPTOR | Q1: CLAVESUSCRIPTOR | R1: NumeroDeUbicaciones | S1: 3 | T1: =VLOOKUP(S1,S2:T5,2) -> TRIMESTRAL | U1: =IF(F13="NACIONAL",1,2) -> 2 | V1: =F13 -> DÓLARES
P2: DULCE HUERTA | Q2: DHUERTA | R2: 364 | S2: 1 | T2: CONTADO | U2: 0 | V2: 0
S3: 2 | T3: SEMESTRAL | U3: 0.042 | V3: 0.014
S4: 3 | T4: TRIMESTRAL | U4: 0.064 | V4: 0.0211
A5: HOJA CONTABLE | S5: 4 | T5: MENSUAL | U5: 0.077 | V5: 0.0258
A7: RAMO COMERCIAL | C7: 20 - SME 1ER RIESGO - ESPARCIMIENTO | K7: =MID(C7,1,2)*1 -> 20 | L7: POLIZA A PRIMER RIESGO | S7: Recargo Forma de Pago: | U7: =VLOOKUP(S1,S2:V5,U1+2) -> 0.0211
A8: GIRO | C8: 0590-ESPECTÁCULOS PÚBLICOS, CINES, TEATROS, PARQUES DE DIVERSIÓN, CASINOS Y/O SIMILARES | F8: SUBGIRO | G8: 0590.05-Cines | L8: =Hoja3!A8
A9: ASEGURADO | C9: OPERADORA DE CINEMAS SA DE CV | J9: COD. ASEG. | K9: 0 | L9: TIPO DE MOVIMIENTO | N9: RENOVACION | S9: Factor Prorrata: | U9: =IF(H14="DIRECTA",1,J15/I15) -> 1
A10: DIRECCIÓN FISCAL | C10: JAVIER BARROS SIERRA 540 TORRE 1 PH1 COL SANTA FE ALVARO OBREGON CDMX CP 01210 | L10: TIPO DE PÓLIZA | N10: TODO RIESGO
A11: DIRECCIÓN DEL RIESGO | C11: =C10 -> JAVIER BARROS SIERRA 540 TORRE 1 PH1 COL SANTA FE ALVARO OBREGON CDMX CP 01210 | L11: ZONA TEV | M11: ='COTIZACIÓN M.N.'!G13 -> A | N11: ZONA F.H.M. | O11: ='COTIZACIÓN M.N.'!G17 -> A1PS
A12: VIG. INICIO | C12: 45107 | D12: T. DE RIESGO: | F12: ORDINARIO | G12: AGENTE | H12: MARSH | K12: 1 | L12: REM. ESC. | M12: ='COTIZACIÓN M.N.'!G15 -> 0.2 | N12: Indice Variable | O12: ='COTIZACIÓN M.N.'!G16 -> 0
A13: VIG. FINAL | C13: 45473 | D13: MONEDA | F13: DÓLARES | G13: R.F.C. | H13: OCI970818KX9 | J13: DÍAS DE VIGENCIA | N13: Coaseguro FHM | O13: =100%-'COTIZACIÓN M.N.'!G18 -> 1
A14: PÓLIZA | C14: POLIZA NUEVA | D14: F. PAGO | G14: CALCULO | H14: DIRECTA | K14: IVA | N14: Coaseguro TEV | O14: =100%-'COTIZACIÓN M.N.'!G14 -> 1
C15: 1 | I15: 365 | J15: =C13-C12 -> 366 | K15: 0.16
A16: COD. RAMO TECNICO | B16: SECCIÓN / COB. | C16: SECCIÓN / COBERTURA | D16: S/N | E16: Sublimite | F16: SUMA ASEGURADA | G16: CUOTAS | H16: PRIMA | I16: METODO DE CALCULO | J16: REC. PAGO FRACC. | K16: IVA | L16: PRIMA TOTAL | M16: COM. % | N16: COMISIÓN | O16: COMISIÓN TOTAL | P16: FILTRO
A17: 902 | B17: 001 | C17: INCENDIO EDIFICIO | D17: ='Ramo Comercial'!C121 -> INCLUIDO | F17: 20000000 | G17: ='COTIZACIÓN M.N.'!E24+'COTIZACIÓN M.N.'!E25+'COTIZACIÓN M.N.'!E26 -> 0.3078153 | M17: 0.25 | P17: =IF(Q17=1,"SI","NO") -> SI | Q17: =IF(D17="INCLUIDO",IF(F17<>0,1,0),0) -> 1 | T17: =G17 -> 0.3078153
A18: INCENDIO | B18: 001 | C18: COBERTURA BÁSICA | D18: =$D$17 -> INCLUIDO | E18: Adicional | F18: =$F$17*S18 -> 20000000 | G18: =V18 -> 0.24625224 | H18: 0 | I18: %o Al Millar | J18: =H18*$U$7 -> 0 | K18: =(H18+J18)*$K$15 -> 0 | L18: =ROUND(H18+J18+K18,2) -> 0 | M18: =$M$17 -> 0.25 | N18: =H18*M18 -> 0 | O18: =N18 -> 0 | P18: =IF(Q18=1,"SI","NO") -> SI | Q18: =IF(D18="INCLUIDO",IF(F18<>0,1,0),0) -> 1 | R18: =IF(I18="%o Al Millar",1000,IF(I18="% Al Porciento",100,IF(I18="$ Prima",G18))) -> 1000 | S18: =IF(E18="Excluido",0,IF(D18="NO APLICA",0,1)) -> 1 | T18: 0.8 | U18: =IF(E18="Excluido",0,T17*T18) -> 0.24625224 | V18: =IF(F17=0,0,(U23-U22-U20)+(T17-U23)) -> 0.24625224
A19: INCENDIO | C19: =$O$12 -> 0 | D19: =$D$17 -> INCLUIDO | E19: Adicional | F19: =(F18*$O$12)*S19 -> 0 | G19: =G18*0.35 -> 0.086188284 | H19: =(IF(I19="$ Prima",G19,G19*F19/R19))*$U$9 -> 0 | I19: %o Al Millar | J19: =H19*$U$7 -> 0 | K19: =(H19+J19)*$K$15 -> 0 | L19: =ROUND(H19+J19+K19,2) -> 0 | M19: =$M$17 -> 0.25 | N19: =H19*M19 -> 0 | O19: =N19 -> 0 | P19: =IF(Q19=1,"SI","NO") -> NO | Q19: =IF(D19="INCLUIDO",IF(F19<>0,1,0),0) -> 0 | R19: =IF(I19="%o Al Millar",1000,IF(I19="% Al Porciento",100,IF(I19="$ Prima",G19))) -> 1000 | S19: =IF(E19="Excluido",0,IF(D19="NO APLICA",0,1)) -> 1
A20: INCENDIO | B20: 002 | C20: EXTENSIÓN DE CUBIERTA (SIN HURACÁN Y GRANIZO) | D20: =$D$17 -> INCLUIDO | E20: Sublimite | F20: 0 | G20: =V20 -> 0.03078153 | H20: =(((IF(I20="$ Prima",G20,G20*F20/R20))*$U$9)/365)*$J$15 -> 0 | I20: %o Al Millar | J20: =H20*$U$7 -> 0 | K20: =(H20+J20)*$K$15 -> 0 | L20: =ROUND(H20+J20+K20,2) -> 0 | M20: =$M$17 -> 0.25 | N20: =H20*M20 -> 0 | O20: =N20 -> 0 | P20: =IF(Q20=1,"SI","NO") -> NO | Q20: =IF(D20="INCLUIDO",IF(F20<>0,1,0),0) -> 0 | R20: =IF(I20="%o Al Millar",1000,IF(I20="% Al Porciento",100,IF(I20="$ Prima",G20))) -> 1000 | S20: =IF(E20="Excluido",0,IF(D20="NO APLICA",0,1)) -> 1 | T20: 0.1 | U20: =IF(E20="Excluido",0,T17*T20) -> 0.03078153 | V20: =IF(F$17=0,0,U20) -> 0.03078153
A21: INCENDIO | C21: =$O$12 -> 0 | D21: =$D$17 -> INCLUIDO | E21: =E20 -> Sublimite | F21: =(F20*$O$12)*S21 -> 0 | G21: =G20*0.35 -> 0.010773536 | H21: =(IF(I21="$ Prima",G21,G21*F21/R21))*$U$9 -> 0 | I21: %o Al Millar | J21: =H21*$U$7 -> 0 | K21: =(H21+J21)*$K$15 -> 0 | L21: =ROUND(H21+J21+K21,2) -> 0 | M21: =$M$17 -> 0.25 | N21: =H21*M21 -> 0 | O21: =N21 -> 0 | P21: =IF(Q21=1,"SI","NO") -> NO | Q21: =IF(D21="INCLUIDO",IF(F21<>0,1,0),0) -> 0 | R21: =IF(I21="%o Al Millar",1000,IF(I21="% Al Porciento",100,IF(I21="$ Prima",G21))) -> 1000 | S21: =IF(E21="Excluido",0,IF(D21="NO APLICA",0,1)) -> 1
A22: INCENDIO | B22: 012 | C22: TODO RIESGO | D22: =$D$17 -> INCLUIDO | E22: Sublimite | F22: 0 | G22: =V22 -> 0.03078153 | H22: =(((IF(I22="$ Prima",G22,G22*F22/R22))*$U$9)/365)*$J$15 -> 0 | I22: %o Al Millar | J22: =H22*$U$7 -> 0 | K22: =(H22+J22)*$K$15 -> 0 | L22: =ROUND(H22+J22+K22,2) -> 0 | M22: =$M$17 -> 0.25 | N22: =H22*M22 -> 0 | O22: =N22 -> 0 | P22: =IF(Q22=1,"SI","NO") -> NO | Q22: =IF(D22="INCLUIDO",IF(F22<>0,1,0),0) -> 0 | R22: =IF(I22="%o Al Millar",1000,IF(I22="% Al Porciento",100,IF(I22="$ Prima",G22))) -> 1000 | S22: =IF(E22="Excluido",0,IF(D22="NO APLICA",0,1)) -> 1 | T22: 0.1 | U22: =IF(E22="Excluido",0,T17*T22) -> 0.03078153 | V22: =IF(F$17=0,0,U22) -> 0.03078153
A23: INCENDIO | C23: =$O$12 -> 0 | D23: =$D$17 -> INCLUIDO | E23: =E22 -> Sublimite | F23: =(F22*$O$12)*S23 -> 0 | G23: =G22*0.35 -> 0.010773536 | H23: =(IF(I23="$ Prima",G23,G23*F23/R23))*$U$9 -> 0 | I23: %o Al Millar | J23: =H23*$U$7 -> 0 | K23: =(H23+J23)*$K$15 -> 0 | L23: =ROUND(H23+J23+K23,2) -> 0 | M23: =$M$17 -> 0.25 | N23: =H23*M23 -> 0 | O23: =N23 -> 0 | P23: =IF(Q23=1,"SI","NO") -> NO | Q23: =IF(D23="INCLUIDO",IF(F23<>0,1,0),0) -> 0 | R23: =IF(I23="%o Al Millar",1000,IF(I23="% Al Porciento",100,IF(I23="$ Prima",G23))) -> 1000 | S23: =IF(E23="Excluido",0,IF(D23="NO APLICA",0,1)) -> 1 | T23: =SUM(T18:T22) -> 1 | U23: =SUM(U18:U22) -> 0.3078153 | V23: =SUM(V18:V22) -> 0.3078153
A24: INCENDIO | B24: 280 | C24: MEJORAS Y ADAPTACIONES | D24: =$D$17 -> INCLUIDO | E24: Sublimite | F24: 0 | G24: 0 | H24: =(IF(I24="$ Prima",G24,G24*F24/R24))*$U$9 -> 0 | I24: %o Al Millar | J24: =H24*$U$7 -> 0 | K24: =(H24+J24)*$K$15 -> 0 | L24: =ROUND(H24+J24+K24,2) -> 0 | M24: =$M$17 -> 0.25 | N24: =H24*M24 -> 0 | O24: =N24 -> 0 | P24: =IF(Q24=1,"SI","NO") -> NO | Q24: =IF(D24="INCLUIDO",IF(F24<>0,1,0),0) -> 0 | R24: =IF(I24="%o Al Millar",1000,IF(I24="% Al Porciento",100,IF(I24="$ Prima",G24))) -> 1000 | S24: =IF(E24="Excluido",0,IF(D24="NO APLICA",0,1)) -> 1
A25: INCENDIO | C25: =$O$12 -> 0 | D25: =$D$17 -> INCLUIDO | E25: =E24 -> Sublimite | F25: =(F24*$O$12)*S25 -> 0 | G25: =G24*0.35 -> 0 | H25: =(IF(I25="$ Prima",G25,G25*F25/R25))*$U$9 -> 0 | I25: %o Al Millar | J25: =H25*$U$7 -> 0 | K25: =(H25+J25)*$K$15 -> 0 | L25: =ROUND(H25+J25+K25,2) -> 0 | M25: =$M$17 -> 0.25 | N25: =H25*M25 -> 0 | O25: =N25 -> 0 | P25: =IF(Q25=1,"SI","NO") -> NO | Q25: =IF(D25="INCLUIDO",IF(F25<>0,1,0),0) -> 0 | R25: =IF(I25="%o Al Millar",1000,IF(I25="% Al Porciento",100,IF(I25="$ Prima",G25))) -> 1000 | S25: =IF(E25="Excluido",0,IF(D25="NO APLICA",0,1)) -> 1
A26: INCENDIO | B26: 004 | C26: INCISOS CONOCIDOS | D26: =$D$17 -> INCLUIDO | E26: Sublimite | F26: 0 | G26: ='COTIZACIÓN M.N.'!E67*50% -> 0.0011 | H26: =(IF(I26="$ Prima",G26,G26*F26/R26))*$U$9 -> 0 | I26: %o Al Millar | J26: =H26*$U$7 -> 0 | K26: =(H26+J26)*$K$15 -> 0 | L26: =ROUND(H26+J26+K26,2) -> 0 | M26: =$M$17 -> 0.25 | N26: =H26*M26 -> 0 | O26: =N26 -> 0 | P26: =IF(Q26=1,"SI","NO") -> NO | Q26: =IF(D26="INCLUIDO",IF(F26<>0,1,0),0) -> 0 | R26: =IF(I26="%o Al Millar",1000,IF(I26="% Al Porciento",100,IF(I26="$ Prima",G26))) -> 1000 | S26: =IF(E26="Excluido",0,IF(D26="NO APLICA",0,1)) -> 1
A27: INCENDIO | B27: 005 | C27: INCISOS NO CONOCIDOS | D27: =$D$17 -> INCLUIDO | E27: Sublimite | F27: 0 | G27: =G26 -> 0.0011 | H27: =(IF(I27="$ Prima",G27,G27*F27/R27))*$U$9 -> 0 | I27: %o Al Millar | J27: =H27*$U$7 -> 0 | K27: =(H27+J27)*$K$15 -> 0 | L27: =ROUND(H27+J27+K27,2) -> 0 | M27: =$M$17 -> 0.25 | N27: =H27*M27 -> 0 | O27: =N27 -> 0 | P27: =IF(Q27=1,"SI","NO") -> NO | Q27: =IF(D27="INCLUIDO",IF(F27<>0,1,0),0) -> 0 | R27: =IF(I27="%o Al Millar",1000,IF(I27="% Al Porciento",100,IF(I27="$ Prima",G27))) -> 1000 | S27: =IF(E27="Excluido",0,IF(D27="NO APLICA",0,1)) -> 1
A28: 903 | B28: 1 | C28: HIDROMETEOROLOGICO EDIFICIO | D28: =$D$17 -> INCLUIDO | M28: 0.05 | P28: =IF(Q28=1,"SI","NO") -> SI | Q28: =IF(D28="INCLUIDO",IF(F29<>0,1,0),0) -> 1
A29: FHM | B29: 040 | C29: RIESGOS HIDROMETEOROLÓGICOS | D29: =$D$17 -> INCLUIDO | E29: Sublimite | F29: =$F$17*S29 -> 20000000 | G29: ='COTIZACIÓN M.N.'!E28 -> 0.25 | H29: 0 | I29: %o Al Millar | J29: =H29*$U$7 -> 0 | K29: =(H29+J29)*$K$15 -> 0 | L29: =ROUND(H29+J29+K29,2) -> 0 | M29: =$M$28 -> 0.05 | N29: =H29*M29 -> 0 | O29: =N29 -> 0 | P29: =IF(Q29=1,"SI","NO") -> SI | Q29: =IF(D29="INCLUIDO",IF(F29<>0,1,0),0) -> 1 | R29: =IF(I29="%o Al Millar",1000,IF(I29="% Al Porciento",100,IF(I29="$ Prima",G29))) -> 1000 | S29: =IF(E29="Excluido",0,IF(D29="NO APLICA",0,1)) -> 1
A30: FHM | C30: =$O$12 -> 0 | D30: =$D$17 -> INCLUIDO | E30: =E29 -> Sublimite | F30: =(F29*$O$12)*S30 -> 0 | G30: =G29*0.35 -> 0.0875 | H30: =((IF(I30="$ Prima",G30,G30*F30/R30))*$U$9)*O13 -> 0 | I30: %o Al Millar | J30: =H30*$U$7 -> 0 | K30: =(H30+J30)*$K$15 -> 0 | L30: =ROUND(H30+J30+K30,2) -> 0 | M30: =$M$28 -> 0.05 | N30: =H30*M30 -> 0 | O30: =N30 -> 0 | P30: =IF(Q30=1,"SI","NO") -> NO | Q30: =IF(D30="INCLUIDO",IF(F30<>0,1,0),0) -> 0 | R30: =IF(I30="%o Al Millar",1000,IF(I30="% Al Porciento",100,IF(I30="$ Prima",G30))) -> 1000 | S30: =IF(E30="Excluido",0,IF(D30="NO APLICA",0,1)) -> 1
A31: 904 | B31: 1 | C31: TERREMOTO EDIFICIO | D31: =$D$17 -> INCLUIDO | M31: 0.05 | P31: =IF(Q31=1,"SI","NO") -> SI | Q31: =IF(D31="INCLUIDO",IF(F32<>0,1,0),0) -> 1
A32: TEV | B32: 055 | C32: TERREMOTO Y ERUPCIÓN VOLCÁNICA | D32: =$D$17 -> INCLUIDO | E32: Sublimite | F32: =F17 -> 20000000 | G32: ='COTIZACIÓN M.N.'!E30 -> 0.4 | H32: 0 | I32: %o Al Millar | J32: =H32*$U$7 -> 0 | K32: =(H32+J32)*$K$15 -> 0 | L32: =ROUND(H32+J32+K32,2) -> 0 | M32: =$M$31 -> 0.05 | N32: =H32*M32 -> 0 | O32: =N32 -> 0 | P32: =IF(Q32=1,"SI","NO") -> SI | Q32: =IF(D32="INCLUIDO",IF(F32<>0,1,0),0) -> 1 | R32: =IF(I32="%o Al Millar",1000,IF(I32="% Al Porciento",100,IF(I32="$ Prima",G32))) -> 1000 | S32: =IF(E32="Excluido",0,IF(D32="NO APLICA",0,1)) -> 1
A33: TEV | C33: =$O$12 -> 0 | D33: =$D$17 -> INCLUIDO | E33: =E32 -> Sublimite | F33: =(F32*$O$12)*S33 -> 0 | G33: =G32*0.35 -> 0.14 | H33: =((IF(I33="$ Prima",G33,G33*F33/R33))*$U$9)*O14 -> 0 | I33: %o Al Millar | J33: =H33*$U$7 -> 0 | K33: =(H33+J33)*$K$15 -> 0 | L33: =ROUND(H33+J33+K33,2) -> 0 | M33: =$M$31 -> 0.05 | N33: =H33*M33 -> 0 | O33: =N33 -> 0 | P33: =IF(Q33=1,"SI","NO") -> NO | Q33: =IF(D33="INCLUIDO",IF(F33<>0,1,0),0) -> 0 | R33: =IF(I33="%o Al Millar",1000,IF(I33="% Al Porciento",100,IF(I33="$ Prima",G33))) -> 1000 | S33: =IF(E33="Excluido",0,IF(D33="NO APLICA",0,1)) -> 1
A34: 902 | B34: 001 | C34: INCENDIO EDIFICIO - REM ESC. | D34: =$D$17 -> INCLUIDO | F34: 0 | M34: 0.25 | P34: =IF(Q34=1,"SI","NO") -> NO | Q34: =IF(D34="INCLUIDO",IF(F35<>0,1,0),0) -> 0
A35: INCENDIO | B35: 011 | C35: REMOCIÓN DE ESCOMBROS INCENDIO | D35: =$D$17 -> INCLUIDO | E35: Sublimite | F35: =F34*S35 -> 0 | G35: ='COTIZACIÓN M.N.'!E61*75% -> 0.041836148 | H35: =(((IF(I35="$ Prima",G35,G35*F35/R35))*$U$9)/365)*$J$15 -> 0 | I35: %o Al Millar | J35: =H35*$U$7 -> 0 | K35: =(H35+J35)*$K$15 -> 0 | L35: =ROUND(H35+J35+K35,2) -> 0 | M35: =M34 -> 0.25 | N35: =H35*M35 -> 0 | O35: =N35 -> 0 | P35: =IF(Q35=1,"SI","NO") -> NO | Q35: =IF(D35="INCLUIDO",IF(F35<>0,1,0),0) -> 0 | R35: =IF(I35="%o Al Millar",1000,IF(I35="% Al Porciento",100,IF(I35="$ Prima",G35))) -> 1000 | S35: =IF(E35="Excluido",0,IF(D35="NO APLICA",0,1)) -> 1
A36: 903 | B36: 1 | C36: HIDROMETEOROLOGICO EDIFICIO | D36: =$D$17 -> INCLUIDO | M36: =M28 -> 0.05 | P36: =IF(Q36=1,"SI","NO") -> NO | Q36: =IF(D36="INCLUIDO",IF(F37<>0,1,0),0) -> 0
A37: FHM | B37: 038 | C37: REMOCIÓN DE ESCOMBROS FENÓMENOS HIDROMETEOROLÓGICOS | D37: =$D$17 -> INCLUIDO | E37: Sublimite | F37: 0 | G37: ='COTIZACIÓN M.N.'!E61*25% -> 0.013945383 | H37: =(((IF(I37="$ Prima",G37,G37*F37/R37))*$U$9)/365)*$J$15 -> 0 | I37: %o Al Millar | J37: =H37*$U$7 -> 0 | K37: =(H37+J37)*$K$15 -> 0 | L37: =ROUND(H37+J37+K37,2) -> 0 | M37: =M36 -> 0.05 | N37: =H37*M37 -> 0 | O37: =N37 -> 0 | P37: =IF(Q37=1,"SI","NO") -> NO | Q37: =IF(D37="INCLUIDO",IF(F37<>0,1,0),0) -> 0 | R37: =IF(I37="%o Al Millar",1000,IF(I37="% Al Porciento",100,IF(I37="$ Prima",G37))) -> 1000 | S37: =IF(E37="Excluido",0,IF(D37="NO APLICA",0,1)) -> 1
A38: 904 | B38: 1 | C38: TERREMOTO EDIFICIO | D38: =$D$17 -> INCLUIDO | M38: =M31 -> 0.05 | P38: =IF(Q38=1,"SI","NO") -> NO | Q38: =IF(D38="INCLUIDO",IF(F39<>0,1,0),0) -> 0
A39: TEV | B39: 044 | C39: REMOCIÓN DE ESCOMBROS FENÓMENOS HIDROMETEOROLÓGICOS | D39: =$D$17 -> INCLUIDO | E39: Sublimite | F39: 0 | G39: ='COTIZACIÓN M.N.'!E62 -> 0.04 | H39: =(((IF(I39="$ Prima",G39,G39*F39/R39))*$U$9)/365)*$J$15 -> 0 | I39: %o Al Millar | J39: =H39*$U$7 -> 0 | K39: =(H39+J39)*$K$15 -> 0 | L39: =ROUND(H39+J39+K39,2) -> 0 | M39: =M38 -> 0.05 | N39: =H39*M39 -> 0 | O39: =N39 -> 0 | P39: =IF(Q39=1,"SI","NO") -> NO | Q39: =IF(D39="INCLUIDO",IF(F39<>0,1,0),0) -> 0 | R39: =IF(I39="%o Al Millar",1000,IF(I39="% Al Porciento",100,IF(I39="$ Prima",G39))) -> 1000 | S39: =IF(E39="Excluido",0,IF(D39="NO APLICA",0,1)) -> 1
C40: SUBTOTAL | D40: =D39 -> INCLUIDO | F40: =SUMIF(E18:E39,"Adicional",F18:F39) -> 20000000 | H40: =SUM(H18:H39) -> 0 | J40: =SUM(J18:J39) -> 0 | K40: =SUM(K18:K39) -> 0 | L40: =SUM(L18:L39) -> 0 | N40: =SUM(N18:N39) -> 0 | O40: =SUM(O18:O39) -> 0 | P40: =IF(Q40=1,"SI","NO") -> NO | Q40: =IF(D40="INCLUIDO",IF(H40<>0,1,0),0) -> 0
A41: 902 | B41: 2 | C41: INCENDIO CONTENIDOS | D41: =$D$17 -> INCLUIDO | F41: 0 | G41: ='COTIZACIÓN M.N.'!E33+'COTIZACIÓN M.N.'!E34+'COTIZACIÓN M.N.'!E35 -> 0.3078153 | M41: 0.25 | P41: =IF(Q41=1,"SI","NO") -> NO | Q41: =IF(D41="INCLUIDO",IF(F41<>0,1,0),0) -> 0 | T41: =G41 -> 0.3078153
A42: INCENDIO | B42: 013 | C42: COBERTURA BÁSICA | D42: =$D$17 -> INCLUIDO | E42: Adicional | F42: =$F$41*S42 -> 0 | G42: =V42 -> 0 | H42: =(((IF(I42="$ Prima",G42,G42*F42/R42))*$U$9)/365)*$J$15 -> 0 | I42: %o Al Millar | J42: =H42*$U$7 -> 0 | K42: =(H42+J42)*$K$15 -> 0 | L42: =ROUND(H42+J42+K42,2) -> 0 | M42: =$M$41 -> 0.25 | N42: =H42*M42 -> 0 | O42: =N42 -> 0 | P42: =IF(Q42=1,"SI","NO") -> NO | Q42: =IF(D42="INCLUIDO",IF(F42<>0,1,0),0) -> 0 | R42: =IF(I42="%o Al Millar",1000,IF(I42="% Al Porciento",100,IF(I42="$ Prima",G42))) -> 1000 | S42: =IF(E42="Excluido",0,IF(D42="NO APLICA",0,1)) -> 1 | T42: 0.7 | U42: =IF(E42="Excluido",0,T41*T42) -> 0.21547071 | V42: =IF(F41=0,0,(U51-U46-U44-U50)+(T41-U51)) -> 0
A43: INCENDIO | C43: =$O$12 -> 0 | D43: =$D$17 -> INCLUIDO | E43: =E42 -> Adicional | F43: =(F42*$O$12)*S42 -> 0 | G43: =G42*0.35 -> 0 | H43: =(IF(I43="$ Prima",G43,G43*F43/R43))*$U$9 -> 0 | I43: %o Al Millar | J43: =H43*$U$7 -> 0 | K43: =(H43+J43)*$K$15 -> 0 | L43: =ROUND(H43+J43+K43,2) -> 0 | M43: =$M$41 -> 0.25 | N43: =H43*M43 -> 0 | O43: =N43 -> 0 | P43: =IF(Q43=1,"SI","NO") -> NO | Q43: =IF(D43="INCLUIDO",IF(F43<>0,1,0),0) -> 0 | R43: =IF(I43="%o Al Millar",1000,IF(I43="% Al Porciento",100,IF(I43="$ Prima",G43))) -> 1000 | S43: =IF(E43="Excluido",0,IF(D43="NO APLICA",0,1)) -> 1
A44: INCENDIO | B44: 017 | C44: EXTENSIÓN DE CUBIERTA (SIN HURACÁN Y GRANIZO) | D44: =$D$17 -> INCLUIDO | E44: Sublimite | F44: =$F$41*S44 -> 0 | G44: =V44 -> 0 | H44: =(((IF(I44="$ Prima",G44,G44*F44/R44))*$U$9)/365)*$J$15 -> 0 | I44: %o Al Millar | J44: =H44*$U$7 -> 0 | K44: =(H44+J44)*$K$15 -> 0 | L44: =ROUND(H44+J44+K44,2) -> 0 | M44: =$M$41 -> 0.25 | N44: =H44*M44 -> 0 | O44: =N44 -> 0 | P44: =IF(Q44=1,"SI","NO") -> NO | Q44: =IF(D44="INCLUIDO",IF(F44<>0,1,0),0) -> 0 | R44: =IF(I44="%o Al Millar",1000,IF(I44="% Al Porciento",100,IF(I44="$ Prima",G44))) -> 1000 | S44: =IF(E44="Excluido",0,IF(D44="NO APLICA",0,1)) -> 1 | T44: 0.1 | U44: =IF(E44="Excluido",0,T41*T44) -> 0.03078153 | V44: =IF(F41=0,0,U44) -> 0
A45: INCENDIO | C45: =$O$12 -> 0 | D45: =$D$17 -> INCLUIDO | E45: =E44 -> Sublimite | F45: =(F44*$O$12)*S44 -> 0 | G45: =G44*0.35 -> 0 | H45: =(IF(I45="$ Prima",G45,G45*F45/R45))*$U$9 -> 0 | I45: %o Al Millar | J45: =H45*$U$7 -> 0 | K45: =(H45+J45)*$K$15 -> 0 | L45: =ROUND(H45+J45+K45,2) -> 0 | M45: =$M$41 -> 0.25 | N45: =H45*M45 -> 0 | O45: =N45 -> 0 | P45: =IF(Q45=1,"SI","NO") -> NO | Q45: =IF(D45="INCLUIDO",IF(F45<>0,1,0),0) -> 0 | R45: =IF(I45="%o Al Millar",1000,IF(I45="% Al Porciento",100,IF(I45="$ Prima",G45))) -> 1000 | S45: =IF(E45="Excluido",0,IF(D45="NO APLICA",0,1)) -> 1
A46: INCENDIO | B46: 028 | C46: TODO RIESGO | D46: =$D$17 -> INCLUIDO | E46: Sublimite | F46: 0 | G46: =V46 -> 0 | H46: =(((IF(I46="$ Prima",G46,G46*F46/R46))*$U$9)/365)*$J$15 -> 0 | I46: %o Al Millar | J46: =H46*$U$7 -> 0 | K46: =(H46+J46)*$K$15 -> 0 | L46: =ROUND(H46+J46+K46,2) -> 0 | M46: =$M$41 -> 0.25 | N46: =H46*M46 -> 0 | O46: =N46 -> 0 | P46: =IF(Q46=1,"SI","NO") -> NO | Q46: =IF(D46="INCLUIDO",IF(F46<>0,1,0),0) -> 0 | R46: =IF(I46="%o Al Millar",1000,IF(I46="% Al Porciento",100,IF(I46="$ Prima",G46))) -> 1000 | S46: =IF(E46="Excluido",0,IF(D46="NO APLICA",0,1)) -> 1 | T46: 0.1 | U46: =IF(E46="Excluido",0,T41*T46) -> 0.03078153 | V46: =IF(F41=0,0,U46) -> 0
A47: INCENDIO | C47: =$O$12 -> 0 | D47: =$D$17 -> INCLUIDO | E47: =E46 -> Sublimite | F47: =(F46*$O$12)*S46 -> 0 | G47: =G46*0.35 -> 0 | H47: =(IF(I47="$ Prima",G47,G47*F47/R47))*$U$9 -> 0 | I47: %o Al Millar | J47: =H47*$U$7 -> 0 | K47: =(H47+J47)*$K$15 -> 0 | L47: =ROUND(H47+J47+K47,2) -> 0 | M47: =$M$41 -> 0.25 | N47: =H47*M47 -> 0 | O47: =N47 -> 0 | P47: =IF(Q47=1,"SI","NO") -> NO | Q47: =IF(D47="INCLUIDO",IF(F47<>0,1,0),0) -> 0 | R47: =IF(I47="%o Al Millar",1000,IF(I47="% Al Porciento",100,IF(I47="$ Prima",G47))) -> 1000 | S47: =IF(E47="Excluido",0,IF(D47="NO APLICA",0,1)) -> 1
A48: INCENDIO | B48: 016 | C48: COMBUSTIÓN ESPONTANEA | D48: =$D$17 -> INCLUIDO | E48: Sublimite | F48: 0 | G48: 0 | H48: =(IF(I48="$ Prima",G48,G48*F48/R48))*$U$9 -> 0 | I48: %o Al Millar | J48: =H48*$U$7 -> 0 | K48: =(H48+J48)*$K$15 -> 0 | L48: =ROUND(H48+J48+K48,2) -> 0 | M48: =$M$41 -> 0.25 | N48: =H48*M48 -> 0 | O48: =N48 -> 0 | P48: =IF(Q48=1,"SI","NO") -> NO | Q48: =IF(D48="INCLUIDO",IF(F48<>0,1,0),0) -> 0 | R48: =IF(I48="%o Al Millar",1000,IF(I48="% Al Porciento",100,IF(I48="$ Prima",G48))) -> 1000 | S48: =IF(E48="Excluido",0,IF(D48="NO APLICA",0,1)) -> 1
A49: INCENDIO | C49: =$O$12 -> 0 | D49: =$D$17 -> INCLUIDO | E49: =E48 -> Sublimite | F49: =(F48*$O$12)*S48 -> 0 | G49: =G48*0.35 -> 0 | H49: =(IF(I49="$ Prima",G49,G49*F49/R49))*$U$9 -> 0 | I49: %o Al Millar | J49: =H49*$U$7 -> 0 | K49: =(H49+J49)*$K$15 -> 0 | L49: =ROUND(H49+J49+K49,2) -> 0 | M49: =$M$41 -> 0.25 | N49: =H49*M49 -> 0 | O49: =N49 -> 0 | P49: =IF(Q49=1,"SI","NO") -> NO | Q49: =IF(D49="INCLUIDO",IF(F49<>0,1,0),0) -> 0 | R49: =IF(I49="%o Al Millar",1000,IF(I49="% Al Porciento",100,IF(I49="$ Prima",G49))) -> 1000 | S49: =IF(E49="Excluido",0,IF(D49="NO APLICA",0,1)) -> 1
A50: INCENDIO | B50: 229 | C50: DERRAME DE P.C.I | D50: =$D$17 -> INCLUIDO | E50: Excluido | F50: =$F$41*S50 -> 0 | G50: =V50 -> 0 | H50: =(IF(I50="$ Prima",G50,G50*F50/R50))*$U$9 -> 0 | I50: %o Al Millar | J50: =H50*$U$7 -> 0 | K50: =(H50+J50)*$K$15 -> 0 | L50: =ROUND(H50+J50+K50,2) -> 0 | M50: =$M$41 -> 0.25 | N50: =H50*M50 -> 0 | O50: =N50 -> 0 | P50: =IF(Q50=1,"SI","NO") -> NO | Q50: =IF(D50="INCLUIDO",IF(F50<>0,1,0),0) -> 0 | R50: =IF(I50="%o Al Millar",1000,IF(I50="% Al Porciento",100,IF(I50="$ Prima",G50))) -> 1000 | S50: =IF(E50="Excluido",0,IF(D50="NO APLICA",0,1)) -> 0 | T50: 0.1 | U50: =IF(E50="Excluido",0,T41*T50) -> 0 | V50: =IF(F41=0,0,U50) -> 0
A51: INCENDIO | C51: =$O$12 -> 0 | D51: =$D$17 -> INCLUIDO | E51: =E50 -> Excluido | F51: =(F50*$O$12)*S50 -> 0 | G51: =G50*0.35 -> 0 | H51: =(IF(I51="$ Prima",G51,G51*F51/R51))*$U$9 -> 0 | I51: %o Al Millar | J51: =H51*$U$7 -> 0 | K51: =(H51+J51)*$K$15 -> 0 | L51: =ROUND(H51+J51+K51,2) -> 0 | M51: =$M$41 -> 0.25 | N51: =H51*M51 -> 0 | O51: =N51 -> 0 | P51: =IF(Q51=1,"SI","NO") -> NO | Q51: =IF(D51="INCLUIDO",IF(F51<>0,1,0),0) -> 0 | R51: =IF(I51="%o Al Millar",1000,IF(I51="% Al Porciento",100,IF(I51="$ Prima",G51))) -> 1000 | S51: =IF(E51="Excluido",0,IF(D51="NO APLICA",0,1)) -> 0 | T51: =SUM(T42:T50) -> 1 | U51: =SUM(U42:U50) -> 0.27703377 | V51: =SUM(V42:V50) -> 0
A52: INCENDIO | B52: 230 | C52: EXISTENCIAS | D52: =$D$17 -> INCLUIDO | E52: Sublimite | F52: 0 | G52: 0 | H52: =(IF(I52="$ Prima",G52,G52*F52/R52))*$U$9 -> 0 | I52: %o Al Millar | J52: =H52*$U$7 -> 0 | K52: =(H52+J52)*$K$15 -> 0 | L52: =ROUND(H52+J52+K52,2) -> 0 | M52: =$M$41 -> 0.25 | N52: =H52*M52 -> 0 | O52: =N52 -> 0 | P52: =IF(Q52=1,"SI","NO") -> NO | Q52: =IF(D52="INCLUIDO",IF(F52<>0,1,0),0) -> 0 | R52: =IF(I52="%o Al Millar",1000,IF(I52="% Al Porciento",100,IF(I52="$ Prima",G52))) -> 1000 | S52: =IF(E52="Excluido",0,IF(D52="NO APLICA",0,1)) -> 1
A53: INCENDIO | C53: =$O$12 -> 0 | D53: =$D$17 -> INCLUIDO | E53: =E52 -> Sublimite | F53: =(F52*$O$12)*S52 -> 0 | G53: =G52*0.35 -> 0 | H53: =(IF(I53="$ Prima",G53,G53*F53/R53))*$U$9 -> 0 | I53: %o Al Millar | J53: =H53*$U$7 -> 0 | K53: =(H53+J53)*$K$15 -> 0 | L53: =ROUND(H53+J53+K53,2) -> 0 | M53: =$M$41 -> 0.25 | N53: =H53*M53 -> 0 | O53: =N53 -> 0 | P53: =IF(Q53=1,"SI","NO") -> NO | Q53: =IF(D53="INCLUIDO",IF(F53<>0,1,0),0) -> 0 | R53: =IF(I53="%o Al Millar",1000,IF(I53="% Al Porciento",100,IF(I53="$ Prima",G53))) -> 1000 | S53: =IF(E53="Excluido",0,IF(D53="NO APLICA",0,1)) -> 1
A54: INCENDIO | B54: 231 | C54: INCISO FLOTANTE | D54: =$D$17 -> INCLUIDO | E54: Sublimite | F54: 0 | G54: 0 | H54: =(IF(I54="$ Prima",G54,G54*F54/R54))*$U$9 -> 0 | I54: %o Al Millar | J54: =H54*$U$7 -> 0 | K54: =(H54+J54)*$K$15 -> 0 | L54: =ROUND(H54+J54+K54,2) -> 0 | M54: =$M$41 -> 0.25 | N54: =H54*M54 -> 0 | O54: =N54 -> 0 | P54: =IF(Q54=1,"SI","NO") -> NO | Q54: =IF(D54="INCLUIDO",IF(F54<>0,1,0),0) -> 0 | R54: =IF(I54="%o Al Millar",1000,IF(I54="% Al Porciento",100,IF(I54="$ Prima",G54))) -> 1000 | S54: =IF(E54="Excluido",0,IF(D54="NO APLICA",0,1)) -> 1
A55: INCENDIO | B55: 014 | C55: BIENES A LA INTEMPERIE INCENDIO | D55: =$D$17 -> INCLUIDO | E55: Sublimite | F55: 0 | G55: ='COTIZACIÓN M.N.'!E65 -> 0.25 | H55: =(((IF(I55="$ Prima",G55,G55*F55/R55))*$U$9)/365)*$J$15 -> 0 | I55: %o Al Millar | J55: =H55*$U$7 -> 0 | K55: =(H55+J55)*$K$15 -> 0 | L55: =ROUND(H55+J55+K55,2) -> 0 | M55: =$M$41 -> 0.25 | N55: =H55*M55 -> 0 | O55: =N55 -> 0 | P55: =IF(Q55=1,"SI","NO") -> NO | Q55: =IF(D55="INCLUIDO",IF(F55<>0,1,0),0) -> 0 | R55: =IF(I55="%o Al Millar",1000,IF(I55="% Al Porciento",100,IF(I55="$ Prima",G55))) -> 1000 | S55: =IF(E55="Excluido",0,IF(D55="NO APLICA",0,1)) -> 1
A56: INCENDIO | C56: =$O$12 -> 0 | D56: =$D$17 -> INCLUIDO | E56: =E55 -> Sublimite | F56: 0 | G56: =G55*0.35 -> 0.0875 | H56: =(IF(I56="$ Prima",G56,G56*F56/R56))*$U$9 -> 0 | I56: %o Al Millar | J56: =H56*$U$7 -> 0 | K56: =(H56+J56)*$K$15 -> 0 | L56: =ROUND(H56+J56+K56,2) -> 0 | M56: =$M$41 -> 0.25 | N56: =H56*M56 -> 0 | O56: =N56 -> 0 | P56: =IF(Q56=1,"SI","NO") -> NO | Q56: =IF(D56="INCLUIDO",IF(F56<>0,1,0),0) -> 0 | R56: =IF(I56="%o Al Millar",1000,IF(I56="% Al Porciento",100,IF(I56="$ Prima",G56))) -> 1000 | S56: =IF(E56="Excluido",0,IF(D56="NO APLICA",0,1)) -> 1
A57: INCENDIO | B57: 015 | C57: BIENES EN CUARTOS REFRIGERADOS | D57: =$D$17 -> INCLUIDO | E57: Sublimite | F57: 0 | G57: ='COTIZACIÓN M.N.'!E66 -> 0.2 | H57: =(((IF(I57="$ Prima",G57,G57*F57/R57))*$U$9)/365)*$J$15 -> 0 | I57: %o Al Millar | J57: =H57*$U$7 -> 0 | K57: =(H57+J57)*$K$15 -> 0 | L57: =ROUND(H57+J57+K57,2) -> 0 | M57: =$M$41 -> 0.25 | N57: =H57*M57 -> 0 | O57: =N57 -> 0 | P57: =IF(Q57=1,"SI","NO") -> NO | Q57: =IF(D57="INCLUIDO",IF(F57<>0,1,0),0) -> 0 | R57: =IF(I57="%o Al Millar",1000,IF(I57="% Al Porciento",100,IF(I57="$ Prima",G57))) -> 1000 | S57: =IF(E57="Excluido",0,IF(D57="NO APLICA",0,1)) -> 1
A58: INCENDIO | C58: =$O$12 -> 0 | D58: =$D$17 -> INCLUIDO | E58: =E57 -> Sublimite | F58: 0 | G58: =G57*0.35 -> 0.07 | H58: =(IF(I58="$ Prima",G58,G58*F58/R58))*$U$9 -> 0 | I58: %o Al Millar | J58: =H58*$U$7 -> 0 | K58: =(H58+J58)*$K$15 -> 0 | L58: =ROUND(H58+J58+K58,2) -> 0 | M58: =$M$41 -> 0.25 | N58: =H58*M58 -> 0 | O58: =N58 -> 0 | P58: =IF(Q58=1,"SI","NO") -> NO | Q58: =IF(D58="INCLUIDO",IF(F58<>0,1,0),0) -> 0 | R58: =IF(I58="%o Al Millar",1000,IF(I58="% Al Porciento",100,IF(I58="$ Prima",G58))) -> 1000 | S58: =IF(E58="Excluido",0,IF(D58="NO APLICA",0,1)) -> 1
A59: INCENDIO | B59: 019 | C59: INCISOS CONOCIDOS | D59: =$D$17 -> INCLUIDO | E59: Sublimite | F59: 0 | G59: =G26 -> 0.0011 | H59: =(IF(I59="$ Prima",G59,G59*F59/R59))*$U$9 -> 0 | I59: %o Al Millar | J59: =H59*$U$7 -> 0 | K59: =(H59+J59)*$K$15 -> 0 | L59: =ROUND(H59+J59+K59,2) -> 0 | M59: =$M$41 -> 0.25 | N59: =H59*M59 -> 0 | O59: =N59 -> 0 | P59: =IF(Q59=1,"SI","NO") -> NO | Q59: =IF(D59="INCLUIDO",IF(F59<>0,1,0),0) -> 0 | R59: =IF(I59="%o Al Millar",1000,IF(I59="% Al Porciento",100,IF(I59="$ Prima",G59))) -> 1000 | S59: =IF(E59="Excluido",0,IF(D59="NO APLICA",0,1)) -> 1
A60: INCENDIO | B60: 020 | C60: INCISOS NO CONOCIDOS | D60: =$D$17 -> INCLUIDO | E60: Sublimite | F60: 0 | G60: =G59 -> 0.0011 | H60: 0 | I60: %o Al Millar | J60: =H60*$U$7 -> 0 | K60: =(H60+J60)*$K$15 -> 0 | L60: =ROUND(H60+J60+K60,2) -> 0 | M60: =$M$41 -> 0.25 | N60: =H60*M60 -> 0 | O60: =N60 -> 0 | P60: =IF(Q60=1,"SI","NO") -> NO | Q60: =IF(D60="INCLUIDO",IF(F60<>0,1,0),0) -> 0 | R60: =IF(I60="%o Al Millar",1000,IF(I60="% Al Porciento",100,IF(I60="$ Prima",G60))) -> 1000 | S60: =IF(E60="Excluido",0,IF(D60="NO APLICA",0,1)) -> 1
A61: 903 | B61: 2 | C61: HIDROMETEOROLOGICO CONTENIDOS | D61: =$D$17 -> INCLUIDO | M61: 0.05 | P61: =IF(Q61=1,"SI","NO") -> NO | Q61: =IF(D61="INCLUIDO",IF(F62<>0,1,0),0) -> 0 | S61: =IF(E61="Excluido",0,IF(D61="NO APLICA",0,1)) -> 1
A62: FHM | B62: 046 | C62: RIESGOS HIDROMETEOROLÓGICOS | D62: =$D$17 -> INCLUIDO | E62: Sublimite | F62: =$F$41*S62 -> 0 | G62: ='COTIZACIÓN M.N.'!E37 -> 0.25 | H62: =((((IF(I62="$ Prima",G62,G62*F62/R62))*$U$9)/365)*$J$15) -> 0 | I62: %o Al Millar | J62: =H62*$U$7 -> 0 | K62: =(H62+J62)*$K$15 -> 0 | L62: =ROUND(H62+J62+K62,2) -> 0 | M62: 0.05 | N62: =H62*M62 -> 0 | O62: =N62 -> 0 | P62: =IF(Q62=1,"SI","NO") -> NO | Q62: =IF(D62="INCLUIDO",IF(F62<>0,1,0),0) -> 0 | R62: =IF(I62="%o Al Millar",1000,IF(I62="% Al Porciento",100,IF(I62="$ Prima",G62))) -> 1000 | S62: =IF(E62="Excluido",0,IF(D62="NO APLICA",0,1)) -> 1
A63: FHM | C63: =$O$12 -> 0 | D63: =$D$17 -> INCLUIDO | E63: =E62 -> Sublimite | F63: =(F62*$O$12)*S62 -> 0 | G63: =G62*35% -> 0.0875 | H63: =((IF(I63="$ Prima",G63,G63*F63/R63))*$U$9) -> 0 | I63: %o Al Millar | J63: =H63*$U$7 -> 0 | K63: =(H63+J63)*$K$15 -> 0 | L63: =ROUND(H63+J63+K63,2) -> 0 | M63: =$M$61 -> 0.05 | N63: =H63*M63 -> 0 | O63: =N63 -> 0 | P63: =IF(Q63=1,"SI","NO") -> NO | Q63: =IF(D63="INCLUIDO",IF(F63<>0,1,0),0) -> 0 | R63: =IF(I63="%o Al Millar",1000,IF(I63="% Al Porciento",100,IF(I63="$ Prima",G63))) -> 1000 | S63: =IF(E63="Excluido",0,IF(D63="NO APLICA",0,1)) -> 1
A64: 904 | B64: 2 | C64: TERREMOTO CONTENIDOS | D64: =$D$17 -> INCLUIDO | M64: 0.05 | P64: =IF(Q64=1,"SI","NO") -> NO | Q64: =IF(D64="INCLUIDO",IF(F65<>0,1,0),0) -> 0 | S64: =IF(E64="Excluido",0,IF(D64="NO APLICA",0,1)) -> 1
A65: TEV | B65: 63 | C65: TERREMOTO Y ERUPCIÓN VOLCÁNICA | D65: =$D$17 -> INCLUIDO | E65: Sublimite | F65: =F41 -> 0 | G65: ='COTIZACIÓN M.N.'!E39 -> 0.2 | H65: =((((IF(I65="$ Prima",G65,G65*F65/R65))*$U$9)*O14)/365)*$J$15 -> 0 | I65: %o Al Millar | J65: =H65*$U$7 -> 0 | K65: =(H65+J65)*$K$15 -> 0 | L65: =ROUND(H65+J65+K65,2) -> 0 | M65: =$M$64 -> 0.05 | N65: =H65*M65 -> 0 | O65: =N65 -> 0 | P65: =IF(Q65=1,"SI","NO") -> NO | Q65: =IF(D65="INCLUIDO",IF(F65<>0,1,0),0) -> 0 | R65: =IF(I65="%o Al Millar",1000,IF(I65="% Al Porciento",100,IF(I65="$ Prima",G65))) -> 1000 | S65: =IF(E65="Excluido",0,IF(D65="NO APLICA",0,1)) -> 1
A66: TEV | C66: =$O$12 -> 0 | D66: =$D$17 -> INCLUIDO | E66: =E65 -> Sublimite | F66: =(F65*$O$12)*S65 -> 0 | G66: =G65*0.35 -> 0.07 | H66: =((IF(I66="$ Prima",G66,G66*F66/R66))*$U$9)*O14 -> 0 | I66: %o Al Millar | J66: =H66*$U$7 -> 0 | K66: =(H66+J66)*$K$15 -> 0 | L66: =ROUND(H66+J66+K66,2) -> 0 | M66: =$M$64 -> 0.05 | N66: =H66*M66 -> 0 | O66: =N66 -> 0 | P66: =IF(Q66=1,"SI","NO") -> NO | Q66: =IF(D66="INCLUIDO",IF(F66<>0,1,0),0) -> 0 | R66: =IF(I66="%o Al Millar",1000,IF(I66="% Al Porciento",100,IF(I66="$ Prima",G66))) -> 1000 | S66: =IF(E66="Excluido",0,IF(D66="NO APLICA",0,1)) -> 1
A67: 902 | B67: 2 | C67: INCENDIO CONTENIDOS - REM ESC. | D67: =$D$17 -> INCLUIDO | F67: 0 | M67: =M41 -> 0.25 | P67: =IF(Q67=1,"SI","NO") -> NO | Q67: =IF(D67="INCLUIDO",IF(F68<>0,1,0),0) -> 0 | S67: =IF(E67="Excluido",0,IF(D67="NO APLICA",0,1)) -> 1
A68: INCENDIO | B68: 27 | C68: REMOCIÓN DE ESCOMBROS INCENDIO | D68: =$D$17 -> INCLUIDO | E68: Sublimite | F68: 0 | G68: ='COTIZACIÓN M.N.'!E63*75% -> 0.041836148 | H68: =(((IF(I68="$ Prima",G68,G68*F68/R68))*$U$9)/365)*$J$15 -> 0 | I68: %o Al Millar | J68: =H68*$U$7 -> 0 | K68: =(H68+J68)*$K$15 -> 0 | L68: =ROUND(H68+J68+K68,2) -> 0 | M68: =M67 -> 0.25 | N68: =H68*M68 -> 0 | O68: =N68 -> 0 | P68: =IF(Q68=1,"SI","NO") -> NO | Q68: =IF(D68="INCLUIDO",IF(F68<>0,1,0),0) -> 0 | R68: =IF(I68="%o Al Millar",1000,IF(I68="% Al Porciento",100,IF(I68="$ Prima",G68))) -> 1000 | S68: =IF(E68="Excluido",0,IF(D68="NO APLICA",0,1)) -> 1
A69: 903 | B69: 2 | C69: HIDROMETEOROLOGICO CONTENIDOS | D69: =$D$17 -> INCLUIDO | M69: =M61 -> 0.05 | P69: =IF(Q69=1,"SI","NO") -> NO | Q69: =IF(D69="INCLUIDO",IF(F70<>0,1,0),0) -> 0 | S69: =IF(E69="Excluido",0,IF(D69="NO APLICA",0,1)) -> 1
A70: FHM | B70: 44 | C70: REMOCIÓN DE ESCOMBROS FENÓMENOS HIDROMETEOROLÓGICOS | D70: =$D$17 -> INCLUIDO | E70: Sublimite | F70: 0 | G70: ='COTIZACIÓN M.N.'!E63*25% -> 0.013945383 | H70: =(((IF(I70="$ Prima",G70,G70*F70/R70))*$U$9)/365)*$J$15 -> 0 | I70: %o Al Millar | J70: =H70*$U$7 -> 0 | K70: =(H70+J70)*$K$15 -> 0 | L70: =ROUND(H70+J70+K70,2) -> 0 | M70: =M69 -> 0.05 | N70: =H70*M70 -> 0 | O70: =N70 -> 0 | P70: =IF(Q70=1,"SI","NO") -> NO | Q70: =IF(D70="INCLUIDO",IF(F70<>0,1,0),0) -> 0 | R70: =IF(I70="%o Al Millar",1000,IF(I70="% Al Porciento",100,IF(I70="$ Prima",G70))) -> 1000 | S70: =IF(E70="Excluido",0,IF(D70="NO APLICA",0,1)) -> 1
A71: 904 | B71: 2 | C71: TERREMOTO CONTENIDOS | D71: =$D$17 -> INCLUIDO | M71: =M64 -> 0.05 | P71: =IF(Q71=1,"SI","NO") -> NO | Q71: =IF(D71="INCLUIDO",IF(F72<>0,1,0),0) -> 0 | S71: =IF(E71="Excluido",0,IF(D71="NO APLICA",0,1)) -> 1
A72: TEV | B72: 62 | C72: REMOCIÓN DE ESCOMBROS TERREMOTO Y ERUPCIÓN VOLCÁNICA | D72: =$D$17 -> INCLUIDO | E72: Sublimite | F72: =F68*S72*O14 -> 0 | G72: ='COTIZACIÓN M.N.'!E64 -> 0.02 | H72: =(((IF(I72="$ Prima",G72,G72*F72/R72))*$U$9)/365)*$J$15 -> 0 | I72: %o Al Millar | J72: =H72*$U$7 -> 0 | K72: =(H72+J72)*$K$15 -> 0 | L72: =ROUND(H72+J72+K72,2) -> 0 | M72: =M71 -> 0.05 | N72: =H72*M72 -> 0 | O72: =N72 -> 0 | P72: =IF(Q72=1,"SI","NO") -> NO | Q72: =IF(D72="INCLUIDO",IF(F72<>0,1,0),0) -> 0 | R72: =IF(I72="%o Al Millar",1000,IF(I72="% Al Porciento",100,IF(I72="$ Prima",G72))) -> 1000 | S72: =IF(E72="Excluido",0,IF(D72="NO APLICA",0,1)) -> 1
A73: 903 | B73: 2 | C73: HIDROMETEOROLOGICO CONTENIDOS | D73: =$D$17 -> INCLUIDO | M73: =M61 -> 0.05 | P73: =IF(Q73=1,"SI","NO") -> NO | Q73: =IF(D73="INCLUIDO",IF(F74<>0,1,0),0) -> 0 | S73: =IF(E73="Excluido",0,IF(D73="NO APLICA",0,1)) -> 1
A74: FHM | B74: 027 | C74: BIENES A LA INTEMPERIE FENÓMENOS HIDROMETEOROLÓGICOS | D74: =$D$17 -> INCLUIDO | E74: Sublimite | F74: 0 | G74: 0 | H74: =(IF(I74="$ Prima",G74,G74*F74/R74))*$U$9 -> 0 | I74: %o Al Millar | J74: =H74*$U$7 -> 0 | K74: =(H74+J74)*$K$15 -> 0 | L74: =ROUND(H74+J74+K74,2) -> 0 | M74: =M73 -> 0.05 | N74: =H74*M74 -> 0 | O74: =N74 -> 0 | P74: =IF(Q74=1,"SI","NO") -> NO | Q74: =IF(D74="INCLUIDO",IF(F74<>0,1,0),0) -> 0 | R74: =IF(I74="%o Al Millar",1000,IF(I74="% Al Porciento",100,IF(I74="$ Prima",G74))) -> 1000 | S74: =IF(E74="Excluido",0,IF(D74="NO APLICA",0,1)) -> 1
A75: 904 | B75: 2 | C75: TERREMOTO CONTENIDOS | D75: =$D$17 -> INCLUIDO | M75: =M64 -> 0.05 | P75: =IF(Q75=1,"SI","NO") -> NO | Q75: =IF(D75="INCLUIDO",IF(F76<>0,1,0),0) -> 0 | S75: =IF(E75="Excluido",0,IF(D75="NO APLICA",0,1)) -> 1
A76: TEV | B76: 58 | C76: BIENES A LA INTEMPERIE TERREMOTO Y ERUPCIÓN VOLCÁNICA | D76: =$D$17 -> INCLUIDO | E76: Sublimite | F76: 0 | G76: 0 | H76: =(IF(I76="$ Prima",G76,G76*F76/R76))*$U$9 -> 0 | I76: %o Al Millar | J76: =H76*$U$7 -> 0 | K76: =(H76+J76)*$K$15 -> 0 | L76: =ROUND(H76+J76+K76,2) -> 0 | M76: =M75 -> 0.05 | N76: =H76*M76 -> 0 | O76: =N76 -> 0 | P76: =IF(Q76=1,"SI","NO") -> NO | Q76: =IF(D76="INCLUIDO",IF(F76<>0,1,0),0) -> 0 | R76: =IF(I76="%o Al Millar",1000,IF(I76="% Al Porciento",100,IF(I76="$ Prima",G76))) -> 1000 | S76: =IF(E76="Excluido",0,IF(D76="NO APLICA",0,1)) -> 1
C77: SUBTOTAL | D77: =D76 -> INCLUIDO | F77: =SUMIF(E42:E76,"Adicional",F42:F76) -> 0 | H77: =SUM(H42:H76) -> 0 | J77: =SUM(J42:J76) -> 0 | K77: =SUM(K42:K76) -> 0 | L77: =SUM(L42:L76) -> 0 | N77: =SUM(N42:N76) -> 0 | O77: =SUM(O42:O76) -> 0 | P77: =IF(Q77=1,"SI","NO") -> NO | Q77: =IF(D77="INCLUIDO",IF(H77<>0,1,0),0) -> 0
A78: 902 | B78: 003 | C78: PERDIDAS CONSECUENCIALES INCENDIO | D78: =$D$17 -> INCLUIDO | M78: =M41 -> 0.25 | P78: =IF(Q78=1,"SI","NO") -> NO | Q78: =IF(D78="INCLUIDO",IF(F79<>0,1,0),0) -> 0
A79: INCENDIO | B79: 029 | C79: GANANCIAS BRUTAS UTILIDADES INCENDIO | D79: =$D$17 -> INCLUIDO | E79: Excluido | F79: 0 | G79: 0 | H79: =(IF(I79="$ Prima",G79,G79*F79/R79))*$U$9 -> 0 | I79: %o Al Millar | J79: =H79*$U$7 -> 0 | K79: =(H79+J79)*$K$15 -> 0 | L79: =ROUND(H79+J79+K79,2) -> 0 | M79: =$M$78 -> 0.25 | N79: =H79*M79 -> 0 | O79: =N79 -> 0 | P79: =IF(Q79=1,"SI","NO") -> NO | Q79: =IF(D79="INCLUIDO",IF(F79<>0,1,0),0) -> 0 | R79: =IF(I79="%o Al Millar",1000,IF(I79="% Al Porciento",100,IF(I79="$ Prima",G79))) -> 1000 | S79: =IF(E79="Excluido",0,IF(D79="NO APLICA",0,1)) -> 0
A80: INCENDIO | B80: 034 | C80: PÉRDIDA DE UTILIDADES INCENDIO | D80: =$D$17 -> INCLUIDO | E80: Adicional | F80: 0 | G80: ='COTIZACIÓN M.N.'!E42 -> 0.24625224 | H80: =(((IF(I80="$ Prima",G80,G80*F80/R80))*$U$9)/365)*$J$15 -> 0 | I80: %o Al Millar | J80: =H80*$U$7 -> 0 | K80: =(H80+J80)*$K$15 -> 0 | L80: =ROUND(H80+J80+K80,2) -> 0 | M80: =$M$78 -> 0.25 | N80: =H80*M80 -> 0 | O80: =N80 -> 0 | P80: =IF(Q80=1,"SI","NO") -> NO | Q80: =IF(D80="INCLUIDO",IF(F80<>0,1,0),0) -> 0 | R80: =IF(I80="%o Al Millar",1000,IF(I80="% Al Porciento",100,IF(I80="$ Prima",G80))) -> 1000 | S80: =IF(E80="Excluido",0,IF(D80="NO APLICA",0,1)) -> 1
A81: INCENDIO | B81: 033 | C81: PÉRDIDA DE RENTAS UTILIDADES INCENDIO | D81: =$D$17 -> INCLUIDO | E81: Adicional | F81: 0 | G81: 0 | H81: =(IF(I81="$ Prima",G81,G81*F81/R81))*$U$9 -> 0 | I81: %o Al Millar | J81: =H81*$U$7 -> 0 | K81: =(H81+J81)*$K$15 -> 0 | L81: =ROUND(H81+J81+K81,2) -> 0 | M81: =$M$78 -> 0.25 | N81: =H81*M81 -> 0 | O81: =N81 -> 0 | P81: =IF(Q81=1,"SI","NO") -> NO | Q81: =IF(D81="INCLUIDO",IF(F81<>0,1,0),0) -> 0 | R81: =IF(I81="%o Al Millar",1000,IF(I81="% Al Porciento",100,IF(I81="$ Prima",G81))) -> 1000 | S81: =IF(E81="Excluido",0,IF(D81="NO APLICA",0,1)) -> 1
A82: INCENDIO | B82: 276 | C82: REDUCCIÓN DE INGRESOS POR INTERRUPCIÓN DE ACTIVIDADES COMERCIALES | D82: =$D$17 -> INCLUIDO | E82: Excluido | F82: 0 | G82: 0 | H82: =(IF(I82="$ Prima",G82,G82*F82/R82))*$U$9 -> 0 | I82: %o Al Millar | J82: =H82*$U$7 -> 0 | K82: =(H82+J82)*$K$15 -> 0 | L82: =ROUND(H82+J82+K82,2) -> 0 | M82: =$M$78 -> 0.25 | N82: =H82*M82 -> 0 | O82: =N82 -> 0 | P82: =IF(Q82=1,"SI","NO") -> NO | Q82: =IF(D82="INCLUIDO",IF(F82<>0,1,0),0) -> 0 | R82: =IF(I82="%o Al Millar",1000,IF(I82="% Al Porciento",100,IF(I82="$ Prima",G82))) -> 1000 | S82: =IF(E82="Excluido",0,IF(D82="NO APLICA",0,1)) -> 0
A83: INCENDIO | B83: 030 | C83: GASTOS EXTRAORDINARIOS INCENDIO | D83: =$D$17 -> INCLUIDO | E83: Sublimite | F83: 0 | G83: ='COTIZACIÓN M.N.'!E58 -> 0.11240081 | H83: =(((IF(I83="$ Prima",G83,G83*F83/R83))*$U$9)/365)*$J$15 -> 0 | I83: %o Al Millar | J83: =H83*$U$7 -> 0 | K83: =(H83+J83)*$K$15 -> 0 | L83: =ROUND(H83+J83+K83,2) -> 0 | M83: =$M$78 -> 0.25 | N83: =H83*M83 -> 0 | O83: =N83 -> 0 | P83: =IF(Q83=1,"SI","NO") -> NO | Q83: =IF(D83="INCLUIDO",IF(F83<>0,1,0),0) -> 0 | R83: =IF(I83="%o Al Millar",1000,IF(I83="% Al Porciento",100,IF(I83="$ Prima",G83))) -> 1000 | S83: =IF(E83="Excluido",0,IF(D83="NO APLICA",0,1)) -> 1
A84: INCENDIO | B84: 031 | C84: GASTOS EXTRAORDINARIOS PARA CASA HABITACIÓN INCENDIO | D84: =$D$17 -> INCLUIDO | E84: Excluido | F84: 0 | G84: 0 | H84: =(IF(I84="$ Prima",G84,G84*F84/R84))*$U$9 -> 0 | I84: %o Al Millar | J84: =H84*$U$7 -> 0 | K84: =(H84+J84)*$K$15 -> 0 | L84: =ROUND(H84+J84+K84,2) -> 0 | M84: =$M$78 -> 0.25 | N84: =H84*M84 -> 0 | O84: =N84 -> 0 | P84: =IF(Q84=1,"SI","NO") -> NO | Q84: =IF(D84="INCLUIDO",IF(F84<>0,1,0),0) -> 0 | R84: =IF(I84="%o Al Millar",1000,IF(I84="% Al Porciento",100,IF(I84="$ Prima",G84))) -> 1000 | S84: =IF(E84="Excluido",0,IF(D84="NO APLICA",0,1)) -> 0
A85: INCENDIO | B85: 032 | C85: GASTOS FIJOS Y SALARIOS INCENDIO | D85: =$D$17 -> INCLUIDO | E85: Excluido | F85: 0 | G85: 0 | H85: =(IF(I85="$ Prima",G85,G85*F85/R85))*$U$9 -> 0 | I85: %o Al Millar | J85: =H85*$U$7 -> 0 | K85: =(H85+J85)*$K$15 -> 0 | L85: =ROUND(H85+J85+K85,2) -> 0 | M85: =$M$78 -> 0.25 | N85: =H85*M85 -> 0 | O85: =N85 -> 0 | P85: =IF(Q85=1,"SI","NO") -> NO | Q85: =IF(D85="INCLUIDO",IF(F85<>0,1,0),0) -> 0 | R85: =IF(I85="%o Al Millar",1000,IF(I85="% Al Porciento",100,IF(I85="$ Prima",G85))) -> 1000 | S85: =IF(E85="Excluido",0,IF(D85="NO APLICA",0,1)) -> 0
A86: INCENDIO | B86: 036 | C86: SEGURO CONTINGENTE UTILIDADES INCENDIO | D86: =$D$17 -> INCLUIDO | E86: Excluido | F86: 0 | G86: 0 | H86: =(IF(I86="$ Prima",G86,G86*F86/R86))*$U$9 -> 0 | I86: %o Al Millar | J86: =H86*$U$7 -> 0 | K86: =(H86+J86)*$K$15 -> 0 | L86: =ROUND(H86+J86+K86,2) -> 0 | M86: =$M$78 -> 0.25 | N86: =H86*M86 -> 0 | O86: =N86 -> 0 | P86: =IF(Q86=1,"SI","NO") -> NO | Q86: =IF(D86="INCLUIDO",IF(F86<>0,1,0),0) -> 0 | R86: =IF(I86="%o Al Millar",1000,IF(I86="% Al Porciento",100,IF(I86="$ Prima",G86))) -> 1000 | S86: =IF(E86="Excluido",0,IF(D86="NO APLICA",0,1)) -> 0
A87: INCENDIO | B87: 277 | C87: CLÁUSULA DE OBSTRUCCIÓN DE ACCESO | D87: =$D$17 -> INCLUIDO | E87: Excluido | F87: 0 | G87: 0 | H87: =(IF(I87="$ Prima",G87,G87*F87/R87))*$U$9 -> 0 | I87: %o Al Millar | J87: =H87*$U$7 -> 0 | K87: =(H87+J87)*$K$15 -> 0 | L87: =ROUND(H87+J87+K87,2) -> 0 | M87: =$M$78 -> 0.25 | N87: =H87*M87 -> 0 | O87: =N87 -> 0 | P87: =IF(Q87=1,"SI","NO") -> NO | Q87: =IF(D87="INCLUIDO",IF(F87<>0,1,0),0) -> 0 | R87: =IF(I87="%o Al Millar",1000,IF(I87="% Al Porciento",100,IF(I87="$ Prima",G87))) -> 1000 | S87: =IF(E87="Excluido",0,IF(D87="NO APLICA",0,1)) -> 0
A88: INCENDIO | B88: 278 | C88: CLÁUSULA DE ENFERMEDADES INFECCIOSAS | D88: =$D$17 -> INCLUIDO | E88: Excluido | F88: 0 | G88: 0 | H88: =(IF(I88="$ Prima",G88,G88*F88/R88))*$U$9 -> 0 | I88: %o Al Millar | J88: =H88*$U$7 -> 0 | K88: =(H88+J88)*$K$15 -> 0 | L88: =ROUND(H88+J88+K88,2) -> 0 | M88: =$M$78 -> 0.25 | N88: =H88*M88 -> 0 | O88: =N88 -> 0 | P88: =IF(Q88=1,"SI","NO") -> NO | Q88: =IF(D88="INCLUIDO",IF(F88<>0,1,0),0) -> 0 | R88: =IF(I88="%o Al Millar",1000,IF(I88="% Al Porciento",100,IF(I88="$ Prima",G88))) -> 1000 | S88: =IF(E88="Excluido",0,IF(D88="NO APLICA",0,1)) -> 0
A89: INCENDIO | B89: 279 | C89: INTERRUPCIÓN POR ACTOS DE AUTORIDAD | D89: =$D$17 -> INCLUIDO | E89: Excluido | F89: 0 | G89: 0 | H89: =(IF(I89="$ Prima",G89,G89*F89/R89))*$U$9 -> 0 | I89: %o Al Millar | J89: =H89*$U$7 -> 0 | K89: =(H89+J89)*$K$15 -> 0 | L89: =ROUND(H89+J89+K89,2) -> 0 | M89: =$M$78 -> 0.25 | N89: =H89*M89 -> 0 | O89: =N89 -> 0 | P89: =IF(Q89=1,"SI","NO") -> NO | Q89: =IF(D89="INCLUIDO",IF(F89<>0,1,0),0) -> 0 | R89: =IF(I89="%o Al Millar",1000,IF(I89="% Al Porciento",100,IF(I89="$ Prima",G89))) -> 1000 | S89: =IF(E89="Excluido",0,IF(D89="NO APLICA",0,1)) -> 0
A90: 903 | B90: 3 | C90: PERDIDAS CONSECUENCIALES FHM | D90: =$D$17 -> INCLUIDO | M90: =M61 -> 0.05 | P90: =IF(Q90=1,"SI","NO") -> NO | Q90: =IF(D90="INCLUIDO",IF(F91<>0,1,0),0) -> 0
A91: FHM | B91: 50 | C91: GASTOS FIJOS Y SALARIOS RIESGOS HIDROMETEOROLÓGICOS | D91: =$D$17 -> INCLUIDO | E91: Sublimite | F91: 0 | G91: ='COTIZACIÓN M.N.'!E43 -> 0.2 | H91: =(((IF(I91="$ Prima",G91,G91*F91/R91))*$U$9)/365)*$J$15 -> 0 | I91: %o Al Millar | J91: =H91*$U$7 -> 0 | K91: =(H91+J91)*$K$15 -> 0 | L91: =ROUND(H91+J91+K91,2) -> 0 | M91: =$M$90 -> 0.05 | N91: =H91*M91 -> 0 | O91: =N91 -> 0 | P91: =IF(Q91=1,"SI","NO") -> NO | Q91: =IF(D91="INCLUIDO",IF(F91<>0,1,0),0) -> 0 | R91: =IF(I91="%o Al Millar",1000,IF(I91="% Al Porciento",100,IF(I91="$ Prima",G91))) -> 1000 | S91: =IF(E91="Excluido",0,IF(D91="NO APLICA",0,1)) -> 1
A92: FHM | B92: 49 | C92: GASTOS EXTRAORDINARIOS RIESGOS HIDROMETEOROLÓGICOS | D92: =$D$17 -> INCLUIDO | E92: Sublimite | F92: 0 | G92: ='COTIZACIÓN M.N.'!E59 -> 0.091289165 | H92: =(((IF(I92="$ Prima",G92,G92*F92/R92))*$U$9)/365)*$J$15 -> 0 | I92: %o Al Millar | J92: =H92*$U$7 -> 0 | K92: =(H92+J92)*$K$15 -> 0 | L92: =ROUND(H92+J92+K92,2) -> 0 | M92: =$M$90 -> 0.05 | N92: =H92*M92 -> 0 | O92: =N92 -> 0 | P92: =IF(Q92=1,"SI","NO") -> NO | Q92: =IF(D92="INCLUIDO",IF(F92<>0,1,0),0) -> 0 | R92: =IF(I92="%o Al Millar",1000,IF(I92="% Al Porciento",100,IF(I92="$ Prima",G92))) -> 1000 | S92: =IF(E92="Excluido",0,IF(D92="NO APLICA",0,1)) -> 1
A93: FHM | B93: 48 | C93: GASTOS EXTRAORD. HABITACIÓN RIESGOS HIDROMETEOROLÓGICOS | D93: =$D$17 -> INCLUIDO | E93: Excluido | F93: 0 | G93: 0 | H93: =(IF(I93="$ Prima",G93,G93*F93/R93))*$U$9 -> 0 | I93: %o Al Millar | J93: =H93*$U$7 -> 0 | K93: =(H93+J93)*$K$15 -> 0 | L93: =ROUND(H93+J93+K93,2) -> 0 | M93: =$M$90 -> 0.05 | N93: =H93*M93 -> 0 | O93: =N93 -> 0 | P93: =IF(Q93=1,"SI","NO") -> NO | Q93: =IF(D93="INCLUIDO",IF(F93<>0,1,0),0) -> 0 | R93: =IF(I93="%o Al Millar",1000,IF(I93="% Al Porciento",100,IF(I93="$ Prima",G93))) -> 1000 | S93: =IF(E93="Excluido",0,IF(D93="NO APLICA",0,1)) -> 0
A94: FHM | B94: 47 | C94: AMENAZA DE HURACÁN | D94: =$D$17 -> INCLUIDO | E94: Excluido | F94: 0 | G94: 0 | H94: =(IF(I94="$ Prima",G94,G94*F94/R94))*$U$9 -> 0 | I94: %o Al Millar | J94: =H94*$U$7 -> 0 | K94: =(H94+J94)*$K$15 -> 0 | L94: =ROUND(H94+J94+K94,2) -> 0 | M94: =$M$90 -> 0.05 | N94: =H94*M94 -> 0 | O94: =N94 -> 0 | P94: =IF(Q94=1,"SI","NO") -> NO | Q94: =IF(D94="INCLUIDO",IF(F94<>0,1,0),0) -> 0 | R94: =IF(I94="%o Al Millar",1000,IF(I94="% Al Porciento",100,IF(I94="$ Prima",G94))) -> 1000 | S94: =IF(E94="Excluido",0,IF(D94="NO APLICA",0,1)) -> 0
A95: 904 | B95: 3 | C95: PERDIDAS CONSECUENCIALES TEV | D95: =$D$17 -> INCLUIDO | M95: =M64 -> 0.05 | P95: =IF(Q95=1,"SI","NO") -> NO | Q95: =IF(D95="INCLUIDO",IF(F96<>0,1,0),0) -> 0
A96: TEV | B96: 68 | C96: GASTOS FIJOS Y SALARIOS TERREMOTO Y ERUPCION VOLCANICA | D96: =$D$17 -> INCLUIDO | E96: Sublimite | F96: 0 | G96: ='COTIZACIÓN M.N.'!E44 -> 0.32 | H96: =(((IF(I96="$ Prima",G96,G96*F96/R96))*$U$9)/365)*$J$15 -> 0 | I96: %o Al Millar | J96: =H96*$U$7 -> 0 | K96: =(H96+J96)*$K$15 -> 0 | L96: =ROUND(H96+J96+K96,2) -> 0 | M96: =$M$95 -> 0.05 | N96: =H96*M96 -> 0 | O96: =N96 -> 0 | P96: =IF(Q96=1,"SI","NO") -> NO | Q96: =IF(D96="INCLUIDO",IF(F96<>0,1,0),0) -> 0 | R96: =IF(I96="%o Al Millar",1000,IF(I96="% Al Porciento",100,IF(I96="$ Prima",G96))) -> 1000 | S96: =IF(E96="Excluido",0,IF(D96="NO APLICA",0,1)) -> 1
A97: TEV | B97: 67 | C97: GASTOS EXTRAORDINARIOS TERREMOTO Y ERUPCIÓN VOLCÁNICA | D97: =$D$17 -> INCLUIDO | E97: Sublimite | F97: 0 | G97: ='COTIZACIÓN M.N.'!E60 -> 0.073044399 | H97: =(((IF(I97="$ Prima",G97,G97*F97/R97))*$U$9)/365)*$J$15 -> 0 | I97: %o Al Millar | J97: =H97*$U$7 -> 0 | K97: =(H97+J97)*$K$15 -> 0 | L97: =ROUND(H97+J97+K97,2) -> 0 | M97: =$M$95 -> 0.05 | N97: =H97*M97 -> 0 | O97: =N97 -> 0 | P97: =IF(Q97=1,"SI","NO") -> NO | Q97: =IF(D97="INCLUIDO",IF(F97<>0,1,0),0) -> 0 | R97: =IF(I97="%o Al Millar",1000,IF(I97="% Al Porciento",100,IF(I97="$ Prima",G97))) -> 1000 | S97: =IF(E97="Excluido",0,IF(D97="NO APLICA",0,1)) -> 1
A98: TEV | B98: 65 | C98: GASTOS EXTRAORDINARIOS CASA HABITACIÓN TERREMOTO Y ERUPCIÓN VOLCÁNICA | D98: =$D$17 -> INCLUIDO | E98: Excluido | F98: 0 | G98: 0 | H98: =(IF(I98="$ Prima",G98,G98*F98/R98))*$U$9 -> 0 | I98: %o Al Millar | J98: =H98*$U$7 -> 0 | K98: =(H98+J98)*$K$15 -> 0 | L98: =ROUND(H98+J98+K98,2) -> 0 | M98: =$M$95 -> 0.05 | N98: =H98*M98 -> 0 | O98: =N98 -> 0 | P98: =IF(Q98=1,"SI","NO") -> NO | Q98: =IF(D98="INCLUIDO",IF(F98<>0,1,0),0) -> 0 | R98: =IF(I98="%o Al Millar",1000,IF(I98="% Al Porciento",100,IF(I98="$ Prima",G98))) -> 1000 | S98: =IF(E98="Excluido",0,IF(D98="NO APLICA",0,1)) -> 0
C99: SUBTOTAL | D99: =D98 -> INCLUIDO | F99: =SUMIF(E79:E98,"Adicional",F79:F98) -> 0 | H99: =SUM(H79:H98) -> 0 | J99: =SUM(J79:J98) -> 0 | K99: =SUM(K79:K98) -> 0 | L99: =SUM(L79:L98) -> 0 | N99: =SUM(N79:N98) -> 0 | O99: =SUM(O79:O98) -> 0 | P99: =IF(Q99=1,"SI","NO") -> NO | Q99: =IF(D99="INCLUIDO",IF(H99<>0,1,0),0) -> 0
A100: 905 | B100: 1 | C100: CRISTALES | D100: ='Ramo Comercial'!C130 -> INCLUIDO | F100: 0 | G100: ='COTIZACIÓN M.N.'!E86 -> 5 | M100: 0.058 | P100: =IF(Q100=1,"SI","NO") -> NO | Q100: =IF(D100="INCLUIDO",IF(F100<>0,1,0),0) -> 0 | S100: =IF(E100="Excluido",0,IF(D100="NO APLICA",0,1)) -> 1
A101: D.MISC. | B101: 71 | C101: ROTURA ACCIDENTAL DE CRISTALES | D101: =$D$100 -> INCLUIDO | E101: Adicional | F101: =F100*S101 -> 0 | G101: =G100 -> 5 | H101: =(((IF(I101="$ Prima",G101,G101*F101/R101))*$U$9)/365)*$J$15 -> 0 | I101: % Al Porciento | J101: =H101*$U$7 -> 0 | K101: =(H101+J101)*$K$15 -> 0 | L101: =ROUND(H101+J101+K101,2) -> 0 | M101: =$M$100 -> 0.058 | N101: =H101*M101 -> 0 | O101: =N101 -> 0 | P101: =IF(Q101=1,"SI","NO") -> NO | Q101: =IF(D101="INCLUIDO",IF(F101<>0,1,0),0) -> 0 | R101: =IF(I101="%o Al Millar",1000,IF(I101="% Al Porciento",100,IF(I101="$ Prima",G101))) -> 100 | S101: =IF(E101="Excluido",0,IF(D101="NO APLICA",0,1)) -> 1
...

Sheet Hoja Contable
S1: 3 | T1: =VLOOKUP(S1,S2:T5,2) -> TRIMESTRAL | U1: =IF(F13="NACIONAL",1,2) -> 2 | V1: =F13 -> DÓLARES
S2: 1 | T2: CONTADO | U2: 0 | V2: 0
S3: 2 | T3: SEMESTRAL | U3: 0.042 | V3: 0.014
S4: 3 | T4: TRIMESTRAL | U4: 0.064 | V4: 0.0211
A5: HOJA CONTABLE | S5: 4 | T5: MENSUAL | U5: 0.077 | V5: 0.0258
A7: RAMO COMERCIAL | C7: 20 - SME 1ER RIESGO - ESPARCIMIENTO | K7: =MID(C7,1,2)*1 -> 20 | L7: POLIZA A PRIMER RIESGO | S7: Recargo Forma de Pago: | U7: =VLOOKUP(S1,S2:V5,U1+2) -> 0.0211
A8: GIRO | C8: 0590-ESPECTÁCULOS PÚBLICOS, CINES, TEATROS, PARQUES DE DIVERSIÓN, CASINOS Y/O SIMILARES | F8: SUBGIRO | G8: 0590.05-Cines | L8: =Hoja3!A8
A9: ASEGURADO | C9: OPERADORA DE CINEMAS SA DE CV | J9: COD. ASEG. | K9: 0 | L9: TIPO DE MOVIMIENTO | N9: POLIZA NUEVA | S9: Factor Prorrata: | U9: =IF(H14="DIRECTA",1,J15/I15) -> 1
A10: DIRECCIÓN FISCAL | C10: JAVIER BARROS SIERRA 540 TORRE 1 PH1 COL SANTA FE ALVARO OBREGON CDMX CP 01210 | L10: TIPO DE PÓLIZA | N10: TODO RIESGO
A11: DIRECCIÓN DEL RIESGO | C11: =C10 -> JAVIER BARROS SIERRA 540 TORRE 1 PH1 COL SANTA FE ALVARO OBREGON CDMX CP 01210 | L11: ZONA TEV | M11: ='COTIZACIÓN M.N.'!G13 -> A | N11: ZONA F.H.M. | O11: ='COTIZACIÓN M.N.'!G17 -> A1PS
A12: VIG. INICIO | C12: 45107 | D12: T. DE RIESGO: | F12: ORDINARIO | G12: AGENTE | H12: MARSH | K12: 1 | L12: REM. ESC. | M12: ='COTIZACIÓN M.N.'!G15 -> 0.2 | N12: Indice Variable | O12: ='COTIZACIÓN M.N.'!G16 -> 0
A13: VIG. FINAL | C13: 45473 | D13: MONEDA | F13: DÓLARES | G13: R.F.C. | H13: OCI970818KX9 | J13: DÍAS DE VIGENCIA | N13: Coaseguro FHM | O13: =100%-'COTIZACIÓN M.N.'!G18 -> 1
A14: PÓLIZA | C14: POLIZA NUEVA | D14: F. PAGO | G14: CALCULO | H14: DIRECTA | K14: IVA | N14: Coaseguro TEV | O14: =100%-'COTIZACIÓN M.N.'!G14 -> 1
C15: 1 | I15: 365 | J15: =C13-C12 -> 366 | K15: 0.16
A16: COD. RAMO TECNICO | B16: SECCIÓN / COB. | C16: SECCIÓN / COBERTURA | D16: S/N | E16: Sublimite | F16: SUMA ASEGURADA | G16: CUOTAS | H16: PRIMA | I16: METODO DE CALCULO | J16: REC. PAGO FRACC. | K16: IVA | L16: PRIMA TOTAL | M16: COM. % | N16: COMISIÓN | O16: COMISIÓN TOTAL | P16: FILTRO
A17: 902 | B17: 001 | C17: INCENDIO EDIFICIO | D17: ='Ramo Comercial'!C121 -> INCLUIDO | F17: ='COTIZACIÓN M.N.'!D24 -> 155549.7 | G17: ='COTIZACIÓN M.N.'!E24+'COTIZACIÓN M.N.'!E25+'COTIZACIÓN M.N.'!E26 -> 0.3078153 | M17: 0.1201 | P17: =IF(Q17=1,"SI","NO") -> SI | Q17: =IF(D17="INCLUIDO",IF(F17<>0,1,0),0) -> 1 | T17: =G17 -> 0.3078153
A18: INCENDIO | B18: 001 | C18: COBERTURA BÁSICA | D18: =$D$17 -> INCLUIDO | E18: Sublimite | F18: =$F$17*S18 -> 155549.7 | G18: =V18 -> 0.24625224 | H18: =(((IF(I18="$ Prima",G18,G18*F18/R18))*$U$9)/365)*$J$15 -> 38.409406 | I18: %o Al Millar | J18: =H18*$U$7 -> 0.81043846 | K18: =(H18+J18)*$K$15 -> 6.2751751 | L18: =ROUND(H18+J18+K18,2) -> 45.5 | M18: =$M$17 -> 0.1201 | N18: =H18*M18 -> 4.6129696 | O18: =N18 -> 4.6129696 | P18: =IF(Q18=1,"SI","NO") -> SI | Q18: =IF(D18="INCLUIDO",IF(F18<>0,1,0),0) -> 1 | R18: =IF(I18="%o Al Millar",1000,IF(I18="% Al Porciento",100,IF(I18="$ Prima",G18))) -> 1000 | S18: =IF(E18="Excluido",0,IF(D18="NO APLICA",0,1)) -> 1 | T18: 0.8 | U18: =IF(E18="Excluido",0,T17*T18) -> 0.24625224 | V18: =IF(F17=0,0,(U23-U22-U20)+(T17-U23)) -> 0.24625224 | W18: ='UB (1)'!H18+'UB (2)'!H18+'UB (3)'!H18+#REF!+#REF!+#REF!+#REF!+#REF!+#REF!+#REF!+#REF!+#REF!+#REF!+#REF!+#REF!+#REF!+#REF!+#REF!+#REF!+#REF!+#REF!+#REF!+#REF!+#REF!+#REF!+#REF!+#REF!+#REF!+#REF!+#REF!+#REF!+#REF!+#REF!+#REF!+#REF!+#REF!+#REF!+#REF!+#REF!+#REF!+#REF!+#REF!+#REF!+#REF!+#REF!+#REF!+#REF!+#REF!+#REF!+#REF!+#REF!+#REF!+#REF!+#REF!+#REF!+#REF!+#REF!+#REF!+#REF!+#REF!+#REF!+#REF!+#REF!+#REF!+#REF!+#REF!+#REF!+#REF!+#REF!+#REF!+#REF!+#REF!+#REF!+#REF!+#REF!+#REF!+#REF!+#REF!+#REF!+#REF!+#REF!+#REF!+#REF!+#REF!+#REF!+#REF!+#REF!+#REF!+#REF!+#REF!+#REF!+#REF!+#REF!+#REF!+#REF!+#REF!+#REF!+#REF!+#REF!+#REF!+#REF!+#REF!+#REF!+#REF!+#REF!+#REF!+#REF!+#REF!+#REF!+#REF!+#REF!+#REF!+#REF!+#REF!+#REF!+#REF!+#REF!+#REF!+#REF!+#REF!+#REF!+#REF!+#REF!+#REF!+#REF!+#REF!+#REF!+#REF!+#REF!+#REF!+#REF!+#REF!+#REF!+#REF!+#REF!+#REF!+#REF!+#REF!+#REF!+#REF!+#REF!+#REF!+#REF!+#REF!+#REF!+#REF!+#REF!+#REF!+#REF!+#REF!+#REF!+#REF!+#REF!+#REF!+#REF!+#REF!+#REF!+#REF!+#REF!+#REF!+#REF!+#REF!+#REF!+#REF!+#REF!+#REF!+#REF!+#REF!+#REF!+#REF!+#REF!+#REF!+#REF!+#REF!+#REF!+#REF!+#REF!+#REF!+#REF!+#REF!+#REF!+#REF!+#REF!+#REF!+#REF!+#REF!+#REF!+#REF!+#REF!+#REF!+#REF!+#REF!+#REF!+#REF!+#REF!+#REF!+#REF!+#REF!+#REF!+#REF!+#REF!+#REF!+#REF!+#REF!+#REF!+#REF!+#REF!+#REF!+#REF!+#REF!+#REF!+#REF!+#REF!+#REF!+#REF!+#REF!+#REF!+#REF!+#REF!+#REF!+#REF!+#REF!+#REF!+#REF!+#REF!+#REF!+#REF!+#REF!+#REF!+#REF!+#REF!+#REF!+#REF!+#REF!+#REF!+#REF!+#REF!+#REF!+#REF!+#REF!+#REF!+#REF!+#REF!+#REF!+#REF!+#REF!+#REF!+#REF!+#REF!+#REF!+#REF!+#REF!+#REF!+#REF!+#REF!+#REF!+#REF!+#REF!+#REF!+#REF!+#REF!+#REF!+#REF!+#REF!+#REF!+#REF!+#REF!+#REF!+#REF!+#REF!+#REF!+#REF!+#REF!+#REF!+#REF!+#REF!+#REF!+#REF!+#REF!+#REF!+#REF!+#REF!+#REF!+#REF!+#REF!+#REF!+#REF!+#REF!+#REF!+#REF!+#REF!+#REF!+#REF!+#REF!+#REF!+#REF!+#REF!+#REF!+#REF!+#REF!+#REF!+#REF!+#REF!+#REF!+#REF!+#REF!+#REF!+#REF!+#REF!+#REF!+#REF!+#REF!+#REF!+#REF!+#REF!+#REF!+#REF!+#REF!+#REF!+#REF!+#REF!+#REF!+#REF!+#REF!+#REF!+#REF!+#REF!+#REF!+#REF!+#REF!+#REF!+#REF!+#REF!+#REF!+#REF!+#REF!+#REF!+#REF!+#REF!+#REF!+#REF!+#REF!+#REF!+#REF!+#REF!+#REF!+#REF!+#REF!+#REF!+#REF!+#REF!+#REF!+#REF!+#REF!+#REF!+#REF!+#REF!+#REF!+#REF!+#REF!+#REF!+#REF!+#REF!+#REF! -> #REF!
A19: INCENDIO | C19: =$O$12 -> 0 | D19: =$D$17 -> INCLUIDO | E19: Adicional | F19: =(F18*$O$12)*S19 -> 0 | G19: =G18*0.35 -> 0.086188284 | H19: =(IF(I19="$ Prima",G19,G19*F19/R19))*$U$9 -> 0 | I19: %o Al Millar | J19: =H19*$U$7 -> 0 | K19: =(H19+J19)*$K$15 -> 0 | L19: =ROUND(H19+J19+K19,2) -> 0 | M19: =$M$17 -> 0.1201 | N19: =H19*M19 -> 0 | O19: =N19 -> 0 | P19: =IF(Q19=1,"SI","NO") -> NO | Q19: =IF(D19="INCLUIDO",IF(F19<>0,1,0),0) -> 0 | R19: =IF(I19="%o Al Millar",1000,IF(I19="% Al Porciento",100,IF(I19="$ Prima",G19))) -> 1000 | S19: =IF(E19="Excluido",0,IF(D19="NO APLICA",0,1)) -> 1
A20: INCENDIO | B20: 002 | C20: EXTENSIÓN DE CUBIERTA (SIN HURACÁN Y GRANIZO) | D20: =$D$17 -> INCLUIDO | E20: Sublimite | F20: =$F$17*S20 -> 155549.7 | G20: =V20 -> 0.03078153 | H20: =(((IF(I20="$ Prima",G20,G20*F20/R20))*$U$9)/365)*$J$15 -> 4.8011757 | I20: %o Al Millar | J20: =H20*$U$7 -> 0.10130481 | K20: =(H20+J20)*$K$15 -> 0.78439689 | L20: =ROUND(H20+J20+K20,2) -> 5.69 | M20: =$M$17 -> 0.1201 | N20: =H20*M20 -> 0.5766212 | O20: =N20 -> 0.5766212 | P20: =IF(Q20=1,"SI","NO") -> SI | Q20: =IF(D20="INCLUIDO",IF(F20<>0,1,0),0) -> 1 | R20: =IF(I20="%o Al Millar",1000,IF(I20="% Al Porciento",100,IF(I20="$ Prima",G20))) -> 1000 | S20: =IF(E20="Excluido",0,IF(D20="NO APLICA",0,1)) -> 1 | T20: 0.1 | U20: =IF(E20="Excluido",0,T17*T20) -> 0.03078153 | V20: =IF(F$17=0,0,U20) -> 0.03078153 | W20: ='UB (1)'!H20+'UB (2)'!H20+'UB (3)'!H20+#REF!+#REF!+#REF!+#REF!+#REF!+#REF!+#REF!+#REF!+#REF!+#REF!+#REF!+#REF!+#REF!+#REF!+#REF!+#REF!+#REF!+#REF!+#REF!+#REF!+#REF!+#REF!+#REF!+#REF!+#REF!+#REF!+#REF!+#REF!+#REF!+#REF!+#REF!+#REF!+#REF!+#REF!+#REF!+#REF!+#REF!+#REF!+#REF!+#REF!+#REF!+#REF!+#REF!+#REF!+#REF!+#REF!+#REF!+#REF!+#REF!+#REF!+#REF!+#REF!+#REF!+#REF!+#REF!+#REF!+#REF!+#REF!+#REF!+#REF!+#REF!+#REF!+#REF!+#REF!+#REF!+#REF!+#REF!+#REF!+#REF!+#REF!+#REF!+#REF!+#REF!+#REF!+#REF!+#REF!+#REF!+#REF!+#REF!+#REF!+#REF!+#REF!+#REF!+#REF!+#REF!+#REF!+#REF!+#REF!+#REF!+#REF!+#REF!+#REF!+#REF!+#REF!+#REF!+#REF!+#REF!+#REF!+#REF!+#REF!+#REF!+#REF!+#REF!+#REF!+#REF!+#REF!+#REF!+#REF!+#REF!+#REF!+#REF!+#REF!+#REF!+#REF!+#REF!+#REF!+#REF!+#REF!+#REF!+#REF!+#REF!+#REF!+#REF!+#REF!+#REF!+#REF!+#REF!+#REF!+#REF!+#REF!+#REF!+#REF!+#REF!+#REF!+#REF!+#REF!+#REF!+#REF!+#REF!+#REF!+#REF!+#REF!+#REF!+#REF!+#REF!+#REF!+#REF!+#REF!+#REF!+#REF!+#REF!+#REF!+#REF!+#REF!+#REF!+#REF!+#REF!+#REF!+#REF!+#REF!+#REF!+#REF!+#REF!+#REF!+#REF!+#REF!+#REF!+#REF!+#REF!+#REF!+#REF!+#REF!+#REF!+#REF!+#REF!+#REF!+#REF!+#REF!+#REF!+#REF!+#REF!+#REF!+#REF!+#REF!+#REF!+#REF!+#REF!+#REF!+#REF!+#REF!+#REF!+#REF!+#REF!+#REF!+#REF!+#REF!+#REF!+#REF!+#REF!+#REF!+#REF!+#REF!+#REF!+#REF!+#REF!+#REF!+#REF!+#REF!+#REF!+#REF!+#REF!+#REF!+#REF!+#REF!+#REF!+#REF!+#REF!+#REF!+#REF!+#REF!+#REF!+#REF!+#REF!+#REF!+#REF!+#REF!+#REF!+#REF!+#REF!+#REF!+#REF!+#REF!+#REF!+#REF!+#REF!+#REF!+#REF!+#REF!+#REF!+#REF!+#REF!+#REF!+#REF!+#REF!+#REF!+#REF!+#REF!+#REF!+#REF!+#REF!+#REF!+#REF!+#REF!+#REF!+#REF!+#REF!+#REF!+#REF!+#REF!+#REF!+#REF!+#REF!+#REF!+#REF!+#REF!+#REF!+#REF!+#REF!+#REF!+#REF!+#REF!+#REF!+#REF!+#REF!+#REF!+#REF!+#REF!+#REF!+#REF!+#REF!+#REF!+#REF!+#REF!+#REF!+#REF!+#REF!+#REF!+#REF!+#REF!+#REF!+#REF!+#REF!+#REF!+#REF!+#REF!+#REF!+#REF!+#REF!+#REF!+#REF!+#REF!+#REF!+#REF!+#REF!+#REF!+#REF!+#REF!+#REF!+#REF!+#REF!+#REF!+#REF!+#REF!+#REF!+#REF!+#REF!+#REF!+#REF!+#REF!+#REF!+#REF!+#REF!+#REF!+#REF!+#REF!+#REF!+#REF!+#REF!+#REF!+#REF!+#REF!+#REF!+#REF!+#REF!+#REF!+#REF!+#REF!+#REF!+#REF!+#REF!+#REF!+#REF!+#REF!+#REF!+#REF!+#REF!+#REF!+#REF!+#REF!+#REF!+#REF!+#REF!+#REF!+#REF!+#REF!+#REF!+#REF!+#REF!+#REF!+#REF!+#REF! -> #REF!
A21: INCENDIO | C21: =$O$12 -> 0 | D21: =$D$17 -> INCLUIDO | E21: =E20 -> Sublimite | F21: =(F20*$O$12)*S21 -> 0 | G21: =G20*0.35 -> 0.010773536 | H21: =(IF(I21="$ Prima",G21,G21*F21/R21))*$U$9 -> 0 | I21: %o Al Millar | J21: =H21*$U$7 -> 0 | K21: =(H21+J21)*$K$15 -> 0 | L21: =ROUND(H21+J21+K21,2) -> 0 | M21: =$M$17 -> 0.1201 | N21: =H21*M21 -> 0 | O21: =N21 -> 0 | P21: =IF(Q21=1,"SI","NO") -> NO | Q21: =IF(D21="INCLUIDO",IF(F21<>0,1,0),0) -> 0 | R21: =IF(I21="%o Al Millar",1000,IF(I21="% Al Porciento",100,IF(I21="$ Prima",G21))) -> 1000 | S21: =IF(E21="Excluido",0,IF(D21="NO APLICA",0,1)) -> 1
A22: INCENDIO | B22: 012 | C22: TODO RIESGO | D22: =$D$17 -> INCLUIDO | E22: Sublimite | F22: ='COTIZACIÓN M.N.'!D26 -> 155549.7 | G22: =V22 -> 0.03078153 | H22: =(((IF(I22="$ Prima",G22,G22*F22/R22))*$U$9)/365)*$J$15 -> 4.8011757 | I22: %o Al Millar | J22: =H22*$U$7 -> 0.10130481 | K22: =(H22+J22)*$K$15 -> 0.78439689 | L22: =ROUND(H22+J22+K22,2) -> 5.69 | M22: =$M$17 -> 0.1201 | N22: =H22*M22 -> 0.5766212 | O22: =N22 -> 0.5766212 | P22: =IF(Q22=1,"SI","NO") -> SI | Q22: =IF(D22="INCLUIDO",IF(F22<>0,1,0),0) -> 1 | R22: =IF(I22="%o Al Millar",1000,IF(I22="% Al Porciento",100,IF(I22="$ Prima",G22))) -> 1000 | S22: =IF(E22="Excluido",0,IF(D22="NO APLICA",0,1)) -> 1 | T22: 0.1 | U22: =IF(E22="Excluido",0,T17*T22) -> 0.03078153 | V22: =IF(F$17=0,0,U22) -> 0.03078153 | W22: ='UB (1)'!H22+'UB (2)'!H22+'UB (3)'!H22+#REF!+#REF!+#REF!+#REF!+#REF!+#REF!+#REF!+#REF!+#REF!+#REF!+#REF!+#REF!+#REF!+#REF!+#REF!+#REF!+#REF!+#REF!+#REF!+#REF!+#REF!+#REF!+#REF!+#REF!+#REF!+#REF!+#REF!+#REF!+#REF!+#REF!+#REF!+#REF!+#REF!+#REF!+#REF!+#REF!+#REF!+#REF!+#REF!+#REF!+#REF!+#REF!+#REF!+#REF!+#REF!+#REF!+#REF!+#REF!+#REF!+#REF!+#REF!+#REF!+#REF!+#REF!+#REF!+#REF!+#REF!+#REF!+#REF!+#REF!+#REF!+#REF!+#REF!+#REF!+#REF!+#REF!+#REF!+#REF!+#REF!+#REF!+#REF!+#REF!+#REF!+#REF!+#REF!+#REF!+#REF!+#REF!+#REF!+#REF!+#REF!+#REF!+#REF!+#REF!+#REF!+#REF!+#REF!+#REF!+#REF!+#REF!+#REF!+#REF!+#REF!+#REF!+#REF!+#REF!+#REF!+#REF!+#REF!+#REF!+#REF!+#REF!+#REF!+#REF!+#REF!+#REF!+#REF!+#REF!+#REF!+#REF!+#REF!+#REF!+#REF!+#REF!+#REF!+#REF!+#REF!+#REF!+#REF!+#REF!+#REF!+#REF!+#REF!+#REF!+#REF!+#REF!+#REF!+#REF!+#REF!+#REF!+#REF!+#REF!+#REF!+#REF!+#REF!+#REF!+#REF!+#REF!+#REF!+#REF!+#REF!+#REF!+#REF!+#REF!+#REF!+#REF!+#REF!+#REF!+#REF!+#REF!+#REF!+#REF!+#REF!+#REF!+#REF!+#REF!+#REF!+#REF!+#REF!+#REF!+#REF!+#REF!+#REF!+#REF!+#REF!+#REF!+#REF!+#REF!+#REF!+#REF!+#REF!+#REF!+#REF!+#REF!+#REF!+#REF!+#REF!+#REF!+#REF!+#REF!+#REF!+#REF!+#REF!+#REF!+#REF!+#REF!+#REF!+#REF!+#REF!+#REF!+#REF!+#REF!+#REF!+#REF!+#REF!+#REF!+#REF!+#REF!+#REF!+#REF!+#REF!+#REF!+#REF!+#REF!+#REF!+#REF!+#REF!+#REF!+#REF!+#REF!+#REF!+#REF!+#REF!+#REF!+#REF!+#REF!+#REF!+#REF!+#REF!+#REF!+#REF!+#REF!+#REF!+#REF!+#REF!+#REF!+#REF!+#REF!+#REF!+#REF!+#REF!+#REF!+#REF!+#REF!+#REF!+#REF!+#REF!+#REF!+#REF!+#REF!+#REF!+#REF!+#REF!+#REF!+#REF!+#REF!+#REF!+#REF!+#REF!+#REF!+#REF!+#REF!+#REF!+#REF!+#REF!+#REF!+#REF!+#REF!+#REF!+#REF!+#REF!+#REF!+#REF!+#REF!+#REF!+#REF!+#REF!+#REF!+#REF!+#REF!+#REF!+#REF!+#REF!+#REF!+#REF!+#REF!+#REF!+#REF!+#REF!+#REF!+#REF!+#REF!+#REF!+#REF!+#REF!+#REF!+#REF!+#REF!+#REF!+#REF!+#REF!+#REF!+#REF!+#REF!+#REF!+#REF!+#REF!+#REF!+#REF!+#REF!+#REF!+#REF!+#REF!+#REF!+#REF!+#REF!+#REF!+#REF!+#REF!+#REF!+#REF!+#REF!+#REF!+#REF!+#REF!+#REF!+#REF!+#REF!+#REF!+#REF!+#REF!+#REF!+#REF!+#REF!+#REF!+#REF!+#REF!+#REF!+#REF!+#REF!+#REF!+#REF!+#REF!+#REF!+#REF!+#REF!+#REF!+#REF!+#REF!+#REF!+#REF!+#REF!+#REF!+#REF!+#REF!+#REF!+#REF!+#REF!+#REF!+#REF!+#REF!+#REF!+#REF!+#REF!+#REF!+#REF!+#REF!+#REF!+#REF!+#REF!+#REF! -> #REF!
A23: INCENDIO | C23: =$O$12 -> 0 | D23: =$D$17 -> INCLUIDO | E23: =E22 -> Sublimite | F23: =(F22*$O$12)*S23 -> 0 | G23: =G22*0.35 -> 0.010773536 | H23: =(IF(I23="$ Prima",G23,G23*F23/R23))*$U$9 -> 0 | I23: %o Al Millar | J23: =H23*$U$7 -> 0 | K23: =(H23+J23)*$K$15 -> 0 | L23: =ROUND(H23+J23+K23,2) -> 0 | M23: =$M$17 -> 0.1201 | N23: =H23*M23 -> 0 | O23: =N23 -> 0 | P23: =IF(Q23=1,"SI","NO") -> NO | Q23: =IF(D23="INCLUIDO",IF(F23<>0,1,0),0) -> 0 | R23: =IF(I23="%o Al Millar",1000,IF(I23="% Al Porciento",100,IF(I23="$ Prima",G23))) -> 1000 | S23: =IF(E23="Excluido",0,IF(D23="NO APLICA",0,1)) -> 1 | T23: =SUM(T18:T22) -> 1 | U23: =SUM(U18:U22) -> 0.3078153 | V23: =SUM(V18:V22) -> 0.3078153
A24: INCENDIO | B24: 280 | C24: MEJORAS Y ADAPTACIONES | D24: =$D$17 -> INCLUIDO | E24: Sublimite | F24: 0 | G24: 0 | H24: =(IF(I24="$ Prima",G24,G24*F24/R24))*$U$9 -> 0 | I24: %o Al Millar | J24: =H24*$U$7 -> 0 | K24: =(H24+J24)*$K$15 -> 0 | L24: =ROUND(H24+J24+K24,2) -> 0 | M24: =$M$17 -> 0.1201 | N24: =H24*M24 -> 0 | O24: =N24 -> 0 | P24: =IF(Q24=1,"SI","NO") -> NO | Q24: =IF(D24="INCLUIDO",IF(F24<>0,1,0),0) -> 0 | R24: =IF(I24="%o Al Millar",1000,IF(I24="% Al Porciento",100,IF(I24="$ Prima",G24))) -> 1000 | S24: =IF(E24="Excluido",0,IF(D24="NO APLICA",0,1)) -> 1
A25: INCENDIO | C25: =$O$12 -> 0 | D25: =$D$17 -> INCLUIDO | E25: =E24 -> Sublimite | F25: =(F24*$O$12)*S25 -> 0 | G25: =G24*0.35 -> 0 | H25: =(IF(I25="$ Prima",G25,G25*F25/R25))*$U$9 -> 0 | I25: %o Al Millar | J25: =H25*$U$7 -> 0 | K25: =(H25+J25)*$K$15 -> 0 | L25: =ROUND(H25+J25+K25,2) -> 0 | M25: =$M$17 -> 0.1201 | N25: =H25*M25 -> 0 | O25: =N25 -> 0 | P25: =IF(Q25=1,"SI","NO") -> NO | Q25: =IF(D25="INCLUIDO",IF(F25<>0,1,0),0) -> 0 | R25: =IF(I25="%o Al Millar",1000,IF(I25="% Al Porciento",100,IF(I25="$ Prima",G25))) -> 1000 | S25: =IF(E25="Excluido",0,IF(D25="NO APLICA",0,1)) -> 1
A26: INCENDIO | B26: 004 | C26: INCISOS CONOCIDOS | D26: =$D$17 -> INCLUIDO | E26: Sublimite | F26: 0 | G26: ='COTIZACIÓN M.N.'!E67*50% -> 0.0011 | H26: =(((IF(I26="$ Prima",G26,G26*F26/R26))*$U$9)/365)*$J$15 -> 0 | I26: %o Al Millar | J26: =H26*$U$7 -> 0 | K26: =(H26+J26)*$K$15 -> 0 | L26: =ROUND(H26+J26+K26,2) -> 0 | M26: =$M$17 -> 0.1201 | N26: =H26*M26 -> 0 | O26: =N26 -> 0 | P26: =IF(Q26=1,"SI","NO") -> NO | Q26: =IF(D26="INCLUIDO",IF(F26<>0,1,0),0) -> 0 | R26: =IF(I26="%o Al Millar",1000,IF(I26="% Al Porciento",100,IF(I26="$ Prima",G26))) -> 1000 | S26: =IF(E26="Excluido",0,IF(D26="NO APLICA",0,1)) -> 1 | W26: ='UB (1)'!H26+'UB (2)'!H26+'UB (3)'!H26+#REF!+#REF!+#REF!+#REF!+#REF!+#REF!+#REF!+#REF!+#REF!+#REF!+#REF!+#REF!+#REF!+#REF!+#REF!+#REF!+#REF!+#REF!+#REF!+#REF!+#REF!+#REF!+#REF!+#REF!+#REF!+#REF!+#REF!+#REF!+#REF!+#REF!+#REF!+#REF!+#REF!+#REF!+#REF!+#REF!+#REF!+#REF!+#REF!+#REF!+#REF!+#REF!+#REF!+#REF!+#REF!+#REF!+#REF!+#REF!+#REF!+#REF!+#REF!+#REF!+#REF!+#REF!+#REF!+#REF!+#REF!+#REF!+#REF!+#REF!+#REF!+#REF!+#REF!+#REF!+#REF!+#REF!+#REF!+#REF!+#REF!+#REF!+#REF!+#REF!+#REF!+#REF!+#REF!+#REF!+#REF!+#REF!+#REF!+#REF!+#REF!+#REF!+#REF!+#REF!+#REF!+#REF!+#REF!+#REF!+#REF!+#REF!+#REF!+#REF!+#REF!+#REF!+#REF!+#REF!+#REF!+#REF!+#REF!+#REF!+#REF!+#REF!+#REF!+#REF!+#REF!+#REF!+#REF!+#REF!+#REF!+#REF!+#REF!+#REF!+#REF!+#REF!+#REF!+#REF!+#REF!+#REF!+#REF!+#REF!+#REF!+#REF!+#REF!+#REF!+#REF!+#REF!+#REF!+#REF!+#REF!+#REF!+#REF!+#REF!+#REF!+#REF!+#REF!+#REF!+#REF!+#REF!+#REF!+#REF!+#REF!+#REF!+#REF!+#REF!+#REF!+#REF!+#REF!+#REF!+#REF!+#REF!+#REF!+#REF!+#REF!+#REF!+#REF!+#REF!+#REF!+#REF!+#REF!+#REF!+#REF!+#REF!+#REF!+#REF!+#REF!+#REF!+#REF!+#REF!+#REF!+#REF!+#REF!+#REF!+#REF!+#REF!+#REF!+#REF!+#REF!+#REF!+#REF!+#REF!+#REF!+#REF!+#REF!+#REF!+#REF!+#REF!+#REF!+#REF!+#REF!+#REF!+#REF!+#REF!+#REF!+#REF!+#REF!+#REF!+#REF!+#REF!+#REF!+#REF!+#REF!+#REF!+#REF!+#REF!+#REF!+#REF!+#REF!+#REF!+#REF!+#REF!+#REF!+#REF!+#REF!+#REF!+#REF!+#REF!+#REF!+#REF!+#REF!+#REF!+#REF!+#REF!+#REF!+#REF!+#REF!+#REF!+#REF!+#REF!+#REF!+#REF!+#REF!+#REF!+#REF!+#REF!+#REF!+#REF!+#REF!+#REF!+#REF!+#REF!+#REF!+#REF!+#REF!+#REF!+#REF!+#REF!+#REF!+#REF!+#REF!+#REF!+#REF!+#REF!+#REF!+#REF!+#REF!+#REF!+#REF!+#REF!+#REF!+#REF!+#REF!+#REF!+#REF!+#REF!+#REF!+#REF!+#REF!+#REF!+#REF!+#REF!+#REF!+#REF!+#REF!+#REF!+#REF!+#REF!+#REF!+#REF!+#REF!+#REF!+#REF!+#REF!+#REF!+#REF!+#REF!+#REF!+#REF!+#REF!+#REF!+#REF!+#REF!+#REF!+#REF!+#REF!+#REF!+#REF!+#REF!+#REF!+#REF!+#REF!+#REF!+#REF!+#REF!+#REF!+#REF!+#REF!+#REF!+#REF!+#REF!+#REF!+#REF!+#REF!+#REF!+#REF!+#REF!+#REF!+#REF!+#REF!+#REF!+#REF!+#REF!+#REF!+#REF!+#REF!+#REF!+#REF!+#REF!+#REF!+#REF!+#REF!+#REF!+#REF!+#REF!+#REF!+#REF!+#REF!+#REF!+#REF!+#REF!+#REF!+#REF!+#REF!+#REF!+#REF!+#REF!+#REF!+#REF!+#REF!+#REF!+#REF!+#REF!+#REF!+#REF!+#REF!+#REF!+#REF!+#REF!+#REF!+#REF!+#REF!+#REF! -> #REF!
A27: INCENDIO | B27: 005 | C27: INCISOS NO CONOCIDOS | D27: =$D$17 -> INCLUIDO | E27: Sublimite | F27: 0 | G27: =G26 -> 0.0011 | H27: =(((IF(I27="$ Prima",G27,G27*F27/R27))*$U$9)/365)*$J$15 -> 0 | I27: %o Al Millar | J27: =H27*$U$7 -> 0 | K27: =(H27+J27)*$K$15 -> 0 | L27: =ROUND(H27+J27+K27,2) -> 0 | M27: =$M$17 -> 0.1201 | N27: =H27*M27 -> 0 | O27: =N27 -> 0 | P27: =IF(Q27=1,"SI","NO") -> NO | Q27: =IF(D27="INCLUIDO",IF(F27<>0,1,0),0) -> 0 | R27: =IF(I27="%o Al Millar",1000,IF(I27="% Al Porciento",100,IF(I27="$ Prima",G27))) -> 1000 | S27: =IF(E27="Excluido",0,IF(D27="NO APLICA",0,1)) -> 1 | W27: ='UB (1)'!H27+'UB (2)'!H27+'UB (3)'!H27+#REF!+#REF!+#REF!+#REF!+#REF!+#REF!+#REF!+#REF!+#REF!+#REF!+#REF!+#REF!+#REF!+#REF!+#REF!+#REF!+#REF!+#REF!+#REF!+#REF!+#REF!+#REF!+#REF!+#REF!+#REF!+#REF!+#REF!+#REF!+#REF!+#REF!+#REF!+#REF!+#REF!+#REF!+#REF!+#REF!+#REF!+#REF!+#REF!+#REF!+#REF!+#REF!+#REF!+#REF!+#REF!+#REF!+#REF!+#REF!+#REF!+#REF!+#REF!+#REF!+#REF!+#REF!+#REF!+#REF!+#REF!+#REF!+#REF!+#REF!+#REF!+#REF!+#REF!+#REF!+#REF!+#REF!+#REF!+#REF!+#REF!+#REF!+#REF!+#REF!+#REF!+#REF!+#REF!+#REF!+#REF!+#REF!+#REF!+#REF!+#REF!+#REF!+#REF!+#REF!+#REF!+#REF!+#REF!+#REF!+#REF!+#REF!+#REF!+#REF!+#REF!+#REF!+#REF!+#REF!+#REF!+#REF!+#REF!+#REF!+#REF!+#REF!+#REF!+#REF!+#REF!+#REF!+#REF!+#REF!+#REF!+#REF!+#REF!+#REF!+#REF!+#REF!+#REF!+#REF!+#REF!+#REF!+#REF!+#REF!+#REF!+#REF!+#REF!+#REF!+#REF!+#REF!+#REF!+#REF!+#REF!+#REF!+#REF!+#REF!+#REF!+#REF!+#REF!+#REF!+#REF!+#REF!+#REF!+#REF!+#REF!+#REF!+#REF!+#REF!+#REF!+#REF!+#REF!+#REF!+#REF!+#REF!+#REF!+#REF!+#REF!+#REF!+#REF!+#REF!+#REF!+#REF!+#REF!+#REF!+#REF!+#REF!+#REF!+#REF!+#REF!+#REF!+#REF!+#REF!+#REF!+#REF!+#REF!+#REF!+#REF!+#REF!+#REF!+#REF!+#REF!+#REF!+#REF!+#REF!+#REF!+#REF!+#REF!+#REF!+#REF!+#REF!+#REF!+#REF!+#REF!+#REF!+#REF!+#REF!+#REF!+#REF!+#REF!+#REF!+#REF!+#REF!+#REF!+#REF!+#REF!+#REF!+#REF!+#REF!+#REF!+#REF!+#REF!+#REF!+#REF!+#REF!+#REF!+#REF!+#REF!+#REF!+#REF!+#REF!+#REF!+#REF!+#REF!+#REF!+#REF!+#REF!+#REF!+#REF!+#REF!+#REF!+#REF!+#REF!+#REF!+#REF!+#REF!+#REF!+#REF!+#REF!+#REF!+#REF!+#REF!+#REF!+#REF!+#REF!+#REF!+#REF!+#REF!+#REF!+#REF!+#REF!+#REF!+#REF!+#REF!+#REF!+#REF!+#REF!+#REF!+#REF!+#REF!+#REF!+#REF!+#REF!+#REF!+#REF!+#REF!+#REF!+#REF!+#REF!+#REF!+#REF!+#REF!+#REF!+#REF!+#REF!+#REF!+#REF!+#REF!+#REF!+#REF!+#REF!+#REF!+#REF!+#REF!+#REF!+#REF!+#REF!+#REF!+#REF!+#REF!+#REF!+#REF!+#REF!+#REF!+#REF!+#REF!+#REF!+#REF!+#REF!+#REF!+#REF!+#REF!+#REF!+#REF!+#REF!+#REF!+#REF!+#REF!+#REF!+#REF!+#REF!+#REF!+#REF!+#REF!+#REF!+#REF!+#REF!+#REF!+#REF!+#REF!+#REF!+#REF!+#REF!+#REF!+#REF!+#REF!+#REF!+#REF!+#REF!+#REF!+#REF!+#REF!+#REF!+#REF!+#REF!+#REF!+#REF!+#REF!+#REF!+#REF!+#REF!+#REF!+#REF!+#REF!+#REF!+#REF!+#REF!+#REF!+#REF!+#REF!+#REF!+#REF!+#REF!+#REF!+#REF!+#REF!+#REF!+#REF!+#REF!+#REF!+#REF!+#REF!+#REF!+#REF!+#REF!+#REF! -> #REF!
A28: 903 | B28: 1 | C28: HIDROMETEOROLOGICO EDIFICIO | D28: =$D$17 -> INCLUIDO | M28: 0.05 | P28: =IF(Q28=1,"SI","NO") -> SI | Q28: =IF(D28="INCLUIDO",IF(F29<>0,1,0),0) -> 1 | W28: ='UB (1)'!H28+'UB (2)'!H28+'UB (3)'!H28+#REF!+#REF!+#REF!+#REF!+#REF!+#REF!+#REF!+#REF!+#REF!+#REF!+#REF!+#REF!+#REF!+#REF!+#REF!+#REF!+#REF!+#REF!+#REF!+#REF!+#REF!+#REF!+#REF!+#REF!+#REF!+#REF!+#REF!+#REF!+#REF!+#REF!+#REF!+#REF!+#REF!+#REF!+#REF!+#REF!+#REF!+#REF!+#REF!+#REF!+#REF!+#REF!+#REF!+#REF!+#REF!+#REF!+#REF!+#REF!+#REF!+#REF!+#REF!+#REF!+#REF!+#REF!+#REF!+#REF!+#REF!+#REF!+#REF!+#REF!+#REF!+#REF!+#REF!+#REF!+#REF!+#REF!+#REF!+#REF!+#REF!+#REF!+#REF!+#REF!+#REF!+#REF!+#REF!+#REF!+#REF!+#REF!+#REF!+#REF!+#REF!+#REF!+#REF!+#REF!+#REF!+#REF!+#REF!+#REF!+#REF!+#REF!+#REF!+#REF!+#REF!+#REF!+#REF!+#REF!+#REF!+#REF!+#REF!+#REF!+#REF!+#REF!+#REF!+#REF!+#REF!+#REF!+#REF!+#REF!+#REF!+#REF!+#REF!+#REF!+#REF!+#REF!+#REF!+#REF!+#REF!+#REF!+#REF!+#REF!+#REF!+#REF!+#REF!+#REF!+#REF!+#REF!+#REF!+#REF!+#REF!+#REF!+#REF!+#REF!+#REF!+#REF!+#REF!+#REF!+#REF!+#REF!+#REF!+#REF!+#REF!+#REF!+#REF!+#REF!+#REF!+#REF!+#REF!+#REF!+#REF!+#REF!+#REF!+#REF!+#REF!+#REF!+#REF!+#REF!+#REF!+#REF!+#REF!+#REF!+#REF!+#REF!+#REF!+#REF!+#REF!+#REF!+#REF!+#REF!+#REF!+#REF!+#REF!+#REF!+#REF!+#REF!+#REF!+#REF!+#REF!+#REF!+#REF!+#REF!+#REF!+#REF!+#REF!+#REF!+#REF!+#REF!+#REF!+#REF!+#REF!+#REF!+#REF!+#REF!+#REF!+#REF!+#REF!+#REF!+#REF!+#REF!+#REF!+#REF!+#REF!+#REF!+#REF!+#REF!+#REF!+#REF!+#REF!+#REF!+#REF!+#REF!+#REF!+#REF!+#REF!+#REF!+#REF!+#REF!+#REF!+#REF!+#REF!+#REF!+#REF!+#REF!+#REF!+#REF!+#REF!+#REF!+#REF!+#REF!+#REF!+#REF!+#REF!+#REF!+#REF!+#REF!+#REF!+#REF!+#REF!+#REF!+#REF!+#REF!+#REF!+#REF!+#REF!+#REF!+#REF!+#REF!+#REF!+#REF!+#REF!+#REF!+#REF!+#REF!+#REF!+#REF!+#REF!+#REF!+#REF!+#REF!+#REF!+#REF!+#REF!+#REF!+#REF!+#REF!+#REF!+#REF!+#REF!+#REF!+#REF!+#REF!+#REF!+#REF!+#REF!+#REF!+#REF!+#REF!+#REF!+#REF!+#REF!+#REF!+#REF!+#REF!+#REF!+#REF!+#REF!+#REF!+#REF!+#REF!+#REF!+#REF!+#REF!+#REF!+#REF!+#REF!+#REF!+#REF!+#REF!+#REF!+#REF!+#REF!+#REF!+#REF!+#REF!+#REF!+#REF!+#REF!+#REF!+#REF!+#REF!+#REF!+#REF!+#REF!+#REF!+#REF!+#REF!+#REF!+#REF!+#REF!+#REF!+#REF!+#REF!+#REF!+#REF!+#REF!+#REF!+#REF!+#REF!+#REF!+#REF!+#REF!+#REF!+#REF!+#REF!+#REF!+#REF!+#REF!+#REF!+#REF!+#REF!+#REF!+#REF!+#REF!+#REF!+#REF!+#REF!+#REF!+#REF!+#REF!+#REF!+#REF!+#REF!+#REF!+#REF!+#REF!+#REF!+#REF!+#REF!+#REF!+#REF!+#REF!+#REF! -> #REF!
A29: FHM | B29: 040 | C29: RIESGOS HIDROMETEOROLÓGICOS | D29: =$D$17 -> INCLUIDO | E29: Sublimite | F29: =$F$17*S29 -> 155549.7 | G29: ='COTIZACIÓN M.N.'!E28 -> 0.25 | H29: =((((IF(I29="$ Prima",G29,G29*F29/R29))*$U$9)/365)*$J$15) -> 38.993966 | I29: %o Al Millar | J29: =H29*$U$7 -> 0.82277268 | K29: =(H29+J29)*$K$15 -> 6.3706782 | L29: =ROUND(H29+J29+K29,2) -> 46.19 | M29: =$M$28 -> 0.05 | N29: =H29*M29 -> 1.9496983 | O29: =N29 -> 1.9496983 | P29: =IF(Q29=1,"SI","NO") -> SI | Q29: =IF(D29="INCLUIDO",IF(F29<>0,1,0),0) -> 1 | R29: =IF(I29="%o Al Millar",1000,IF(I29="% Al Porciento",100,IF(I29="$ Prima",G29))) -> 1000 | S29: =IF(E29="Excluido",0,IF(D29="NO APLICA",0,1)) -> 1 | W29: ='UB (1)'!H29+'UB (2)'!H29+'UB (3)'!H29+#REF!+#REF!+#REF!+#REF!+#REF!+#REF!+#REF!+#REF!+#REF!+#REF!+#REF!+#REF!+#REF!+#REF!+#REF!+#REF!+#REF!+#REF!+#REF!+#REF!+#REF!+#REF!+#REF!+#REF!+#REF!+#REF!+#REF!+#REF!+#REF!+#REF!+#REF!+#REF!+#REF!+#REF!+#REF!+#REF!+#REF!+#REF!+#REF!+#REF!+#REF!+#REF!+#REF!+#REF!+#REF!+#REF!+#REF!+#REF!+#REF!+#REF!+#REF!+#REF!+#REF!+#REF!+#REF!+#REF!+#REF!+#REF!+#REF!+#REF!+#REF!+#REF!+#REF!+#REF!+#REF!+#REF!+#REF!+#REF!+#REF!+#REF!+#REF!+#REF!+#REF!+#REF!+#REF!+#REF!+#REF!+#REF!+#REF!+#REF!+#REF!+#REF!+#REF!+#REF!+#REF!+#REF!+#REF!+#REF!+#REF!+#REF!+#REF!+#REF!+#REF!+#REF!+#REF!+#REF!+#REF!+#REF!+#REF!+#REF!+#REF!+#REF!+#REF!+#REF!+#REF!+#REF!+#REF!+#REF!+#REF!+#REF!+#REF!+#REF!+#REF!+#REF!+#REF!+#REF!+#REF!+#REF!+#REF!+#REF!+#REF!+#REF!+#REF!+#REF!+#REF!+#REF!+#REF!+#REF!+#REF!+#REF!+#REF!+#REF!+#REF!+#REF!+#REF!+#REF!+#REF!+#REF!+#REF!+#REF!+#REF!+#REF!+#REF!+#REF!+#REF!+#REF!+#REF!+#REF!+#REF!+#REF!+#REF!+#REF!+#REF!+#REF!+#REF!+#REF!+#REF!+#REF!+#REF!+#REF!+#REF!+#REF!+#REF!+#REF!+#REF!+#REF!+#REF!+#REF!+#REF!+#REF!+#REF!+#REF!+#REF!+#REF!+#REF!+#REF!+#REF!+#REF!+#REF!+#REF!+#REF!+#REF!+#REF!+#REF!+#REF!+#REF!+#REF!+#REF!+#REF!+#REF!+#REF!+#REF!+#REF!+#REF!+#REF!+#REF!+#REF!+#REF!+#REF!+#REF!+#REF!+#REF!+#REF!+#REF!+#REF!+#REF!+#REF!+#REF!+#REF!+#REF!+#REF!+#REF!+#REF!+#REF!+#REF!+#REF!+#REF!+#REF!+#REF!+#REF!+#REF!+#REF!+#REF!+#REF!+#REF!+#REF!+#REF!+#REF!+#REF!+#REF!+#REF!+#REF!+#REF!+#REF!+#REF!+#REF!+#REF!+#REF!+#REF!+#REF!+#REF!+#REF!+#REF!+#REF!+#REF!+#REF!+#REF!+#REF!+#REF!+#REF!+#REF!+#REF!+#REF!+#REF!+#REF!+#REF!+#REF!+#REF!+#REF!+#REF!+#REF!+#REF!+#REF!+#REF!+#REF!+#REF!+#REF!+#REF!+#REF!+#REF!+#REF!+#REF!+#REF!+#REF!+#REF!+#REF!+#REF!+#REF!+#REF!+#REF!+#REF!+#REF!+#REF!+#REF!+#REF!+#REF!+#REF!+#REF!+#REF!+#REF!+#REF!+#REF!+#REF!+#REF!+#REF!+#REF!+#REF!+#REF!+#REF!+#REF!+#REF!+#REF!+#REF!+#REF!+#REF!+#REF!+#REF!+#REF!+#REF!+#REF!+#REF!+#REF!+#REF!+#REF!+#REF!+#REF!+#REF!+#REF!+#REF!+#REF!+#REF!+#REF!+#REF!+#REF!+#REF!+#REF!+#REF!+#REF!+#REF!+#REF!+#REF!+#REF!+#REF!+#REF!+#REF!+#REF!+#REF!+#REF!+#REF!+#REF!+#REF!+#REF!+#REF!+#REF!+#REF!+#REF!+#REF!+#REF!+#REF!+#REF!+#REF!+#REF!+#REF!+#REF!+#REF!+#REF!+#REF!+#REF!+#REF!+#REF!+#REF! -> #REF!
A30: FHM | C30: =$O$12 -> 0 | D30: =$D$17 -> INCLUIDO | E30: =E29 -> Sublimite | F30: =(F29*$O$12)*S30 -> 0 | G30: =G29*0.35 -> 0.0875 | H30: =((IF(I30="$ Prima",G30,G30*F30/R30))*$U$9)*O13 -> 0 | I30: %o Al Millar | J30: =H30*$U$7 -> 0 | K30: =(H30+J30)*$K$15 -> 0 | L30: =ROUND(H30+J30+K30,2) -> 0 | M30: =$M$28 -> 0.05 | N30: =H30*M30 -> 0 | O30: =N30 -> 0 | P30: =IF(Q30=1,"SI","NO") -> NO | Q30: =IF(D30="INCLUIDO",IF(F30<>0,1,0),0) -> 0 | R30: =IF(I30="%o Al Millar",1000,IF(I30="% Al Porciento",100,IF(I30="$ Prima",G30))) -> 1000 | S30: =IF(E30="Excluido",0,IF(D30="NO APLICA",0,1)) -> 1
A31: 904 | B31: 1 | C31: TERREMOTO EDIFICIO | D31: =$D$17 -> INCLUIDO | M31: 0.05 | P31: =IF(Q31=1,"SI","NO") -> SI | Q31: =IF(D31="INCLUIDO",IF(F32<>0,1,0),0) -> 1 | W31: ='UB (1)'!H31+'UB (2)'!H31+'UB (3)'!H31+#REF!+#REF!+#REF!+#REF!+#REF!+#REF!+#REF!+#REF!+#REF!+#REF!+#REF!+#REF!+#REF!+#REF!+#REF!+#REF!+#REF!+#REF!+#REF!+#REF!+#REF!+#REF!+#REF!+#REF!+#REF!+#REF!+#REF!+#REF!+#REF!+#REF!+#REF!+#REF!+#REF!+#REF!+#REF!+#REF!+#REF!+#REF!+#REF!+#REF!+#REF!+#REF!+#REF!+#REF!+#REF!+#REF!+#REF!+#REF!+#REF!+#REF!+#REF!+#REF!+#REF!+#REF!+#REF!+#REF!+#REF!+#REF!+#REF!+#REF!+#REF!+#REF!+#REF!+#REF!+#REF!+#REF!+#REF!+#REF!+#REF!+#REF!+#REF!+#REF!+#REF!+#REF!+#REF!+#REF!+#REF!+#REF!+#REF!+#REF!+#REF!+#REF!+#REF!+#REF!+#REF!+#REF!+#REF!+#REF!+#REF!+#REF!+#REF!+#REF!+#REF!+#REF!+#REF!+#REF!+#REF!+#REF!+#REF!+#REF!+#REF!+#REF!+#REF!+#REF!+#REF!+#REF!+#REF!+#REF!+#REF!+#REF!+#REF!+#REF!+#REF!+#REF!+#REF!+#REF!+#REF!+#REF!+#REF!+#REF!+#REF!+#REF!+#REF!+#REF!+#REF!+#REF!+#REF!+#REF!+#REF!+#REF!+#REF!+#REF!+#REF!+#REF!+#REF!+#REF!+#REF!+#REF!+#REF!+#REF!+#REF!+#REF!+#REF!+#REF!+#REF!+#REF!+#REF!+#REF!+#REF!+#REF!+#REF!+#REF!+#REF!+#REF!+#REF!+#REF!+#REF!+#REF!+#REF!+#REF!+#REF!+#REF!+#REF!+#REF!+#REF!+#REF!+#REF!+#REF!+#REF!+#REF!+#REF!+#REF!+#REF!+#REF!+#REF!+#REF!+#REF!+#REF!+#REF!+#REF!+#REF!+#REF!+#REF!+#REF!+#REF!+#REF!+#REF!+#REF!+#REF!+#REF!+#REF!+#REF!+#REF!+#REF!+#REF!+#REF!+#REF!+#REF!+#REF!+#REF!+#REF!+#REF!+#REF!+#REF!+#REF!+#REF!+#REF!+#REF!+#REF!+#REF!+#REF!+#REF!+#REF!+#REF!+#REF!+#REF!+#REF!+#REF!+#REF!+#REF!+#REF!+#REF!+#REF!+#REF!+#REF!+#REF!+#REF!+#REF!+#REF!+#REF!+#REF!+#REF!+#REF!+#REF!+#REF!+#REF!+#REF!+#REF!+#REF!+#REF!+#REF!+#REF!+#REF!+#REF!+#REF!+#REF!+#REF!+#REF!+#REF!+#REF!+#REF!+#REF!+#REF!+#REF!+#REF!+#REF!+#REF!+#REF!+#REF!+#REF!+#REF!+#REF!+#REF!+#REF!+#REF!+#REF!+#REF!+#REF!+#REF!+#REF!+#REF!+#REF!+#REF!+#REF!+#REF!+#REF!+#REF!+#REF!+#REF!+#REF!+#REF!+#REF!+#REF!+#REF!+#REF!+#REF!+#REF!+#REF!+#REF!+#REF!+#REF!+#REF!+#REF!+#REF!+#REF!+#REF!+#REF!+#REF!+#REF!+#REF!+#REF!+#REF!+#REF!+#REF!+#REF!+#REF!+#REF!+#REF!+#REF!+#REF!+#REF!+#REF!+#REF!+#REF!+#REF!+#REF!+#REF!+#REF!+#REF!+#REF!+#REF!+#REF!+#REF!+#REF!+#REF!+#REF!+#REF!+#REF!+#REF!+#REF!+#REF!+#REF!+#REF!+#REF!+#REF!+#REF!+#REF!+#REF!+#REF!+#REF!+#REF!+#REF!+#REF!+#REF!+#REF!+#REF!+#REF!+#REF!+#REF!+#REF!+#REF!+#REF!+#REF!+#REF!+#REF!+#REF!+#REF!+#REF!+#REF!+#REF!+#REF! -> #REF!
A32: TEV | B32: 055 | C32: TERREMOTO Y ERUPCIÓN VOLCÁNICA | D32: =$D$17 -> INCLUIDO | E32: Sublimite | F32: =F17 -> 155549.7 | G32: ='COTIZACIÓN M.N.'!E30 -> 0.4 | H32: =((((IF(I32="$ Prima",G32,G32*F32/R32))*$U$9)*O14)/365)*$J$15 -> 62.390345 | I32: %o Al Millar | J32: =H32*$U$7 -> 1.3164363 | K32: =(H32+J32)*$K$15 -> 10.193085 | L32: =ROUND(H32+J32+K32,2) -> 73.9 | M32: =$M$31 -> 0.05 | N32: =H32*M32 -> 3.1195173 | O32: =N32 -> 3.1195173 | P32: =IF(Q32=1,"SI","NO") -> SI | Q32: =IF(D32="INCLUIDO",IF(F32<>0,1,0),0) -> 1 | R32: =IF(I32="%o Al Millar",1000,IF(I32="% Al Porciento",100,IF(I32="$ Prima",G32))) -> 1000 | S32: =IF(E32="Excluido",0,IF(D32="NO APLICA",0,1)) -> 1 | W32: ='UB (1)'!H32+'UB (2)'!H32+'UB (3)'!H32+#REF!+#REF!+#REF!+#REF!+#REF!+#REF!+#REF!+#REF!+#REF!+#REF!+#REF!+#REF!+#REF!+#REF!+#REF!+#REF!+#REF!+#REF!+#REF!+#REF!+#REF!+#REF!+#REF!+#REF!+#REF!+#REF!+#REF!+#REF!+#REF!+#REF!+#REF!+#REF!+#REF!+#REF!+#REF!+#REF!+#REF!+#REF!+#REF!+#REF!+#REF!+#REF!+#REF!+#REF!+#REF!+#REF!+#REF!+#REF!+#REF!+#REF!+#REF!+#REF!+#REF!+#REF!+#REF!+#REF!+#REF!+#REF!+#REF!+#REF!+#REF!+#REF!+#REF!+#REF!+#REF!+#REF!+#REF!+#REF!+#REF!+#REF!+#REF!+#REF!+#REF!+#REF!+#REF!+#REF!+#REF!+#REF!+#REF!+#REF!+#REF!+#REF!+#REF!+#REF!+#REF!+#REF!+#REF!+#REF!+#REF!+#REF!+#REF!+#REF!+#REF!+#REF!+#REF!+#REF!+#REF!+#REF!+#REF!+#REF!+#REF!+#REF!+#REF!+#REF!+#REF!+#REF!+#REF!+#REF!+#REF!+#REF!+#REF!+#REF!+#REF!+#REF!+#REF!+#REF!+#REF!+#REF!+#REF!+#REF!+#REF!+#REF!+#REF!+#REF!+#REF!+#REF!+#REF!+#REF!+#REF!+#REF!+#REF!+#REF!+#REF!+#REF!+#REF!+#REF!+#REF!+#REF!+#REF!+#REF!+#REF!+#REF!+#REF!+#REF!+#REF!+#REF!+#REF!+#REF!+#REF!+#REF!+#REF!+#REF!+#REF!+#REF!+#REF!+#REF!+#REF!+#REF!+#REF!+#REF!+#REF!+#REF!+#REF!+#REF!+#REF!+#REF!+#REF!+#REF!+#REF!+#REF!+#REF!+#REF!+#REF!+#REF!+#REF!+#REF!+#REF!+#REF!+#REF!+#REF!+#REF!+#REF!+#REF!+#REF!+#REF!+#REF!+#REF!+#REF!+#REF!+#REF!+#REF!+#REF!+#REF!+#REF!+#REF!+#REF!+#REF!+#REF!+#REF!+#REF!+#REF!+#REF!+#REF!+#REF!+#REF!+#REF!+#REF!+#REF!+#REF!+#REF!+#REF!+#REF!+#REF!+#REF!+#REF!+#REF!+#REF!+#REF!+#REF!+#REF!+#REF!+#REF!+#REF!+#REF!+#REF!+#REF!+#REF!+#REF!+#REF!+#REF!+#REF!+#REF!+#REF!+#REF!+#REF!+#REF!+#REF!+#REF!+#REF!+#REF!+#REF!+#REF!+#REF!+#REF!+#REF!+#REF!+#REF!+#REF!+#REF!+#REF!+#REF!+#REF!+#REF!+#REF!+#REF!+#REF!+#REF!+#REF!+#REF!+#REF!+#REF!+#REF!+#REF!+#REF!+#REF!+#REF!+#REF!+#REF!+#REF!+#REF!+#REF!+#REF!+#REF!+#REF!+#REF!+#REF!+#REF!+#REF!+#REF!+#REF!+#REF!+#REF!+#REF!+#REF!+#REF!+#REF!+#REF!+#REF!+#REF!+#REF!+#REF!+#REF!+#REF!+#REF!+#REF!+#REF!+#REF!+#REF!+#REF!+#REF!+#REF!+#REF!+#REF!+#REF!+#REF!+#REF!+#REF!+#REF!+#REF!+#REF!+#REF!+#REF!+#REF!+#REF!+#REF!+#REF!+#REF!+#REF!+#REF!+#REF!+#REF!+#REF!+#REF!+#REF!+#REF!+#REF!+#REF!+#REF!+#REF!+#REF!+#REF!+#REF!+#REF!+#REF!+#REF!+#REF!+#REF!+#REF!+#REF!+#REF!+#REF!+#REF!+#REF!+#REF!+#REF!+#REF!+#REF!+#REF!+#REF!+#REF!+#REF!+#REF!+#REF!+#REF!+#REF!+#REF!+#REF!+#REF!+#REF!+#REF!+#REF! -> #REF!
A33: TEV | C33: =$O$12 -> 0 | D33: =$D$17 -> INCLUIDO | E33: =E32 -> Sublimite | F33: =(F32*$O$12)*S33 -> 0 | G33: =G32*0.35 -> 0.14 | H33: =((IF(I33="$ Prima",G33,G33*F33/R33))*$U$9)*O14 -> 0 | I33: %o Al Millar | J33: =H33*$U$7 -> 0 | K33: =(H33+J33)*$K$15 -> 0 | L33: =ROUND(H33+J33+K33,2) -> 0 | M33: =$M$31 -> 0.05 | N33: =H33*M33 -> 0 | O33: =N33 -> 0 | P33: =IF(Q33=1,"SI","NO") -> NO | Q33: =IF(D33="INCLUIDO",IF(F33<>0,1,0),0) -> 0 | R33: =IF(I33="%o Al Millar",1000,IF(I33="% Al Porciento",100,IF(I33="$ Prima",G33))) -> 1000 | S33: =IF(E33="Excluido",0,IF(D33="NO APLICA",0,1)) -> 1
A34: 902 | B34: 001 | C34: INCENDIO EDIFICIO - REM ESC. | D34: =$D$17 -> INCLUIDO | F34: ='COTIZACIÓN M.N.'!D61 -> 31109.94 | M34: 0.25 | P34: =IF(Q34=1,"SI","NO") -> SI | Q34: =IF(D34="INCLUIDO",IF(F35<>0,1,0),0) -> 1 | W34: ='UB (1)'!H34+'UB (2)'!H34+'UB (3)'!H34+#REF!+#REF!+#REF!+#REF!+#REF!+#REF!+#REF!+#REF!+#REF!+#REF!+#REF!+#REF!+#REF!+#REF!+#REF!+#REF!+#REF!+#REF!+#REF!+#REF!+#REF!+#REF!+#REF!+#REF!+#REF!+#REF!+#REF!+#REF!+#REF!+#REF!+#REF!+#REF!+#REF!+#REF!+#REF!+#REF!+#REF!+#REF!+#REF!+#REF!+#REF!+#REF!+#REF!+#REF!+#REF!+#REF!+#REF!+#REF!+#REF!+#REF!+#REF!+#REF!+#REF!+#REF!+#REF!+#REF!+#REF!+#REF!+#REF!+#REF!+#REF!+#REF!+#REF!+#REF!+#REF!+#REF!+#REF!+#REF!+#REF!+#REF!+#REF!+#REF!+#REF!+#REF!+#REF!+#REF!+#REF!+#REF!+#REF!+#REF!+#REF!+#REF!+#REF!+#REF!+#REF!+#REF!+#REF!+#REF!+#REF!+#REF!+#REF!+#REF!+#REF!+#REF!+#REF!+#REF!+#REF!+#REF!+#REF!+#REF!+#REF!+#REF!+#REF!+#REF!+#REF!+#REF!+#REF!+#REF!+#REF!+#REF!+#REF!+#REF!+#REF!+#REF!+#REF!+#REF!+#REF!+#REF!+#REF!+#REF!+#REF!+#REF!+#REF!+#REF!+#REF!+#REF!+#REF!+#REF!+#REF!+#REF!+#REF!+#REF!+#REF!+#REF!+#REF!+#REF!+#REF!+#REF!+#REF!+#REF!+#REF!+#REF!+#REF!+#REF!+#REF!+#REF!+#REF!+#REF!+#REF!+#REF!+#REF!+#REF!+#REF!+#REF!+#REF!+#REF!+#REF!+#REF!+#REF!+#REF!+#REF!+#REF!+#REF!+#REF!+#REF!+#REF!+#REF!+#REF!+#REF!+#REF!+#REF!+#REF!+#REF!+#REF!+#REF!+#REF!+#REF!+#REF!+#REF!+#REF!+#REF!+#REF!+#REF!+#REF!+#REF!+#REF!+#REF!+#REF!+#REF!+#REF!+#REF!+#REF!+#REF!+#REF!+#REF!+#REF!+#REF!+#REF!+#REF!+#REF!+#REF!+#REF!+#REF!+#REF!+#REF!+#REF!+#REF!+#REF!+#REF!+#REF!+#REF!+#REF!+#REF!+#REF!+#REF!+#REF!+#REF!+#REF!+#REF!+#REF!+#REF!+#REF!+#REF!+#REF!+#REF!+#REF!+#REF!+#REF!+#REF!+#REF!+#REF!+#REF!+#REF!+#REF!+#REF!+#REF!+#REF!+#REF!+#REF!+#REF!+#REF!+#REF!+#REF!+#REF!+#REF!+#REF!+#REF!+#REF!+#REF!+#REF!+#REF!+#REF!+#REF!+#REF!+#REF!+#REF!+#REF!+#REF!+#REF!+#REF!+#REF!+#REF!+#REF!+#REF!+#REF!+#REF!+#REF!+#REF!+#REF!+#REF!+#REF!+#REF!+#REF!+#REF!+#REF!+#REF!+#REF!+#REF!+#REF!+#REF!+#REF!+#REF!+#REF!+#REF!+#REF!+#REF!+#REF!+#REF!+#REF!+#REF!+#REF!+#REF!+#REF!+#REF!+#REF!+#REF!+#REF!+#REF!+#REF!+#REF!+#REF!+#REF!+#REF!+#REF!+#REF!+#REF!+#REF!+#REF!+#REF!+#REF!+#REF!+#REF!+#REF!+#REF!+#REF!+#REF!+#REF!+#REF!+#REF!+#REF!+#REF!+#REF!+#REF!+#REF!+#REF!+#REF!+#REF!+#REF!+#REF!+#REF!+#REF!+#REF!+#REF!+#REF!+#REF!+#REF!+#REF!+#REF!+#REF!+#REF!+#REF!+#REF!+#REF!+#REF!+#REF!+#REF!+#REF!+#REF!+#REF!+#REF!+#REF!+#REF!+#REF!+#REF!+#REF!+#REF!+#REF!+#REF!+#REF!+#REF!+#REF! -> #REF!
A35: INCENDIO | B35: 011 | C35: REMOCIÓN DE ESCOMBROS INCENDIO | D35: =$D$17 -> INCLUIDO | E35: Sublimite | F35: =F34*S35 -> 31109.94 | G35: ='COTIZACIÓN M.N.'!E61*75% -> 0.041836148 | H35: =(((IF(I35="$ Prima",G35,G35*F35/R35))*$U$9)/365)*$J$15 -> 1.3050858 | I35: %o Al Millar | J35: =H35*$U$7 -> 0.027537311 | K35: =(H35+J35)*$K$15 -> 0.21321971 | L35: =ROUND(H35+J35+K35,2) -> 1.55 | M35: =M34 -> 0.25 | N35: =H35*M35 -> 0.32627146 | O35: =N35 -> 0.32627146 | P35: =IF(Q35=1,"SI","NO") -> SI | Q35: =IF(D35="INCLUIDO",IF(F35<>0,1,0),0) -> 1 | R35: =IF(I35="%o Al Millar",1000,IF(I35="% Al Porciento",100,IF(I35="$ Prima",G35))) -> 1000 | S35: =IF(E35="Excluido",0,IF(D35="NO APLICA",0,1)) -> 1 | W35: ='UB (1)'!H35+'UB (2)'!H35+'UB (3)'!H35+#REF!+#REF!+#REF!+#REF!+#REF!+#REF!+#REF!+#REF!+#REF!+#REF!+#REF!+#REF!+#REF!+#REF!+#REF!+#REF!+#REF!+#REF!+#REF!+#REF!+#REF!+#REF!+#REF!+#REF!+#REF!+#REF!+#REF!+#REF!+#REF!+#REF!+#REF!+#REF!+#REF!+#REF!+#REF!+#REF!+#REF!+#REF!+#REF!+#REF!+#REF!+#REF!+#REF!+#REF!+#REF!+#REF!+#REF!+#REF!+#REF!+#REF!+#REF!+#REF!+#REF!+#REF!+#REF!+#REF!+#REF!+#REF!+#REF!+#REF!+#REF!+#REF!+#REF!+#REF!+#REF!+#REF!+#REF!+#REF!+#REF!+#REF!+#REF!+#REF!+#REF!+#REF!+#REF!+#REF!+#REF!+#REF!+#REF!+#REF!+#REF!+#REF!+#REF!+#REF!+#REF!+#REF!+#REF!+#REF!+#REF!+#REF!+#REF!+#REF!+#REF!+#REF!+#REF!+#REF!+#REF!+#REF!+#REF!+#REF!+#REF!+#REF!+#REF!+#REF!+#REF!+#REF!+#REF!+#REF!+#REF!+#REF!+#REF!+#REF!+#REF!+#REF!+#REF!+#REF!+#REF!+#REF!+#REF!+#REF!+#REF!+#REF!+#REF!+#REF!+#REF!+#REF!+#REF!+#REF!+#REF!+#REF!+#REF!+#REF!+#REF!+#REF!+#REF!+#REF!+#REF!+#REF!+#REF!+#REF!+#REF!+#REF!+#REF!+#REF!+#REF!+#REF!+#REF!+#REF!+#REF!+#REF!+#REF!+#REF!+#REF!+#REF!+#REF!+#REF!+#REF!+#REF!+#REF!+#REF!+#REF!+#REF!+#REF!+#REF!+#REF!+#REF!+#REF!+#REF!+#REF!+#REF!+#REF!+#REF!+#REF!+#REF!+#REF!+#REF!+#REF!+#REF!+#REF!+#REF!+#REF!+#REF!+#REF!+#REF!+#REF!+#REF!+#REF!+#REF!+#REF!+#REF!+#REF!+#REF!+#REF!+#REF!+#REF!+#REF!+#REF!+#REF!+#REF!+#REF!+#REF!+#REF!+#REF!+#REF!+#REF!+#REF!+#REF!+#REF!+#REF!+#REF!+#REF!+#REF!+#REF!+#REF!+#REF!+#REF!+#REF!+#REF!+#REF!+#REF!+#REF!+#REF!+#REF!+#REF!+#REF!+#REF!+#REF!+#REF!+#REF!+#REF!+#REF!+#REF!+#REF!+#REF!+#REF!+#REF!+#REF!+#REF!+#REF!+#REF!+#REF!+#REF!+#REF!+#REF!+#REF!+#REF!+#REF!+#REF!+#REF!+#REF!+#REF!+#REF!+#REF!+#REF!+#REF!+#REF!+#REF!+#REF!+#REF!+#REF!+#REF!+#REF!+#REF!+#REF!+#REF!+#REF!+#REF!+#REF!+#REF!+#REF!+#REF!+#REF!+#REF!+#REF!+#REF!+#REF!+#REF!+#REF!+#REF!+#REF!+#REF!+#REF!+#REF!+#REF!+#REF!+#REF!+#REF!+#REF!+#REF!+#REF!+#REF!+#REF!+#REF!+#REF!+#REF!+#REF!+#REF!+#REF!+#REF!+#REF!+#REF!+#REF!+#REF!+#REF!+#REF!+#REF!+#REF!+#REF!+#REF!+#REF!+#REF!+#REF!+#REF!+#REF!+#REF!+#REF!+#REF!+#REF!+#REF!+#REF!+#REF!+#REF!+#REF!+#REF!+#REF!+#REF!+#REF!+#REF!+#REF!+#REF!+#REF!+#REF!+#REF!+#REF!+#REF!+#REF!+#REF!+#REF!+#REF!+#REF!+#REF!+#REF!+#REF!+#REF!+#REF!+#REF!+#REF!+#REF!+#REF!+#REF!+#REF!+#REF!+#REF!+#REF!+#REF!+#REF!+#REF!+#REF!+#REF!+#REF!+#REF! -> #REF!
A36: 903 | B36: 1 | C36: HIDROMETEOROLOGICO EDIFICIO | D36: =$D$17 -> INCLUIDO | M36: =M28 -> 0.05 | P36: =IF(Q36=1,"SI","NO") -> SI | Q36: =IF(D36="INCLUIDO",IF(F37<>0,1,0),0) -> 1 | W36: ='UB (1)'!H36+'UB (2)'!H36+'UB (3)'!H36+#REF!+#REF!+#REF!+#REF!+#REF!+#REF!+#REF!+#REF!+#REF!+#REF!+#REF!+#REF!+#REF!+#REF!+#REF!+#REF!+#REF!+#REF!+#REF!+#REF!+#REF!+#REF!+#REF!+#REF!+#REF!+#REF!+#REF!+#REF!+#REF!+#REF!+#REF!+#REF!+#REF!+#REF!+#REF!+#REF!+#REF!+#REF!+#REF!+#REF!+#REF!+#REF!+#REF!+#REF!+#REF!+#REF!+#REF!+#REF!+#REF!+#REF!+#REF!+#REF!+#REF!+#REF!+#REF!+#REF!+#REF!+#REF!+#REF!+#REF!+#REF!+#REF!+#REF!+#REF!+#REF!+#REF!+#REF!+#REF!+#REF!+#REF!+#REF!+#REF!+#REF!+#REF!+#REF!+#REF!+#REF!+#REF!+#REF!+#REF!+#REF!+#REF!+#REF!+#REF!+#REF!+#REF!+#REF!+#REF!+#REF!+#REF!+#REF!+#REF!+#REF!+#REF!+#REF!+#REF!+#REF!+#REF!+#REF!+#REF!+#REF!+#REF!+#REF!+#REF!+#REF!+#REF!+#REF!+#REF!+#REF!+#REF!+#REF!+#REF!+#REF!+#REF!+#REF!+#REF!+#REF!+#REF!+#REF!+#REF!+#REF!+#REF!+#REF!+#REF!+#REF!+#REF!+#REF!+#REF!+#REF!+#REF!+#REF!+#REF!+#REF!+#REF!+#REF!+#REF!+#REF!+#REF!+#REF!+#REF!+#REF!+#REF!+#REF!+#REF!+#REF!+#REF!+#REF!+#REF!+#REF!+#REF!+#REF!+#REF!+#REF!+#REF!+#REF!+#REF!+#REF!+#REF!+#REF!+#REF!+#REF!+#REF!+#REF!+#REF!+#REF!+#REF!+#REF!+#REF!+#REF!+#REF!+#REF!+#REF!+#REF!+#REF!+#REF!+#REF!+#REF!+#REF!+#REF!+#REF!+#REF!+#REF!+#REF!+#REF!+#REF!+#REF!+#REF!+#REF!+#REF!+#REF!+#REF!+#REF!+#REF!+#REF!+#REF!+#REF!+#REF!+#REF!+#REF!+#REF!+#REF!+#REF!+#REF!+#REF!+#REF!+#REF!+#REF!+#REF!+#REF!+#REF!+#REF!+#REF!+#REF!+#REF!+#REF!+#REF!+#REF!+#REF!+#REF!+#REF!+#REF!+#REF!+#REF!+#REF!+#REF!+#REF!+#REF!+#REF!+#REF!+#REF!+#REF!+#REF!+#REF!+#REF!+#REF!+#REF!+#REF!+#REF!+#REF!+#REF!+#REF!+#REF!+#REF!+#REF!+#REF!+#REF!+#REF!+#REF!+#REF!+#REF!+#REF!+#REF!+#REF!+#REF!+#REF!+#REF!+#REF!+#REF!+#REF!+#REF!+#REF!+#REF!+#REF!+#REF!+#REF!+#REF!+#REF!+#REF!+#REF!+#REF!+#REF!+#REF!+#REF!+#REF!+#REF!+#REF!+#REF!+#REF!+#REF!+#REF!+#REF!+#REF!+#REF!+#REF!+#REF!+#REF!+#REF!+#REF!+#REF!+#REF!+#REF!+#REF!+#REF!+#REF!+#REF!+#REF!+#REF!+#REF!+#REF!+#REF!+#REF!+#REF!+#REF!+#REF!+#REF!+#REF!+#REF!+#REF!+#REF!+#REF!+#REF!+#REF!+#REF!+#REF!+#REF!+#REF!+#REF!+#REF!+#REF!+#REF!+#REF!+#REF!+#REF!+#REF!+#REF!+#REF!+#REF!+#REF!+#REF!+#REF!+#REF!+#REF!+#REF!+#REF!+#REF!+#REF!+#REF!+#REF!+#REF!+#REF!+#REF!+#REF!+#REF!+#REF!+#REF!+#REF!+#REF!+#REF!+#REF!+#REF!+#REF!+#REF!+#REF!+#REF!+#REF!+#REF!+#REF!+#REF!+#REF!+#REF!+#REF! -> #REF!
A37: FHM | B37: 038 | C37: REMOCIÓN DE ESCOMBROS FENÓMENOS HIDROMETEOROLÓGICOS | D37: =$D$17 -> INCLUIDO | E37: Sublimite | F37: ='COTIZACIÓN M.N.'!D61 -> 31109.94 | G37: ='COTIZACIÓN M.N.'!E61*25% -> 0.013945383 | H37: =(((IF(I37="$ Prima",G37,G37*F37/R37))*$U$9)/365)*$J$15 -> 0.43502862 | I37: %o Al Millar | J37: =H37*$U$7 -> 0.0091791038 | K37: =(H37+J37)*$K$15 -> 0.071073235 | L37: =ROUND(H37+J37+K37,2) -> 0.52 | M37: =M36 -> 0.05 | N37: =H37*M37 -> 0.021751431 | O37: =N37 -> 0.021751431 | P37: =IF(Q37=1,"SI","NO") -> SI | Q37: =IF(D37="INCLUIDO",IF(F37<>0,1,0),0) -> 1 | R37: =IF(I37="%o Al Millar",1000,IF(I37="% Al Porciento",100,IF(I37="$ Prima",G37))) -> 1000 | S37: =IF(E37="Excluido",0,IF(D37="NO APLICA",0,1)) -> 1 | W37: ='UB (1)'!H37+'UB (2)'!H37+'UB (3)'!H37+#REF!+#REF!+#REF!+#REF!+#REF!+#REF!+#REF!+#REF!+#REF!+#REF!+#REF!+#REF!+#REF!+#REF!+#REF!+#REF!+#REF!+#REF!+#REF!+#REF!+#REF!+#REF!+#REF!+#REF!+#REF!+#REF!+#REF!+#REF!+#REF!+#REF!+#REF!+#REF!+#REF!+#REF!+#REF!+#REF!+#REF!+#REF!+#REF!+#REF!+#REF!+#REF!+#REF!+#REF!+#REF!+#REF!+#REF!+#REF!+#REF!+#REF!+#REF!+#REF!+#REF!+#REF!+#REF!+#REF!+#REF!+#REF!+#REF!+#REF!+#REF!+#REF!+#REF!+#REF!+#REF!+#REF!+#REF!+#REF!+#REF!+#REF!+#REF!+#REF!+#REF!+#REF!+#REF!+#REF!+#REF!+#REF!+#REF!+#REF!+#REF!+#REF!+#REF!+#REF!+#REF!+#REF!+#REF!+#REF!+#REF!+#REF!+#REF!+#REF!+#REF!+#REF!+#REF!+#REF!+#REF!+#REF!+#REF!+#REF!+#REF!+#REF!+#REF!+#REF!+#REF!+#REF!+#REF!+#REF!+#REF!+#REF!+#REF!+#REF!+#REF!+#REF!+#REF!+#REF!+#REF!+#REF!+#REF!+#REF!+#REF!+#REF!+#REF!+#REF!+#REF!+#REF!+#REF!+#REF!+#REF!+#REF!+#REF!+#REF!+#REF!+#REF!+#REF!+#REF!+#REF!+#REF!+#REF!+#REF!+#REF!+#REF!+#REF!+#REF!+#REF!+#REF!+#REF!+#REF!+#REF!+#REF!+#REF!+#REF!+#REF!+#REF!+#REF!+#REF!+#REF!+#REF!+#REF!+#REF!+#REF!+#REF!+#REF!+#REF!+#REF!+#REF!+#REF!+#REF!+#REF!+#REF!+#REF!+#REF!+#REF!+#REF!+#REF!+#REF!+#REF!+#REF!+#REF!+#REF!+#REF!+#REF!+#REF!+#REF!+#REF!+#REF!+#REF!+#REF!+#REF!+#REF!+#REF!+#REF!+#REF!+#REF!+#REF!+#REF!+#REF!+#REF!+#REF!+#REF!+#REF!+#REF!+#REF!+#REF!+#REF!+#REF!+#REF!+#REF!+#REF!+#REF!+#REF!+#REF!+#REF!+#REF!+#REF!+#REF!+#REF!+#REF!+#REF!+#REF!+#REF!+#REF!+#REF!+#REF!+#REF!+#REF!+#REF!+#REF!+#REF!+#REF!+#REF!+#REF!+#REF!+#REF!+#REF!+#REF!+#REF!+#REF!+#REF!+#REF!+#REF!+#REF!+#REF!+#REF!+#REF!+#REF!+#REF!+#REF!+#REF!+#REF!+#REF!+#REF!+#REF!+#REF!+#REF!+#REF!+#REF!+#REF!+#REF!+#REF!+#REF!+#REF!+#REF!+#REF!+#REF!+#REF!+#REF!+#REF!+#REF!+#REF!+#REF!+#REF!+#REF!+#REF!+#REF!+#REF!+#REF!+#REF!+#REF!+#REF!+#REF!+#REF!+#REF!+#REF!+#REF!+#REF!+#REF!+#REF!+#REF!+#REF!+#REF!+#REF!+#REF!+#REF!+#REF!+#REF!+#REF!+#REF!+#REF!+#REF!+#REF!+#REF!+#REF!+#REF!+#REF!+#REF!+#REF!+#REF!+#REF!+#REF!+#REF!+#REF!+#REF!+#REF!+#REF!+#REF!+#REF!+#REF!+#REF!+#REF!+#REF!+#REF!+#REF!+#REF!+#REF!+#REF!+#REF!+#REF!+#REF!+#REF!+#REF!+#REF!+#REF!+#REF!+#REF!+#REF!+#REF!+#REF!+#REF!+#REF!+#REF!+#REF!+#REF!+#REF!+#REF!+#REF!+#REF!+#REF!+#REF!+#REF!+#REF!+#REF!+#REF!+#REF!+#REF!+#REF!+#REF!+#REF!+#REF!+#REF!+#REF! -> #REF!
A38: 904 | B38: 1 | C38: TERREMOTO EDIFICIO | D38: =$D$17 -> INCLUIDO | M38: =M31 -> 0.05 | P38: =IF(Q38=1,"SI","NO") -> SI | Q38: =IF(D38="INCLUIDO",IF(F39<>0,1,0),0) -> 1 | W38: ='UB (1)'!H38+'UB (2)'!H38+'UB (3)'!H38+#REF!+#REF!+#REF!+#REF!+#REF!+#REF!+#REF!+#REF!+#REF!+#REF!+#REF!+#REF!+#REF!+#REF!+#REF!+#REF!+#REF!+#REF!+#REF!+#REF!+#REF!+#REF!+#REF!+#REF!+#REF!+#REF!+#REF!+#REF!+#REF!+#REF!+#REF!+#REF!+#REF!+#REF!+#REF!+#REF!+#REF!+#REF!+#REF!+#REF!+#REF!+#REF!+#REF!+#REF!+#REF!+#REF!+#REF!+#REF!+#REF!+#REF!+#REF!+#REF!+#REF!+#REF!+#REF!+#REF!+#REF!+#REF!+#REF!+#REF!+#REF!+#REF!+#REF!+#REF!+#REF!+#REF!+#REF!+#REF!+#REF!+#REF!+#REF!+#REF!+#REF!+#REF!+#REF!+#REF!+#REF!+#REF!+#REF!+#REF!+#REF!+#REF!+#REF!+#REF!+#REF!+#REF!+#REF!+#REF!+#REF!+#REF!+#REF!+#REF!+#REF!+#REF!+#REF!+#REF!+#REF!+#REF!+#REF!+#REF!+#REF!+#REF!+#REF!+#REF!+#REF!+#REF!+#REF!+#REF!+#REF!+#REF!+#REF!+#REF!+#REF!+#REF!+#REF!+#REF!+#REF!+#REF!+#REF!+#REF!+#REF!+#REF!+#REF!+#REF!+#REF!+#REF!+#REF!+#REF!+#REF!+#REF!+#REF!+#REF!+#REF!+#REF!+#REF!+#REF!+#REF!+#REF!+#REF!+#REF!+#REF!+#REF!+#REF!+#REF!+#REF!+#REF!+#REF!+#REF!+#REF!+#REF!+#REF!+#REF!+#REF!+#REF!+#REF!+#REF!+#REF!+#REF!+#REF!+#REF!+#REF!+#REF!+#REF!+#REF!+#REF!+#REF!+#REF!+#REF!+#REF!+#REF!+#REF!+#REF!+#REF!+#REF!+#REF!+#REF!+#REF!+#REF!+#REF!+#REF!+#REF!+#REF!+#REF!+#REF!+#REF!+#REF!+#REF!+#REF!+#REF!+#REF!+#REF!+#REF!+#REF!+#REF!+#REF!+#REF!+#REF!+#REF!+#REF!+#REF!+#REF!+#REF!+#REF!+#REF!+#REF!+#REF!+#REF!+#REF!+#REF!+#REF!+#REF!+#REF!+#REF!+#REF!+#REF!+#REF!+#REF!+#REF!+#REF!+#REF!+#REF!+#REF!+#REF!+#REF!+#REF!+#REF!+#REF!+#REF!+#REF!+#REF!+#REF!+#REF!+#REF!+#REF!+#REF!+#REF!+#REF!+#REF!+#REF!+#REF!+#REF!+#REF!+#REF!+#REF!+#REF!+#REF!+#REF!+#REF!+#REF!+#REF!+#REF!+#REF!+#REF!+#REF!+#REF!+#REF!+#REF!+#REF!+#REF!+#REF!+#REF!+#REF!+#REF!+#REF!+#REF!+#REF!+#REF!+#REF!+#REF!+#REF!+#REF!+#REF!+#REF!+#REF!+#REF!+#REF!+#REF!+#REF!+#REF!+#REF!+#REF!+#REF!+#REF!+#REF!+#REF!+#REF!+#REF!+#REF!+#REF!+#REF!+#REF!+#REF!+#REF!+#REF!+#REF!+#REF!+#REF!+#REF!+#REF!+#REF!+#REF!+#REF!+#REF!+#REF!+#REF!+#REF!+#REF!+#REF!+#REF!+#REF!+#REF!+#REF!+#REF!+#REF!+#REF!+#REF!+#REF!+#REF!+#REF!+#REF!+#REF!+#REF!+#REF!+#REF!+#REF!+#REF!+#REF!+#REF!+#REF!+#REF!+#REF!+#REF!+#REF!+#REF!+#REF!+#REF!+#REF!+#REF!+#REF!+#REF!+#REF!+#REF!+#REF!+#REF!+#REF!+#REF!+#REF!+#REF!+#REF!+#REF!+#REF!+#REF!+#REF!+#REF!+#REF!+#REF!+#REF!+#REF!+#REF!+#REF!+#REF! -> #REF!
A39: TEV | B39: 044 | C39: REMOCIÓN DE ESCOMBROS FENÓMENOS HIDROMETEOROLÓGICOS | D39: =$D$17 -> INCLUIDO | E39: Sublimite | F39: ='COTIZACIÓN M.N.'!D62 -> 31109.94 | G39: ='COTIZACIÓN M.N.'!E62 -> 0.04 | H39: =(((IF(I39="$ Prima",G39,G39*F39/R39))*$U$9)/365)*$J$15 -> 1.2478069 | I39: %o Al Millar | J39: =H39*$U$7 -> 0.026328726 | K39: =(H39+J39)*$K$15 -> 0.2038617 | L39: =ROUND(H39+J39+K39,2) -> 1.48 | M39: =M38 -> 0.05 | N39: =H39*M39 -> 0.062390345 | O39: =N39 -> 0.062390345 | P39: =IF(Q39=1,"SI","NO") -> SI | Q39: =IF(D39="INCLUIDO",IF(F39<>0,1,0),0) -> 1 | R39: =IF(I39="%o Al Millar",1000,IF(I39="% Al Porciento",100,IF(I39="$ Prima",G39))) -> 1000 | S39: =IF(E39="Excluido",0,IF(D39="NO APLICA",0,1)) -> 1 | W39: ='UB (1)'!H39+'UB (2)'!H39+'UB (3)'!H39+#REF!+#REF!+#REF!+#REF!+#REF!+#REF!+#REF!+#REF!+#REF!+#REF!+#REF!+#REF!+#REF!+#REF!+#REF!+#REF!+#REF!+#REF!+#REF!+#REF!+#REF!+#REF!+#REF!+#REF!+#REF!+#REF!+#REF!+#REF!+#REF!+#REF!+#REF!+#REF!+#REF!+#REF!+#REF!+#REF!+#REF!+#REF!+#REF!+#REF!+#REF!+#REF!+#REF!+#REF!+#REF!+#REF!+#REF!+#REF!+#REF!+#REF!+#REF!+#REF!+#REF!+#REF!+#REF!+#REF!+#REF!+#REF!+#REF!+#REF!+#REF!+#REF!+#REF!+#REF!+#REF!+#REF!+#REF!+#REF!+#REF!+#REF!+#REF!+#REF!+#REF!+#REF!+#REF!+#REF!+#REF!+#REF!+#REF!+#REF!+#REF!+#REF!+#REF!+#REF!+#REF!+#REF!+#REF!+#REF!+#REF!+#REF!+#REF!+#REF!+#REF!+#REF!+#REF!+#REF!+#REF!+#REF!+#REF!+#REF!+#REF!+#REF!+#REF!+#REF!+#REF!+#REF!+#REF!+#REF!+#REF!+#REF!+#REF!+#REF!+#REF!+#REF!+#REF!+#REF!+#REF!+#REF!+#REF!+#REF!+#REF!+#REF!+#REF!+#REF!+#REF!+#REF!+#REF!+#REF!+#REF!+#REF!+#REF!+#REF!+#REF!+#REF!+#REF!+#REF!+#REF!+#REF!+#REF!+#REF!+#REF!+#REF!+#REF!+#REF!+#REF!+#REF!+#REF!+#REF!+#REF!+#REF!+#REF!+#REF!+#REF!+#REF!+#REF!+#REF!+#REF!+#REF!+#REF!+#REF!+#REF!+#REF!+#REF!+#REF!+#REF!+#REF!+#REF!+#REF!+#REF!+#REF!+#REF!+#REF!+#REF!+#REF!+#REF!+#REF!+#REF!+#REF!+#REF!+#REF!+#REF!+#REF!+#REF!+#REF!+#REF!+#REF!+#REF!+#REF!+#REF!+#REF!+#REF!+#REF!+#REF!+#REF!+#REF!+#REF!+#REF!+#REF!+#REF!+#REF!+#REF!+#REF!+#REF!+#REF!+#REF!+#REF!+#REF!+#REF!+#REF!+#REF!+#REF!+#REF!+#REF!+#REF!+#REF!+#REF!+#REF!+#REF!+#REF!+#REF!+#REF!+#REF!+#REF!+#REF!+#REF!+#REF!+#REF!+#REF!+#REF!+#REF!+#REF!+#REF!+#REF!+#REF!+#REF!+#REF!+#REF!+#REF!+#REF!+#REF!+#REF!+#REF!+#REF!+#REF!+#REF!+#REF!+#REF!+#REF!+#REF!+#REF!+#REF!+#REF!+#REF!+#REF!+#REF!+#REF!+#REF!+#REF!+#REF!+#REF!+#REF!+#REF!+#REF!+#REF!+#REF!+#REF!+#REF!+#REF!+#REF!+#REF!+#REF!+#REF!+#REF!+#REF!+#REF!+#REF!+#REF!+#REF!+#REF!+#REF!+#REF!+#REF!+#REF!+#REF!+#REF!+#REF!+#REF!+#REF!+#REF!+#REF!+#REF!+#REF!+#REF!+#REF!+#REF!+#REF!+#REF!+#REF!+#REF!+#REF!+#REF!+#REF!+#REF!+#REF!+#REF!+#REF!+#REF!+#REF!+#REF!+#REF!+#REF!+#REF!+#REF!+#REF!+#REF!+#REF!+#REF!+#REF!+#REF!+#REF!+#REF!+#REF!+#REF!+#REF!+#REF!+#REF!+#REF!+#REF!+#REF!+#REF!+#REF!+#REF!+#REF!+#REF!+#REF!+#REF!+#REF!+#REF!+#REF!+#REF!+#REF!+#REF!+#REF!+#REF!+#REF!+#REF!+#REF!+#REF!+#REF!+#REF!+#REF!+#REF!+#REF!+#REF!+#REF!+#REF!+#REF!+#REF!+#REF!+#REF!+#REF! -> #REF!
C40: SUBTOTAL | D40: =D39 -> INCLUIDO | F40: =SUMIF(E18:E39,"Adicional",F18:F39) -> 0 | H40: =SUM(H18:H39) -> 152.38399 | J40: =SUM(J18:J39) -> 3.2153022 | K40: =SUM(K18:K39) -> 24.895887 | L40: =SUM(L18:L39) -> 180.52 | N40: =SUM(N18:N39) -> 11.245841 | O40: =SUM(O18:O39) -> 11.245841 | P40: =IF(Q40=1,"SI","NO") -> SI | Q40: =IF(D40="INCLUIDO",IF(H40<>0,1,0),0) -> 1 | W40: ='UB (1)'!H40+'UB (2)'!H40+'UB (3)'!H40+#REF!+#REF!+#REF!+#REF!+#REF!+#REF!+#REF!+#REF!+#REF!+#REF!+#REF!+#REF!+#REF!+#REF!+#REF!+#REF!+#REF!+#REF!+#REF!+#REF!+#REF!+#REF!+#REF!+#REF!+#REF!+#REF!+#REF!+#REF!+#REF!+#REF!+#REF!+#REF!+#REF!+#REF!+#REF!+#REF!+#REF!+#REF!+#REF!+#REF!+#REF!+#REF!+#REF!+#REF!+#REF!+#REF!+#REF!+#REF!+#REF!+#REF!+#REF!+#REF!+#REF!+#REF!+#REF!+#REF!+#REF!+#REF!+#REF!+#REF!+#REF!+#REF!+#REF!+#REF!+#REF!+#REF!+#REF!+#REF!+#REF!+#REF!+#REF!+#REF!+#REF!+#REF!+#REF!+#REF!+#REF!+#REF!+#REF!+#REF!+#REF!+#REF!+#REF!+#REF!+#REF!+#REF!+#REF!+#REF!+#REF!+#REF!+#REF!+#REF!+#REF!+#REF!+#REF!+#REF!+#REF!+#REF!+#REF!+#REF!+#REF!+#REF!+#REF!+#REF!+#REF!+#REF!+#REF!+#REF!+#REF!+#REF!+#REF!+#REF!+#REF!+#REF!+#REF!+#REF!+#REF!+#REF!+#REF!+#REF!+#REF!+#REF!+#REF!+#REF!+#REF!+#REF!+#REF!+#REF!+#REF!+#REF!+#REF!+#REF!+#REF!+#REF!+#REF!+#REF!+#REF!+#REF!+#REF!+#REF!+#REF!+#REF!+#REF!+#REF!+#REF!+#REF!+#REF!+#REF!+#REF!+#REF!+#REF!+#REF!+#REF!+#REF!+#REF!+#REF!+#REF!+#REF!+#REF!+#REF!+#REF!+#REF!+#REF!+#REF!+#REF!+#REF!+#REF!+#REF!+#REF!+#REF!+#REF!+#REF!+#REF!+#REF!+#REF!+#REF!+#REF!+#REF!+#REF!+#REF!+#REF!+#REF!+#REF!+#REF!+#REF!+#REF!+#REF!+#REF!+#REF!+#REF!+#REF!+#REF!+#REF!+#REF!+#REF!+#REF!+#REF!+#REF!+#REF!+#REF!+#REF!+#REF!+#REF!+#REF!+#REF!+#REF!+#REF!+#REF!+#REF!+#REF!+#REF!+#REF!+#REF!+#REF!+#REF!+#REF!+#REF!+#REF!+#REF!+#REF!+#REF!+#REF!+#REF!+#REF!+#REF!+#REF!+#REF!+#REF!+#REF!+#REF!+#REF!+#REF!+#REF!+#REF!+#REF!+#REF!+#REF!+#REF!+#REF!+#REF!+#REF!+#REF!+#REF!+#REF!+#REF!+#REF!+#REF!+#REF!+#REF!+#REF!+#REF!+#REF!+#REF!+#REF!+#REF!+#REF!+#REF!+#REF!+#REF!+#REF!+#REF!+#REF!+#REF!+#REF!+#REF!+#REF!+#REF!+#REF!+#REF!+#REF!+#REF!+#REF!+#REF!+#REF!+#REF!+#REF!+#REF!+#REF!+#REF!+#REF!+#REF!+#REF!+#REF!+#REF!+#REF!+#REF!+#REF!+#REF!+#REF!+#REF!+#REF!+#REF!+#REF!+#REF!+#REF!+#REF!+#REF!+#REF!+#REF!+#REF!+#REF!+#REF!+#REF!+#REF!+#REF!+#REF!+#REF!+#REF!+#REF!+#REF!+#REF!+#REF!+#REF!+#REF!+#REF!+#REF!+#REF!+#REF!+#REF!+#REF!+#REF!+#REF!+#REF!+#REF!+#REF!+#REF!+#REF!+#REF!+#REF!+#REF!+#REF!+#REF!+#REF!+#REF!+#REF!+#REF!+#REF!+#REF!+#REF!+#REF!+#REF!+#REF!+#REF!+#REF!+#REF!+#REF!+#REF!+#REF!+#REF!+#REF!+#REF!+#REF!+#REF!+#REF!+#REF!+#REF!+#REF!+#REF!+#REF!+#REF!+#REF! -> #REF!
A41: 902 | B41: 2 | C41: INCENDIO CONTENIDOS | D41: =$D$17 -> INCLUIDO | F41: ='COTIZACIÓN M.N.'!D33 -> 8.6921645e+08 | G41: ='COTIZACIÓN M.N.'!E33+'COTIZACIÓN M.N.'!E34+'COTIZACIÓN M.N.'!E35 -> 0.3078153 | M41: =M17 -> 0.1201 | P41: =IF(Q41=1,"SI","NO") -> SI | Q41: =IF(D41="INCLUIDO",IF(F41<>0,1,0),0) -> 1 | T41: =G41 -> 0.3078153 | W41: ='UB (1)'!H41+'UB (2)'!H41+'UB (3)'!H41+#REF!+#REF!+#REF!+#REF!+#REF!+#REF!+#REF!+#REF!+#REF!+#REF!+#REF!+#REF!+#REF!+#REF!+#REF!+#REF!+#REF!+#REF!+#REF!+#REF!+#REF!+#REF!+#REF!+#REF!+#REF!+#REF!+#REF!+#REF!+#REF!+#REF!+#REF!+#REF!+#REF!+#REF!+#REF!+#REF!+#REF!+#REF!+#REF!+#REF!+#REF!+#REF!+#REF!+#REF!+#REF!+#REF!+#REF!+#REF!+#REF!+#REF!+#REF!+#REF!+#REF!+#REF!+#REF!+#REF!+#REF!+#REF!+#REF!+#REF!+#REF!+#REF!+#REF!+#REF!+#REF!+#REF!+#REF!+#REF!+#REF!+#REF!+#REF!+#REF!+#REF!+#REF!+#REF!+#REF!+#REF!+#REF!+#REF!+#REF!+#REF!+#REF!+#REF!+#REF!+#REF!+#REF!+#REF!+#REF!+#REF!+#REF!+#REF!+#REF!+#REF!+#REF!+#REF!+#REF!+#REF!+#REF!+#REF!+#REF!+#REF!+#REF!+#REF!+#REF!+#REF!+#REF!+#REF!+#REF!+#REF!+#REF!+#REF!+#REF!+#REF!+#REF!+#REF!+#REF!+#REF!+#REF!+#REF!+#REF!+#REF!+#REF!+#REF!+#REF!+#REF!+#REF!+#REF!+#REF!+#REF!+#REF!+#REF!+#REF!+#REF!+#REF!+#REF!+#REF!+#REF!+#REF!+#REF!+#REF!+#REF!+#REF!+#REF!+#REF!+#REF!+#REF!+#REF!+#REF!+#REF!+#REF!+#REF!+#REF!+#REF!+#REF!+#REF!+#REF!+#REF!+#REF!+#REF!+#REF!+#REF!+#REF!+#REF!+#REF!+#REF!+#REF!+#REF!+#REF!+#REF!+#REF!+#REF!+#REF!+#REF!+#REF!+#REF!+#REF!+#REF!+#REF!+#REF!+#REF!+#REF!+#REF!+#REF!+#REF!+#REF!+#REF!+#REF!+#REF!+#REF!+#REF!+#REF!+#REF!+#REF!+#REF!+#REF!+#REF!+#REF!+#REF!+#REF!+#REF!+#REF!+#REF!+#REF!+#REF!+#REF!+#REF!+#REF!+#REF!+#REF!+#REF!+#REF!+#REF!+#REF!+#REF!+#REF!+#REF!+#REF!+#REF!+#REF!+#REF!+#REF!+#REF!+#REF!+#REF!+#REF!+#REF!+#REF!+#REF!+#REF!+#REF!+#REF!+#REF!+#REF!+#REF!+#REF!+#REF!+#REF!+#REF!+#REF!+#REF!+#REF!+#REF!+#REF!+#REF!+#REF!+#REF!+#REF!+#REF!+#REF!+#REF!+#REF!+#REF!+#REF!+#REF!+#REF!+#REF!+#REF!+#REF!+#REF!+#REF!+#REF!+#REF!+#REF!+#REF!+#REF!+#REF!+#REF!+#REF!+#REF!+#REF!+#REF!+#REF!+#REF!+#REF!+#REF!+#REF!+#REF!+#REF!+#REF!+#REF!+#REF!+#REF!+#REF!+#REF!+#REF!+#REF!+#REF!+#REF!+#REF!+#REF!+#REF!+#REF!+#REF!+#REF!+#REF!+#REF!+#REF!+#REF!+#REF!+#REF!+#REF!+#REF!+#REF!+#REF!+#REF!+#REF!+#REF!+#REF!+#REF!+#REF!+#REF!+#REF!+#REF!+#REF!+#REF!+#REF!+#REF!+#REF!+#REF!+#REF!+#REF!+#REF!+#REF!+#REF!+#REF!+#REF!+#REF!+#REF!+#REF!+#REF!+#REF!+#REF!+#REF!+#REF!+#REF!+#REF!+#REF!+#REF!+#REF!+#REF!+#REF!+#REF!+#REF!+#REF!+#REF!+#REF!+#REF!+#REF!+#REF!+#REF!+#REF!+#REF!+#REF!+#REF!+#REF!+#REF!+#REF!+#REF!+#REF!+#REF!+#REF! -> #REF!
A42: INCENDIO | B42: 013 | C42: COBERTURA BÁSICA | D42: =$D$17 -> INCLUIDO | E42: Sublimite | F42: =$F$41*S42 -> 8.6921645e+08 | G42: =V42 -> 0.24625224 | H42: =(((IF(I42="$ Prima",G42,G42*F42/R42))*$U$9)/365)*$J$15 -> 214632.93 | I42: %o Al Millar | J42: =H42*$U$7 -> 4528.7548 | K42: =(H42+J42)*$K$15 -> 35065.869 | L42: =ROUND(H42+J42+K42,2) -> 254227.55 | M42: =$M$41 -> 0.1201 | N42: =H42*M42 -> 25777.414 | O42: =N42 -> 25777.414 | P42: =IF(Q42=1,"SI","NO") -> SI | Q42: =IF(D42="INCLUIDO",IF(F42<>0,1,0),0) -> 1 | R42: =IF(I42="%o Al Millar",1000,IF(I42="% Al Porciento",100,IF(I42="$ Prima",G42))) -> 1000 | S42: =IF(E42="Excluido",0,IF(D42="NO APLICA",0,1)) -> 1 | T42: 0.7 | U42: =IF(E42="Excluido",0,T41*T42) -> 0.21547071 | V42: =IF(F41=0,0,(U51-U46-U44-U50)+(T41-U51)) -> 0.24625224 | W42: ='UB (1)'!H42+'UB (2)'!H42+'UB (3)'!H42+#REF!+#REF!+#REF!+#REF!+#REF!+#REF!+#REF!+#REF!+#REF!+#REF!+#REF!+#REF!+#REF!+#REF!+#REF!+#REF!+#REF!+#REF!+#REF!+#REF!+#REF!+#REF!+#REF!+#REF!+#REF!+#REF!+#REF!+#REF!+#REF!+#REF!+#REF!+#REF!+#REF!+#REF!+#REF!+#REF!+#REF!+#REF!+#REF!+#REF!+#REF!+#REF!+#REF!+#REF!+#REF!+#REF!+#REF!+#REF!+#REF!+#REF!+#REF!+#REF!+#REF!+#REF!+#REF!+#REF!+#REF!+#REF!+#REF!+#REF!+#REF!+#REF!+#REF!+#REF!+#REF!+#REF!+#REF!+#REF!+#REF!+#REF!+#REF!+#REF!+#REF!+#REF!+#REF!+#REF!+#REF!+#REF!+#REF!+#REF!+#REF!+#REF!+#REF!+#REF!+#REF!+#REF!+#REF!+#REF!+#REF!+#REF!+#REF!+#REF!+#REF!+#REF!+#REF!+#REF!+#REF!+#REF!+#REF!+#REF!+#REF!+#REF!+#REF!+#REF!+#REF!+#REF!+#REF!+#REF!+#REF!+#REF!+#REF!+#REF!+#REF!+#REF!+#REF!+#REF!+#REF!+#REF!+#REF!+#REF!+#REF!+#REF!+#REF!+#REF!+#REF!+#REF!+#REF!+#REF!+#REF!+#REF!+#REF!+#REF!+#REF!+#REF!+#REF!+#REF!+#REF!+#REF!+#REF!+#REF!+#REF!+#REF!+#REF!+#REF!+#REF!+#REF!+#REF!+#REF!+#REF!+#REF!+#REF!+#REF!+#REF!+#REF!+#REF!+#REF!+#REF!+#REF!+#REF!+#REF!+#REF!+#REF!+#REF!+#REF!+#REF!+#REF!+#REF!+#REF!+#REF!+#REF!+#REF!+#REF!+#REF!+#REF!+#REF!+#REF!+#REF!+#REF!+#REF!+#REF!+#REF!+#REF!+#REF!+#REF!+#REF!+#REF!+#REF!+#REF!+#REF!+#REF!+#REF!+#REF!+#REF!+#REF!+#REF!+#REF!+#REF!+#REF!+#REF!+#REF!+#REF!+#REF!+#REF!+#REF!+#REF!+#REF!+#REF!+#REF!+#REF!+#REF!+#REF!+#REF!+#REF!+#REF!+#REF!+#REF!+#REF!+#REF!+#REF!+#REF!+#REF!+#REF!+#REF!+#REF!+#REF!+#REF!+#REF!+#REF!+#REF!+#REF!+#REF!+#REF!+#REF!+#REF!+#REF!+#REF!+#REF!+#REF!+#REF!+#REF!+#REF!+#REF!+#REF!+#REF!+#REF!+#REF!+#REF!+#REF!+#REF!+#REF!+#REF!+#REF!+#REF!+#REF!+#REF!+#REF!+#REF!+#REF!+#REF!+#REF!+#REF!+#REF!+#REF!+#REF!+#REF!+#REF!+#REF!+#REF!+#REF!+#REF!+#REF!+#REF!+#REF!+#REF!+#REF!+#REF!+#REF!+#REF!+#REF!+#REF!+#REF!+#REF!+#REF!+#REF!+#REF!+#REF!+#REF!+#REF!+#REF!+#REF!+#REF!+#REF!+#REF!+#REF!+#REF!+#REF!+#REF!+#REF!+#REF!+#REF!+#REF!+#REF!+#REF!+#REF!+#REF!+#REF!+#REF!+#REF!+#REF!+#REF!+#REF!+#REF!+#REF!+#REF!+#REF!+#REF!+#REF!+#REF!+#REF!+#REF!+#REF!+#REF!+#REF!+#REF!+#REF!+#REF!+#REF!+#REF!+#REF!+#REF!+#REF!+#REF!+#REF!+#REF!+#REF!+#REF!+#REF!+#REF!+#REF!+#REF!+#REF!+#REF!+#REF!+#REF!+#REF!+#REF!+#REF!+#REF!+#REF!+#REF!+#REF!+#REF!+#REF!+#REF!+#REF!+#REF!+#REF!+#REF!+#REF!+#REF!+#REF! -> #REF!
A43: INCENDIO | C43: =$O$12 -> 0 | D43: =$D$17 -> INCLUIDO | E43: =E42 -> Sublimite | F43: =(F42*$O$12)*S42 -> 0 | G43: =G42*0.35 -> 0.086188284 | H43: =(IF(I43="$ Prima",G43,G43*F43/R43))*$U$9 -> 0 | I43: %o Al Millar | J43: =H43*$U$7 -> 0 | K43: =(H43+J43)*$K$15 -> 0 | L43: =ROUND(H43+J43+K43,2) -> 0 | M43: =$M$41 -> 0.1201 | N43: =H43*M43 -> 0 | O43: =N43 -> 0 | P43: =IF(Q43=1,"SI","NO") -> NO | Q43: =IF(D43="INCLUIDO",IF(F43<>0,1,0),0) -> 0 | R43: =IF(I43="%o Al Millar",1000,IF(I43="% Al Porciento",100,IF(I43="$ Prima",G43))) -> 1000 | S43: =IF(E43="Excluido",0,IF(D43="NO APLICA",0,1)) -> 1
A44: INCENDIO | B44: 017 | C44: EXTENSIÓN DE CUBIERTA (SIN HURACÁN Y GRANIZO) | D44: =$D$17 -> INCLUIDO | E44: Sublimite | F44: =$F$41*S44 -> 8.6921645e+08 | G44: =V44 -> 0.03078153 | H44: =(((IF(I44="$ Prima",G44,G44*F44/R44))*$U$9)/365)*$J$15 -> 26829.116 | I44: %o Al Millar | J44: =H44*$U$7 -> 566.09434 | K44: =(H44+J44)*$K$15 -> 4383.2336 | L44: =ROUND(H44+J44+K44,2) -> 31778.44 | M44: =$M$41 -> 0.1201 | N44: =H44*M44 -> 3222.1768 | O44: =N44 -> 3222.1768 | P44: =IF(Q44=1,"SI","NO") -> SI | Q44: =IF(D44="INCLUIDO",IF(F44<>0,1,0),0) -> 1 | R44: =IF(I44="%o Al Millar",1000,IF(I44="% Al Porciento",100,IF(I44="$ Prima",G44))) -> 1000 | S44: =IF(E44="Excluido",0,IF(D44="NO APLICA",0,1)) -> 1 | T44: 0.1 | U44: =IF(E44="Excluido",0,T41*T44) -> 0.03078153 | V44: =IF(F41=0,0,U44) -> 0.03078153 | W44: ='UB (1)'!H44+'UB (2)'!H44+'UB (3)'!H44+#REF!+#REF!+#REF!+#REF!+#REF!+#REF!+#REF!+#REF!+#REF!+#REF!+#REF!+#REF!+#REF!+#REF!+#REF!+#REF!+#REF!+#REF!+#REF!+#REF!+#REF!+#REF!+#REF!+#REF!+#REF!+#REF!+#REF!+#REF!+#REF!+#REF!+#REF!+#REF!+#REF!+#REF!+#REF!+#REF!+#REF!+#REF!+#REF!+#REF!+#REF!+#REF!+#REF!+#REF!+#REF!+#REF!+#REF!+#REF!+#REF!+#REF!+#REF!+#REF!+#REF!+#REF!+#REF!+#REF!+#REF!+#REF!+#REF!+#REF!+#REF!+#REF!+#REF!+#REF!+#REF!+#REF!+#REF!+#REF!+#REF!+#REF!+#REF!+#REF!+#REF!+#REF!+#REF!+#REF!+#REF!+#REF!+#REF!+#REF!+#REF!+#REF!+#REF!+#REF!+#REF!+#REF!+#REF!+#REF!+#REF!+#REF!+#REF!+#REF!+#REF!+#REF!+#REF!+#REF!+#REF!+#REF!+#REF!+#REF!+#REF!+#REF!+#REF!+#REF!+#REF!+#REF!+#REF!+#REF!+#REF!+#REF!+#REF!+#REF!+#REF!+#REF!+#REF!+#REF!+#REF!+#REF!+#REF!+#REF!+#REF!+#REF!+#REF!+#REF!+#REF!+#REF!+#REF!+#REF!+#REF!+#REF!+#REF!+#REF!+#REF!+#REF!+#REF!+#REF!+#REF!+#REF!+#REF!+#REF!+#REF!+#REF!+#REF!+#REF!+#REF!+#REF!+#REF!+#REF!+#REF!+#REF!+#REF!+#REF!+#REF!+#REF!+#REF!+#REF!+#REF!+#REF!+#REF!+#REF!+#REF!+#REF!+#REF!+#REF!+#REF!+#REF!+#REF!+#REF!+#REF!+#REF!+#REF!+#REF!+#REF!+#REF!+#REF!+#REF!+#REF!+#REF!+#REF!+#REF!+#REF!+#REF!+#REF!+#REF!+#REF!+#REF!+#REF!+#REF!+#REF!+#REF!+#REF!+#REF!+#REF!+#REF!+#REF!+#REF!+#REF!+#REF!+#REF!+#REF!+#REF!+#REF!+#REF!+#REF!+#REF!+#REF!+#REF!+#REF!+#REF!+#REF!+#REF!+#REF!+#REF!+#REF!+#REF!+#REF!+#REF!+#REF!+#REF!+#REF!+#REF!+#REF!+#REF!+#REF!+#REF!+#REF!+#REF!+#REF!+#REF!+#REF!+#REF!+#REF!+#REF!+#REF!+#REF!+#REF!+#REF!+#REF!+#REF!+#REF!+#REF!+#REF!+#REF!+#REF!+#REF!+#REF!+#REF!+#REF!+#REF!+#REF!+#REF!+#REF!+#REF!+#REF!+#REF!+#REF!+#REF!+#REF!+#REF!+#REF!+#REF!+#REF!+#REF!+#REF!+#REF!+#REF!+#REF!+#REF!+#REF!+#REF!+#REF!+#REF!+#REF!+#REF!+#REF!+#REF!+#REF!+#REF!+#REF!+#REF!+#REF!+#REF!+#REF!+#REF!+#REF!+#REF!+#REF!+#REF!+#REF!+#REF!+#REF!+#REF!+#REF!+#REF!+#REF!+#REF!+#REF!+#REF!+#REF!+#REF!+#REF!+#REF!+#REF!+#REF!+#REF!+#REF!+#REF!+#REF!+#REF!+#REF!+#REF!+#REF!+#REF!+#REF!+#REF!+#REF!+#REF!+#REF!+#REF!+#REF!+#REF!+#REF!+#REF!+#REF!+#REF!+#REF!+#REF!+#REF!+#REF!+#REF!+#REF!+#REF!+#REF!+#REF!+#REF!+#REF!+#REF!+#REF!+#REF!+#REF!+#REF!+#REF!+#REF!+#REF!+#REF!+#REF!+#REF!+#REF!+#REF!+#REF!+#REF!+#REF!+#REF!+#REF!+#REF!+#REF!+#REF!+#REF!+#REF!+#REF!+#REF! -> #REF!
A45: INCENDIO | C45: =$O$12 -> 0 | D45: =$D$17 -> INCLUIDO | E45: =E44 -> Sublimite | F45: =(F44*$O$12)*S44 -> 0 | G45: =G44*0.35 -> 0.010773536 | H45: =(IF(I45="$ Prima",G45,G45*F45/R45))*$U$9 -> 0 | I45: %o Al Millar | J45: =H45*$U$7 -> 0 | K45: =(H45+J45)*$K$15 -> 0 | L45: =ROUND(H45+J45+K45,2) -> 0 | M45: =$M$41 -> 0.1201 | N45: =H45*M45 -> 0 | O45: =N45 -> 0 | P45: =IF(Q45=1,"SI","NO") -> NO | Q45: =IF(D45="INCLUIDO",IF(F45<>0,1,0),0) -> 0 | R45: =IF(I45="%o Al Millar",1000,IF(I45="% Al Porciento",100,IF(I45="$ Prima",G45))) -> 1000 | S45: =IF(E45="Excluido",0,IF(D45="NO APLICA",0,1)) -> 1
A46: INCENDIO | B46: 028 | C46: TODO RIESGO | D46: =$D$17 -> INCLUIDO | E46: Sublimite | F46: ='COTIZACIÓN M.N.'!D35 -> 8.6921645e+08 | G46: =V46 -> 0.03078153 | H46: =(((IF(I46="$ Prima",G46,G46*F46/R46))*$U$9)/365)*$J$15 -> 26829.116 | I46: %o Al Millar | J46: =H46*$U$7 -> 566.09434 | K46: =(H46+J46)*$K$15 -> 4383.2336 | L46: =ROUND(H46+J46+K46,2) -> 31778.44 | M46: =$M$41 -> 0.1201 | N46: =H46*M46 -> 3222.1768 | O46: =N46 -> 3222.1768 | P46: =IF(Q46=1,"SI","NO") -> SI | Q46: =IF(D46="INCLUIDO",IF(F46<>0,1,0),0) -> 1 | R46: =IF(I46="%o Al Millar",1000,IF(I46="% Al Porciento",100,IF(I46="$ Prima",G46))) -> 1000 | S46: =IF(E46="Excluido",0,IF(D46="NO APLICA",0,1)) -> 1 | T46: 0.1 | U46: =IF(E46="Excluido",0,T41*T46) -> 0.03078153 | V46: =IF(F41=0,0,U46) -> 0.03078153 | W46: ='UB (1)'!H46+'UB (2)'!H46+'UB (3)'!H46+#REF!+#REF!+#REF!+#REF!+#REF!+#REF!+#REF!+#REF!+#REF!+#REF!+#REF!+#REF!+#REF!+#REF!+#REF!+#REF!+#REF!+#REF!+#REF!+#REF!+#REF!+#REF!+#REF!+#REF!+#REF!+#REF!+#REF!+#REF!+#REF!+#REF!+#REF!+#REF!+#REF!+#REF!+#REF!+#REF!+#REF!+#REF!+#REF!+#REF!+#REF!+#REF!+#REF!+#REF!+#REF!+#REF!+#REF!+#REF!+#REF!+#REF!+#REF!+#REF!+#REF!+#REF!+#REF!+#REF!+#REF!+#REF!+#REF!+#REF!+#REF!+#REF!+#REF!+#REF!+#REF!+#REF!+#REF!+#REF!+#REF!+#REF!+#REF!+#REF!+#REF!+#REF!+#REF!+#REF!+#REF!+#REF!+#REF!+#REF!+#REF!+#REF!+#REF!+#REF!+#REF!+#REF!+#REF!+#REF!+#REF!+#REF!+#REF!+#REF!+#REF!+#REF!+#REF!+#REF!+#REF!+#REF!+#REF!+#REF!+#REF!+#REF!+#REF!+#REF!+#REF!+#REF!+#REF!+#REF!+#REF!+#REF!+#REF!+#REF!+#REF!+#REF!+#REF!+#REF!+#REF!+#REF!+#REF!+#REF!+#REF!+#REF!+#REF!+#REF!+#REF!+#REF!+#REF!+#REF!+#REF!+#REF!+#REF!+#REF!+#REF!+#REF!+#REF!+#REF!+#REF!+#REF!+#REF!+#REF!+#REF!+#REF!+#REF!+#REF!+#REF!+#REF!+#REF!+#REF!+#REF!+#REF!+#REF!+#REF!+#REF!+#REF!+#REF!+#REF!+#REF!+#REF!+#REF!+#REF!+#REF!+#REF!+#REF!+#REF!+#REF!+#REF!+#REF!+#REF!+#REF!+#REF!+#REF!+#REF!+#REF!+#REF!+#REF!+#REF!+#REF!+#REF!+#REF!+#REF!+#REF!+#REF!+#REF!+#REF!+#REF!+#REF!+#REF!+#REF!+#REF!+#REF!+#REF!+#REF!+#REF!+#REF!+#REF!+#REF!+#REF!+#REF!+#REF!+#REF!+#REF!+#REF!+#REF!+#REF!+#REF!+#REF!+#REF!+#REF!+#REF!+#REF!+#REF!+#REF!+#REF!+#REF!+#REF!+#REF!+#REF!+#REF!+#REF!+#REF!+#REF!+#REF!+#REF!+#REF!+#REF!+#REF!+#REF!+#REF!+#REF!+#REF!+#REF!+#REF!+#REF!+#REF!+#REF!+#REF!+#REF!+#REF!+#REF!+#REF!+#REF!+#REF!+#REF!+#REF!+#REF!+#REF!+#REF!+#REF!+#REF!+#REF!+#REF!+#REF!+#REF!+#REF!+#REF!+#REF!+#REF!+#REF!+#REF!+#REF!+#REF!+#REF!+#REF!+#REF!+#REF!+#REF!+#REF!+#REF!+#REF!+#REF!+#REF!+#REF!+#REF!+#REF!+#REF!+#REF!+#REF!+#REF!+#REF!+#REF!+#REF!+#REF!+#REF!+#REF!+#REF!+#REF!+#REF!+#REF!+#REF!+#REF!+#REF!+#REF!+#REF!+#REF!+#REF!+#REF!+#REF!+#REF!+#REF!+#REF!+#REF!+#REF!+#REF!+#REF!+#REF!+#REF!+#REF!+#REF!+#REF!+#REF!+#REF!+#REF!+#REF!+#REF!+#REF!+#REF!+#REF!+#REF!+#REF!+#REF!+#REF!+#REF!+#REF!+#REF!+#REF!+#REF!+#REF!+#REF!+#REF!+#REF!+#REF!+#REF!+#REF!+#REF!+#REF!+#REF!+#REF!+#REF!+#REF!+#REF!+#REF!+#REF!+#REF!+#REF!+#REF!+#REF!+#REF!+#REF!+#REF!+#REF!+#REF!+#REF!+#REF!+#REF!+#REF!+#REF!+#REF!+#REF!+#REF!+#REF!+#REF! -> #REF!
A47: INCENDIO | C47: =$O$12 -> 0 | D47: =$D$17 -> INCLUIDO | E47: =E46 -> Sublimite | F47: =(F46*$O$12)*S46 -> 0 | G47: =G46*0.35 -> 0.010773536 | H47: =(IF(I47="$ Prima",G47,G47*F47/R47))*$U$9 -> 0 | I47: %o Al Millar | J47: =H47*$U$7 -> 0 | K47: =(H47+J47)*$K$15 -> 0 | L47: =ROUND(H47+J47+K47,2) -> 0 | M47: =$M$41 -> 0.1201 | N47: =H47*M47 -> 0 | O47: =N47 -> 0 | P47: =IF(Q47=1,"SI","NO") -> NO | Q47: =IF(D47="INCLUIDO",IF(F47<>0,1,0),0) -> 0 | R47: =IF(I47="%o Al Millar",1000,IF(I47="% Al Porciento",100,IF(I47="$ Prima",G47))) -> 1000 | S47: =IF(E47="Excluido",0,IF(D47="NO APLICA",0,1)) -> 1
A48: INCENDIO | B48: 016 | C48: COMBUSTIÓN ESPONTANEA | D48: =$D$17 -> INCLUIDO | E48: Sublimite | F48: 0 | G48: 0 | H48: =(IF(I48="$ Prima",G48,G48*F48/R48))*$U$9 -> 0 | I48: %o Al Millar | J48: =H48*$U$7 -> 0 | K48: =(H48+J48)*$K$15 -> 0 | L48: =ROUND(H48+J48+K48,2) -> 0 | M48: =$M$41 -> 0.1201 | N48: =H48*M48 -> 0 | O48: =N48 -> 0 | P48: =IF(Q48=1,"SI","NO") -> NO | Q48: =IF(D48="INCLUIDO",IF(F48<>0,1,0),0) -> 0 | R48: =IF(I48="%o Al Millar",1000,IF(I48="% Al Porciento",100,IF(I48="$ Prima",G48))) -> 1000 | S48: =IF(E48="Excluido",0,IF(D48="NO APLICA",0,1)) -> 1
A49: INCENDIO | C49: =$O$12 -> 0 | D49: =$D$17 -> INCLUIDO | E49: =E48 -> Sublimite | F49: =(F48*$O$12)*S48 -> 0 | G49: =G48*0.35 -> 0 | H49: =(IF(I49="$ Prima",G49,G49*F49/R49))*$U$9 -> 0 | I49: %o Al Millar | J49: =H49*$U$7 -> 0 | K49: =(H49+J49)*$K$15 -> 0 | L49: =ROUND(H49+J49+K49,2) -> 0 | M49: =$M$41 -> 0.1201 | N49: =H49*M49 -> 0 | O49: =N49 -> 0 | P49: =IF(Q49=1,"SI","NO") -> NO | Q49: =IF(D49="INCLUIDO",IF(F49<>0,1,0),0) -> 0 | R49: =IF(I49="%o Al Millar",1000,IF(I49="% Al Porciento",100,IF(I49="$ Prima",G49))) -> 1000 | S49: =IF(E49="Excluido",0,IF(D49="NO APLICA",0,1)) -> 1
A50: INCENDIO | B50: 229 | C50: DERRAME DE P.C.I | D50: =$D$17 -> INCLUIDO | E50: Excluido | F50: =$F$41*S50 -> 0 | G50: =V50 -> 0 | H50: =(IF(I50="$ Prima",G50,G50*F50/R50))*$U$9 -> 0 | I50: %o Al Millar | J50: =H50*$U$7 -> 0 | K50: =(H50+J50)*$K$15 -> 0 | L50: =ROUND(H50+J50+K50,2) -> 0 | M50: =$M$41 -> 0.1201 | N50: =H50*M50 -> 0 | O50: =N50 -> 0 | P50: =IF(Q50=1,"SI","NO") -> NO | Q50: =IF(D50="INCLUIDO",IF(F50<>0,1,0),0) -> 0 | R50: =IF(I50="%o Al Millar",1000,IF(I50="% Al Porciento",100,IF(I50="$ Prima",G50))) -> 1000 | S50: =IF(E50="Excluido",0,IF(D50="NO APLICA",0,1)) -> 0 | T50: 0.1 | U50: =IF(E50="Excluido",0,T41*T50) -> 0 | V50: =IF(F41=0,0,U50) -> 0
A51: INCENDIO | C51: =$O$12 -> 0 | D51: =$D$17 -> INCLUIDO | E51: =E50 -> Excluido | F51: =(F50*$O$12)*S50 -> 0 | G51: =G50*0.35 -> 0 | H51: =(IF(I51="$ Prima",G51,G51*F51/R51))*$U$9 -> 0 | I51: %o Al Millar | J51: =H51*$U$7 -> 0 | K51: =(H51+J51)*$K$15 -> 0 | L51: =ROUND(H51+J51+K51,2) -> 0 | M51: =$M$41 -> 0.1201 | N51: =H51*M51 -> 0 | O51: =N51 -> 0 | P51: =IF(Q51=1,"SI","NO") -> NO | Q51: =IF(D51="INCLUIDO",IF(F51<>0,1,0),0) -> 0 | R51: =IF(I51="%o Al Millar",1000,IF(I51="% Al Porciento",100,IF(I51="$ Prima",G51))) -> 1000 | S51: =IF(E51="Excluido",0,IF(D51="NO APLICA",0,1)) -> 0 | T51: =SUM(T42:T50) -> 1 | U51: =SUM(U42:U50) -> 0.27703377 | V51: =SUM(V42:V50) -> 0.3078153
A52: INCENDIO | B52: 230 | C52: EXISTENCIAS | D52: =$D$17 -> INCLUIDO | E52: Sublimite | F52: 0 | G52: 0 | H52: =(IF(I52="$ Prima",G52,G52*F52/R52))*$U$9 -> 0 | I52: %o Al Millar | J52: =H52*$U$7 -> 0 | K52: =(H52+J52)*$K$15 -> 0 | L52: =ROUND(H52+J52+K52,2) -> 0 | M52: =$M$41 -> 0.1201 | N52: =H52*M52 -> 0 | O52: =N52 -> 0 | P52: =IF(Q52=1,"SI","NO") -> NO | Q52: =IF(D52="INCLUIDO",IF(F52<>0,1,0),0) -> 0 | R52: =IF(I52="%o Al Millar",1000,IF(I52="% Al Porciento",100,IF(I52="$ Prima",G52))) -> 1000 | S52: =IF(E52="Excluido",0,IF(D52="NO APLICA",0,1)) -> 1
A53: INCENDIO | C53: =$O$12 -> 0 | D53: =$D$17 -> INCLUIDO | E53: =E52 -> Sublimite | F53: =(F52*$O$12)*S52 -> 0 | G53: =G52*0.35 -> 0 | H53: =(IF(I53="$ Prima",G53,G53*F53/R53))*$U$9 -> 0 | I53: %o Al Millar | J53: =H53*$U$7 -> 0 | K53: =(H53+J53)*$K$15 -> 0 | L53: =ROUND(H53+J53+K53,2) -> 0 | M53: =$M$41 -> 0.1201 | N53: =H53*M53 -> 0 | O53: =N53 -> 0 | P53: =IF(Q53=1,"SI","NO") -> NO | Q53: =IF(D53="INCLUIDO",IF(F53<>0,1,0),0) -> 0 | R53: =IF(I53="%o Al Millar",1000,IF(I53="% Al Porciento",100,IF(I53="$ Prima",G53))) -> 1000 | S53: =IF(E53="Excluido",0,IF(D53="NO APLICA",0,1)) -> 1
A54: INCENDIO | B54: 231 | C54: INCISO FLOTANTE | D54: =$D$17 -> INCLUIDO | E54: Sublimite | F54: 0 | G54: 0 | H54: =(IF(I54="$ Prima",G54,G54*F54/R54))*$U$9 -> 0 | I54: %o Al Millar | J54: =H54*$U$7 -> 0 | K54: =(H54+J54)*$K$15 -> 0 | L54: =ROUND(H54+J54+K54,2) -> 0 | M54: =$M$41 -> 0.1201 | N54: =H54*M54 -> 0 | O54: =N54 -> 0 | P54: =IF(Q54=1,"SI","NO") -> NO | Q54: =IF(D54="INCLUIDO",IF(F54<>0,1,0),0) -> 0 | R54: =IF(I54="%o Al Millar",1000,IF(I54="% Al Porciento",100,IF(I54="$ Prima",G54))) -> 1000 | S54: =IF(E54="Excluido",0,IF(D54="NO APLICA",0,1)) -> 1
A55: INCENDIO | B55: 014 | C55: BIENES A LA INTEMPERIE INCENDIO | D55: =$D$17 -> INCLUIDO | E55: Sublimite | F55: ='COTIZACIÓN M.N.'!D65 -> 3000000 | G55: ='COTIZACIÓN M.N.'!E65 -> 0.25 | H55: =((((IF(I55="$ Prima",G55,G55*F55/R55))*$U$9)/365)*$J$15)/3 -> 250.68493 | I55: %o Al Millar | J55: =H55*$U$7 -> 5.2894521 | K55: =(H55+J55)*$K$15 -> 40.955901 | L55: =ROUND(H55+J55+K55,2) -> 296.93 | M55: =$M$41 -> 0.1201 | N55: =H55*M55 -> 30.10726 | O55: =N55 -> 30.10726 | P55: =IF(Q55=1,"SI","NO") -> SI | Q55: =IF(D55="INCLUIDO",IF(F55<>0,1,0),0) -> 1 | R55: =IF(I55="%o Al Millar",1000,IF(I55="% Al Porciento",100,IF(I55="$ Prima",G55))) -> 1000 | S55: =IF(E55="Excluido",0,IF(D55="NO APLICA",0,1)) -> 1 | W55: ='UB (1)'!H55+'UB (2)'!H55+'UB (3)'!H55+#REF!+#REF!+#REF!+#REF!+#REF!+#REF!+#REF!+#REF!+#REF!+#REF!+#REF!+#REF!+#REF!+#REF!+#REF!+#REF!+#REF!+#REF!+#REF!+#REF!+#REF!+#REF!+#REF!+#REF!+#REF!+#REF!+#REF!+#REF!+#REF!+#REF!+#REF!+#REF!+#REF!+#REF!+#REF!+#REF!+#REF!+#REF!+#REF!+#REF!+#REF!+#REF!+#REF!+#REF!+#REF!+#REF!+#REF!+#REF!+#REF!+#REF!+#REF!+#REF!+#REF!+#REF!+#REF!+#REF!+#REF!+#REF!+#REF!+#REF!+#REF!+#REF!+#REF!+#REF!+#REF!+#REF!+#REF!+#REF!+#REF!+#REF!+#REF!+#REF!+#REF!+#REF!+#REF!+#REF!+#REF!+#REF!+#REF!+#REF!+#REF!+#REF!+#REF!+#REF!+#REF!+#REF!+#REF!+#REF!+#REF!+#REF!+#REF!+#REF!+#REF!+#REF!+#REF!+#REF!+#REF!+#REF!+#REF!+#REF!+#REF!+#REF!+#REF!+#REF!+#REF!+#REF!+#REF!+#REF!+#REF!+#REF!+#REF!+#REF!+#REF!+#REF!+#REF!+#REF!+#REF!+#REF!+#REF!+#REF!+#REF!+#REF!+#REF!+#REF!+#REF!+#REF!+#REF!+#REF!+#REF!+#REF!+#REF!+#REF!+#REF!+#REF!+#REF!+#REF!+#REF!+#REF!+#REF!+#REF!+#REF!+#REF!+#REF!+#REF!+#REF!+#REF!+#REF!+#REF!+#REF!+#REF!+#REF!+#REF!+#REF!+#REF!+#REF!+#REF!+#REF!+#REF!+#REF!+#REF!+#REF!+#REF!+#REF!+#REF!+#REF!+#REF!+#REF!+#REF!+#REF!+#REF!+#REF!+#REF!+#REF!+#REF!+#REF!+#REF!+#REF!+#REF!+#REF!+#REF!+#REF!+#REF!+#REF!+#REF!+#REF!+#REF!+#REF!+#REF!+#REF!+#REF!+#REF!+#REF!+#REF!+#REF!+#REF!+#REF!+#REF!+#REF!+#REF!+#REF!+#REF!+#REF!+#REF!+#REF!+#REF!+#REF!+#REF!+#REF!+#REF!+#REF!+#REF!+#REF!+#REF!+#REF!+#REF!+#REF!+#REF!+#REF!+#REF!+#REF!+#REF!+#REF!+#REF!+#REF!+#REF!+#REF!+#REF!+#REF!+#REF!+#REF!+#REF!+#REF!+#REF!+#REF!+#REF!+#REF!+#REF!+#REF!+#REF!+#REF!+#REF!+#REF!+#REF!+#REF!+#REF!+#REF!+#REF!+#REF!+#REF!+#REF!+#REF!+#REF!+#REF!+#REF!+#REF!+#REF!+#REF!+#REF!+#REF!+#REF!+#REF!+#REF!+#REF!+#REF!+#REF!+#REF!+#REF!+#REF!+#REF!+#REF!+#REF!+#REF!+#REF!+#REF!+#REF!+#REF!+#REF!+#REF!+#REF!+#REF!+#REF!+#REF!+#REF!+#REF!+#REF!+#REF!+#REF!+#REF!+#REF!+#REF!+#REF!+#REF!+#REF!+#REF!+#REF!+#REF!+#REF!+#REF!+#REF!+#REF!+#REF!+#REF!+#REF!+#REF!+#REF!+#REF!+#REF!+#REF!+#REF!+#REF!+#REF!+#REF!+#REF!+#REF!+#REF!+#REF!+#REF!+#REF!+#REF!+#REF!+#REF!+#REF!+#REF!+#REF!+#REF!+#REF!+#REF!+#REF!+#REF!+#REF!+#REF!+#REF!+#REF!+#REF!+#REF!+#REF!+#REF!+#REF!+#REF!+#REF!+#REF!+#REF!+#REF!+#REF!+#REF!+#REF!+#REF!+#REF!+#REF!+#REF!+#REF!+#REF!+#REF!+#REF!+#REF!+#REF!+#REF!+#REF!+#REF!+#REF!+#REF! -> #REF!
A56: INCENDIO | C56: =$O$12 -> 0 | D56: =$D$17 -> INCLUIDO | E56: =E55 -> Sublimite | F56: 0 | G56: =G55*0.35 -> 0.0875 | H56: =(IF(I56="$ Prima",G56,G56*F56/R56))*$U$9 -> 0 | I56: %o Al Millar | J56: =H56*$U$7 -> 0 | K56: =(H56+J56)*$K$15 -> 0 | L56: =ROUND(H56+J56+K56,2) -> 0 | M56: =$M$41 -> 0.1201 | N56: =H56*M56 -> 0 | O56: =N56 -> 0 | P56: =IF(Q56=1,"SI","NO") -> NO | Q56: =IF(D56="INCLUIDO",IF(F56<>0,1,0),0) -> 0 | R56: =IF(I56="%o Al Millar",1000,IF(I56="% Al Porciento",100,IF(I56="$ Prima",G56))) -> 1000 | S56: =IF(E56="Excluido",0,IF(D56="NO APLICA",0,1)) -> 1
A57: INCENDIO | B57: 015 | C57: BIENES EN CUARTOS REFRIGERADOS | D57: =$D$17 -> INCLUIDO | E57: Sublimite | F57: ='COTIZACIÓN M.N.'!D66 -> 150000 | G57: ='COTIZACIÓN M.N.'!E66 -> 0.2 | H57: =(((IF(I57="$ Prima",G57,G57*F57/R57))*$U$9)/365)*$J$15 -> 30.082192 | I57: %o Al Millar | J57: =H57*$U$7 -> 0.63473425 | K57: =(H57+J57)*$K$15 -> 4.9147082 | L57: =ROUND(H57+J57+K57,2) -> 35.63 | M57: =$M$41 -> 0.1201 | N57: =H57*M57 -> 3.6128712 | O57: =N57 -> 3.6128712 | P57: =IF(Q57=1,"SI","NO") -> SI | Q57: =IF(D57="INCLUIDO",IF(F57<>0,1,0),0) -> 1 | R57: =IF(I57="%o Al Millar",1000,IF(I57="% Al Porciento",100,IF(I57="$ Prima",G57))) -> 1000 | S57: =IF(E57="Excluido",0,IF(D57="NO APLICA",0,1)) -> 1 | W57: ='UB (1)'!H57+'UB (2)'!H57+'UB (3)'!H57+#REF!+#REF!+#REF!+#REF!+#REF!+#REF!+#REF!+#REF!+#REF!+#REF!+#REF!+#REF!+#REF!+#REF!+#REF!+#REF!+#REF!+#REF!+#REF!+#REF!+#REF!+#REF!+#REF!+#REF!+#REF!+#REF!+#REF!+#REF!+#REF!+#REF!+#REF!+#REF!+#REF!+#REF!+#REF!+#REF!+#REF!+#REF!+#REF!+#REF!+#REF!+#REF!+#REF!+#REF!+#REF!+#REF!+#REF!+#REF!+#REF!+#REF!+#REF!+#REF!+#REF!+#REF!+#REF!+#REF!+#REF!+#REF!+#REF!+#REF!+#REF!+#REF!+#REF!+#REF!+#REF!+#REF!+#REF!+#REF!+#REF!+#REF!+#REF!+#REF!+#REF!+#REF!+#REF!+#REF!+#REF!+#REF!+#REF!+#REF!+#REF!+#REF!+#REF!+#REF!+#REF!+#REF!+#REF!+#REF!+#REF!+#REF!+#REF!+#REF!+#REF!+#REF!+#REF!+#REF!+#REF!+#REF!+#REF!+#REF!+#REF!+#REF!+#REF!+#REF!+#REF!+#REF!+#REF!+#REF!+#REF!+#REF!+#REF!+#REF!+#REF!+#REF!+#REF!+#REF!+#REF!+#REF!+#REF!+#REF!+#REF!+#REF!+#REF!+#REF!+#REF!+#REF!+#REF!+#REF!+#REF!+#REF!+#REF!+#REF!+#REF!+#REF!+#REF!+#REF!+#REF!+#REF!+#REF!+#REF!+#REF!+#REF!+#REF!+#REF!+#REF!+#REF!+#REF!+#REF!+#REF!+#REF!+#REF!+#REF!+#REF!+#REF!+#REF!+#REF!+#REF!+#REF!+#REF!+#REF!+#REF!+#REF!+#REF!+#REF!+#REF!+#REF!+#REF!+#REF!+#REF!+#REF!+#REF!+#REF!+#REF!+#REF!+#REF!+#REF!+#REF!+#REF!+#REF!+#REF!+#REF!+#REF!+#REF!+#REF!+#REF!+#REF!+#REF!+#REF!+#REF!+#REF!+#REF!+#REF!+#REF!+#REF!+#REF!+#REF!+#REF!+#REF!+#REF!+#REF!+#REF!+#REF!+#REF!+#REF!+#REF!+#REF!+#REF!+#REF!+#REF!+#REF!+#REF!+#REF!+#REF!+#REF!+#REF!+#REF!+#REF!+#REF!+#REF!+#REF!+#REF!+#REF!+#REF!+#REF!+#REF!+#REF!+#REF!+#REF!+#REF!+#REF!+#REF!+#REF!+#REF!+#REF!+#REF!+#REF!+#REF!+#REF!+#REF!+#REF!+#REF!+#REF!+#REF!+#REF!+#REF!+#REF!+#REF!+#REF!+#REF!+#REF!+#REF!+#REF!+#REF!+#REF!+#REF!+#REF!+#REF!+#REF!+#REF!+#REF!+#REF!+#REF!+#REF!+#REF!+#REF!+#REF!+#REF!+#REF!+#REF!+#REF!+#REF!+#REF!+#REF!+#REF!+#REF!+#REF!+#REF!+#REF!+#REF!+#REF!+#REF!+#REF!+#REF!+#REF!+#REF!+#REF!+#REF!+#REF!+#REF!+#REF!+#REF!+#REF!+#REF!+#REF!+#REF!+#REF!+#REF!+#REF!+#REF!+#REF!+#REF!+#REF!+#REF!+#REF!+#REF!+#REF!+#REF!+#REF!+#REF!+#REF!+#REF!+#REF!+#REF!+#REF!+#REF!+#REF!+#REF!+#REF!+#REF!+#REF!+#REF!+#REF!+#REF!+#REF!+#REF!+#REF!+#REF!+#REF!+#REF!+#REF!+#REF!+#REF!+#REF!+#REF!+#REF!+#REF!+#REF!+#REF!+#REF!+#REF!+#REF!+#REF!+#REF!+#REF!+#REF!+#REF!+#REF!+#REF!+#REF!+#REF!+#REF!+#REF!+#REF!+#REF!+#REF!+#REF!+#REF!+#REF!+#REF!+#REF!+#REF! -> #REF!
A58: INCENDIO | C58: =$O$12 -> 0 | D58: =$D$17 -> INCLUIDO | E58: =E57 -> Sublimite | F58: 0 | G58: =G57*0.35 -> 0.07 | H58: =(IF(I58="$ Prima",G58,G58*F58/R58))*$U$9 -> 0 | I58: %o Al Millar | J58: =H58*$U$7 -> 0 | K58: =(H58+J58)*$K$15 -> 0 | L58: =ROUND(H58+J58+K58,2) -> 0 | M58: =$M$41 -> 0.1201 | N58: =H58*M58 -> 0 | O58: =N58 -> 0 | P58: =IF(Q58=1,"SI","NO") -> NO | Q58: =IF(D58="INCLUIDO",IF(F58<>0,1,0),0) -> 0 | R58: =IF(I58="%o Al Millar",1000,IF(I58="% Al Porciento",100,IF(I58="$ Prima",G58))) -> 1000 | S58: =IF(E58="Excluido",0,IF(D58="NO APLICA",0,1)) -> 1
A59: INCENDIO | B59: 019 | C59: INCISOS CONOCIDOS | D59: =$D$17 -> INCLUIDO | E59: Sublimite | F59: ='COTIZACIÓN M.N.'!D67 -> 5000000 | G59: =G26 -> 0.0011 | H59: =((IF(I59="$ Prima",G59,G59*F59/R59))*$U$9)*2 -> 11 | I59: %o Al Millar | J59: =H59*$U$7 -> 0.2321 | K59: =(H59+J59)*$K$15 -> 1.797136 | L59: =ROUND(H59+J59+K59,2) -> 13.03 | M59: =$M$41 -> 0.1201 | N59: =H59*M59 -> 1.3211 | O59: =N59 -> 1.3211 | P59: =IF(Q59=1,"SI","NO") -> SI | Q59: =IF(D59="INCLUIDO",IF(F59<>0,1,0),0) -> 1 | R59: =IF(I59="%o Al Millar",1000,IF(I59="% Al Porciento",100,IF(I59="$ Prima",G59))) -> 1000 | S59: =IF(E59="Excluido",0,IF(D59="NO APLICA",0,1)) -> 1 | W59: ='UB (1)'!H59+'UB (2)'!H59+'UB (3)'!H59+#REF!+#REF!+#REF!+#REF!+#REF!+#REF!+#REF!+#REF!+#REF!+#REF!+#REF!+#REF!+#REF!+#REF!+#REF!+#REF!+#REF!+#REF!+#REF!+#REF!+#REF!+#REF!+#REF!+#REF!+#REF!+#REF!+#REF!+#REF!+#REF!+#REF!+#REF!+#REF!+#REF!+#REF!+#REF!+#REF!+#REF!+#REF!+#REF!+#REF!+#REF!+#REF!+#REF!+#REF!+#REF!+#REF!+#REF!+#REF!+#REF!+#REF!+#REF!+#REF!+#REF!+#REF!+#REF!+#REF!+#REF!+#REF!+#REF!+#REF!+#REF!+#REF!+#REF!+#REF!+#REF!+#REF!+#REF!+#REF!+#REF!+#REF!+#REF!+#REF!+#REF!+#REF!+#REF!+#REF!+#REF!+#REF!+#REF!+#REF!+#REF!+#REF!+#REF!+#REF!+#REF!+#REF!+#REF!+#REF!+#REF!+#REF!+#REF!+#REF!+#REF!+#REF!+#REF!+#REF!+#REF!+#REF!+#REF!+#REF!+#REF!+#REF!+#REF!+#REF!+#REF!+#REF!+#REF!+#REF!+#REF!+#REF!+#REF!+#REF!+#REF!+#REF!+#REF!+#REF!+#REF!+#REF!+#REF!+#REF!+#REF!+#REF!+#REF!+#REF!+#REF!+#REF!+#REF!+#REF!+#REF!+#REF!+#REF!+#REF!+#REF!+#REF!+#REF!+#REF!+#REF!+#REF!+#REF!+#REF!+#REF!+#REF!+#REF!+#REF!+#REF!+#REF!+#REF!+#REF!+#REF!+#REF!+#REF!+#REF!+#REF!+#REF!+#REF!+#REF!+#REF!+#REF!+#REF!+#REF!+#REF!+#REF!+#REF!+#REF!+#REF!+#REF!+#REF!+#REF!+#REF!+#REF!+#REF!+#REF!+#REF!+#REF!+#REF!+#REF!+#REF!+#REF!+#REF!+#REF!+#REF!+#REF!+#REF!+#REF!+#REF!+#REF!+#REF!+#REF!+#REF!+#REF!+#REF!+#REF!+#REF!+#REF!+#REF!+#REF!+#REF!+#REF!+#REF!+#REF!+#REF!+#REF!+#REF!+#REF!+#REF!+#REF!+#REF!+#REF!+#REF!+#REF!+#REF!+#REF!+#REF!+#REF!+#REF!+#REF!+#REF!+#REF!+#REF!+#REF!+#REF!+#REF!+#REF!+#REF!+#REF!+#REF!+#REF!+#REF!+#REF!+#REF!+#REF!+#REF!+#REF!+#REF!+#REF!+#REF!+#REF!+#REF!+#REF!+#REF!+#REF!+#REF!+#REF!+#REF!+#REF!+#REF!+#REF!+#REF!+#REF!+#REF!+#REF!+#REF!+#REF!+#REF!+#REF!+#REF!+#REF!+#REF!+#REF!+#REF!+#REF!+#REF!+#REF!+#REF!+#REF!+#REF!+#REF!+#REF!+#REF!+#REF!+#REF!+#REF!+#REF!+#REF!+#REF!+#REF!+#REF!+#REF!+#REF!+#REF!+#REF!+#REF!+#REF!+#REF!+#REF!+#REF!+#REF!+#REF!+#REF!+#REF!+#REF!+#REF!+#REF!+#REF!+#REF!+#REF!+#REF!+#REF!+#REF!+#REF!+#REF!+#REF!+#REF!+#REF!+#REF!+#REF!+#REF!+#REF!+#REF!+#REF!+#REF!+#REF!+#REF!+#REF!+#REF!+#REF!+#REF!+#REF!+#REF!+#REF!+#REF!+#REF!+#REF!+#REF!+#REF!+#REF!+#REF!+#REF!+#REF!+#REF!+#REF!+#REF!+#REF!+#REF!+#REF!+#REF!+#REF!+#REF!+#REF!+#REF!+#REF!+#REF!+#REF!+#REF!+#REF!+#REF!+#REF!+#REF!+#REF!+#REF!+#REF!+#REF!+#REF!+#REF!+#REF!+#REF!+#REF!+#REF!+#REF!+#REF!+#REF! -> #REF!
A60: INCENDIO | B60: 020 | C60: INCISOS NO CONOCIDOS | D60: =$D$17 -> INCLUIDO | E60: Sublimite | F60: ='COTIZACIÓN M.N.'!D68 -> 5000000 | G60: =G59 -> 0.0011 | H60: =((IF(I60="$ Prima",G60,G60*F60/R60))*$U$9)*2 -> 11 | I60: %o Al Millar | J60: =H60*$U$7 -> 0.2321 | K60: =(H60+J60)*$K$15 -> 1.797136 | L60: =ROUND(H60+J60+K60,2) -> 13.03 | M60: =$M$41 -> 0.1201 | N60: =H60*M60 -> 1.3211 | O60: =N60 -> 1.3211 | P60: =IF(Q60=1,"SI","NO") -> SI | Q60: =IF(D60="INCLUIDO",IF(F60<>0,1,0),0) -> 1 | R60: =IF(I60="%o Al Millar",1000,IF(I60="% Al Porciento",100,IF(I60="$ Prima",G60))) -> 1000 | S60: =IF(E60="Excluido",0,IF(D60="NO APLICA",0,1)) -> 1 | W60: ='UB (1)'!H60+'UB (2)'!H60+'UB (3)'!H60+#REF!+#REF!+#REF!+#REF!+#REF!+#REF!+#REF!+#REF!+#REF!+#REF!+#REF!+#REF!+#REF!+#REF!+#REF!+#REF!+#REF!+#REF!+#REF!+#REF!+#REF!+#REF!+#REF!+#REF!+#REF!+#REF!+#REF!+#REF!+#REF!+#REF!+#REF!+#REF!+#REF!+#REF!+#REF!+#REF!+#REF!+#REF!+#REF!+#REF!+#REF!+#REF!+#REF!+#REF!+#REF!+#REF!+#REF!+#REF!+#REF!+#REF!+#REF!+#REF!+#REF!+#REF!+#REF!+#REF!+#REF!+#REF!+#REF!+#REF!+#REF!+#REF!+#REF!+#REF!+#REF!+#REF!+#REF!+#REF!+#REF!+#REF!+#REF!+#REF!+#REF!+#REF!+#REF!+#REF!+#REF!+#REF!+#REF!+#REF!+#REF!+#REF!+#REF!+#REF!+#REF!+#REF!+#REF!+#REF!+#REF!+#REF!+#REF!+#REF!+#REF!+#REF!+#REF!+#REF!+#REF!+#REF!+#REF!+#REF!+#REF!+#REF!+#REF!+#REF!+#REF!+#REF!+#REF!+#REF!+#REF!+#REF!+#REF!+#REF!+#REF!+#REF!+#REF!+#REF!+#REF!+#REF!+#REF!+#REF!+#REF!+#REF!+#REF!+#REF!+#REF!+#REF!+#REF!+#REF!+#REF!+#REF!+#REF!+#REF!+#REF!+#REF!+#REF!+#REF!+#REF!+#REF!+#REF!+#REF!+#REF!+#REF!+#REF!+#REF!+#REF!+#REF!+#REF!+#REF!+#REF!+#REF!+#REF!+#REF!+#REF!+#REF!+#REF!+#REF!+#REF!+#REF!+#REF!+#REF!+#REF!+#REF!+#REF!+#REF!+#REF!+#REF!+#REF!+#REF!+#REF!+#REF!+#REF!+#REF!+#REF!+#REF!+#REF!+#REF!+#REF!+#REF!+#REF!+#REF!+#REF!+#REF!+#REF!+#REF!+#REF!+#REF!+#REF!+#REF!+#REF!+#REF!+#REF!+#REF!+#REF!+#REF!+#REF!+#REF!+#REF!+#REF!+#REF!+#REF!+#REF!+#REF!+#REF!+#REF!+#REF!+#REF!+#REF!+#REF!+#REF!+#REF!+#REF!+#REF!+#REF!+#REF!+#REF!+#REF!+#REF!+#REF!+#REF!+#REF!+#REF!+#REF!+#REF!+#REF!+#REF!+#REF!+#REF!+#REF!+#REF!+#REF!+#REF!+#REF!+#REF!+#REF!+#REF!+#REF!+#REF!+#REF!+#REF!+#REF!+#REF!+#REF!+#REF!+#REF!+#REF!+#REF!+#REF!+#REF!+#REF!+#REF!+#REF!+#REF!+#REF!+#REF!+#REF!+#REF!+#REF!+#REF!+#REF!+#REF!+#REF!+#REF!+#REF!+#REF!+#REF!+#REF!+#REF!+#REF!+#REF!+#REF!+#REF!+#REF!+#REF!+#REF!+#REF!+#REF!+#REF!+#REF!+#REF!+#REF!+#REF!+#REF!+#REF!+#REF!+#REF!+#REF!+#REF!+#REF!+#REF!+#REF!+#REF!+#REF!+#REF!+#REF!+#REF!+#REF!+#REF!+#REF!+#REF!+#REF!+#REF!+#REF!+#REF!+#REF!+#REF!+#REF!+#REF!+#REF!+#REF!+#REF!+#REF!+#REF!+#REF!+#REF!+#REF!+#REF!+#REF!+#REF!+#REF!+#REF!+#REF!+#REF!+#REF!+#REF!+#REF!+#REF!+#REF!+#REF!+#REF!+#REF!+#REF!+#REF!+#REF!+#REF!+#REF!+#REF!+#REF!+#REF!+#REF!+#REF!+#REF!+#REF!+#REF!+#REF!+#REF!+#REF!+#REF!+#REF!+#REF!+#REF!+#REF!+#REF!+#REF!+#REF!+#REF!+#REF!+#REF!+#REF!+#REF!+#REF!+#REF! -> #REF!
A61: 903 | B61: 2 | C61: HIDROMETEOROLOGICO CONTENIDOS | D61: =$D$17 -> INCLUIDO | M61: 0.05 | P61: =IF(Q61=1,"SI","NO") -> SI | Q61: =IF(D61="INCLUIDO",IF(F62<>0,1,0),0) -> 1 | S61: =IF(E61="Excluido",0,IF(D61="NO APLICA",0,1)) -> 1 | W61: ='UB (1)'!H61+'UB (2)'!H61+'UB (3)'!H61+#REF!+#REF!+#REF!+#REF!+#REF!+#REF!+#REF!+#REF!+#REF!+#REF!+#REF!+#REF!+#REF!+#REF!+#REF!+#REF!+#REF!+#REF!+#REF!+#REF!+#REF!+#REF!+#REF!+#REF!+#REF!+#REF!+#REF!+#REF!+#REF!+#REF!+#REF!+#REF!+#REF!+#REF!+#REF!+#REF!+#REF!+#REF!+#REF!+#REF!+#REF!+#REF!+#REF!+#REF!+#REF!+#REF!+#REF!+#REF!+#REF!+#REF!+#REF!+#REF!+#REF!+#REF!+#REF!+#REF!+#REF!+#REF!+#REF!+#REF!+#REF!+#REF!+#REF!+#REF!+#REF!+#REF!+#REF!+#REF!+#REF!+#REF!+#REF!+#REF!+#REF!+#REF!+#REF!+#REF!+#REF!+#REF!+#REF!+#REF!+#REF!+#REF!+#REF!+#REF!+#REF!+#REF!+#REF!+#REF!+#REF!+#REF!+#REF!+#REF!+#REF!+#REF!+#REF!+#REF!+#REF!+#REF!+#REF!+#REF!+#REF!+#REF!+#REF!+#REF!+#REF!+#REF!+#REF!+#REF!+#REF!+#REF!+#REF!+#REF!+#REF!+#REF!+#REF!+#REF!+#REF!+#REF!+#REF!+#REF!+#REF!+#REF!+#REF!+#REF!+#REF!+#REF!+#REF!+#REF!+#REF!+#REF!+#REF!+#REF!+#REF!+#REF!+#REF!+#REF!+#REF!+#REF!+#REF!+#REF!+#REF!+#REF!+#REF!+#REF!+#REF!+#REF!+#REF!+#REF!+#REF!+#REF!+#REF!+#REF!+#REF!+#REF!+#REF!+#REF!+#REF!+#REF!+#REF!+#REF!+#REF!+#REF!+#REF!+#REF!+#REF!+#REF!+#REF!+#REF!+#REF!+#REF!+#REF!+#REF!+#REF!+#REF!+#REF!+#REF!+#REF!+#REF!+#REF!+#REF!+#REF!+#REF!+#REF!+#REF!+#REF!+#REF!+#REF!+#REF!+#REF!+#REF!+#REF!+#REF!+#REF!+#REF!+#REF!+#REF!+#REF!+#REF!+#REF!+#REF!+#REF!+#REF!+#REF!+#REF!+#REF!+#REF!+#REF!+#REF!+#REF!+#REF!+#REF!+#REF!+#REF!+#REF!+#REF!+#REF!+#REF!+#REF!+#REF!+#REF!+#REF!+#REF!+#REF!+#REF!+#REF!+#REF!+#REF!+#REF!+#REF!+#REF!+#REF!+#REF!+#REF!+#REF!+#REF!+#REF!+#REF!+#REF!+#REF!+#REF!+#REF!+#REF!+#REF!+#REF!+#REF!+#REF!+#REF!+#REF!+#REF!+#REF!+#REF!+#REF!+#REF!+#REF!+#REF!+#REF!+#REF!+#REF!+#REF!+#REF!+#REF!+#REF!+#REF!+#REF!+#REF!+#REF!+#REF!+#REF!+#REF!+#REF!+#REF!+#REF!+#REF!+#REF!+#REF!+#REF!+#REF!+#REF!+#REF!+#REF!+#REF!+#REF!+#REF!+#REF!+#REF!+#REF!+#REF!+#REF!+#REF!+#REF!+#REF!+#REF!+#REF!+#REF!+#REF!+#REF!+#REF!+#REF!+#REF!+#REF!+#REF!+#REF!+#REF!+#REF!+#REF!+#REF!+#REF!+#REF!+#REF!+#REF!+#REF!+#REF!+#REF!+#REF!+#REF!+#REF!+#REF!+#REF!+#REF!+#REF!+#REF!+#REF!+#REF!+#REF!+#REF!+#REF!+#REF!+#REF!+#REF!+#REF!+#REF!+#REF!+#REF!+#REF!+#REF!+#REF!+#REF!+#REF!+#REF!+#REF!+#REF!+#REF!+#REF!+#REF!+#REF!+#REF!+#REF!+#REF!+#REF!+#REF!+#REF!+#REF!+#REF!+#REF!+#REF!+#REF!+#REF!+#REF!+#REF!+#REF!+#REF! -> #REF!
A62: FHM | B62: 046 | C62: RIESGOS HIDROMETEOROLÓGICOS | D62: =$D$17 -> INCLUIDO | E62: Sublimite | F62: =$F$41*S62 -> 8.6921645e+08 | G62: ='COTIZACIÓN M.N.'!E37 -> 0.25 | H62: =((((IF(I62="$ Prima",G62,G62*F62/R62))*$U$9)/365)*$J$15) -> 217899.47 | I62: %o Al Millar | J62: =H62*$U$7 -> 4597.6787 | K62: =(H62+J62)*$K$15 -> 35599.543 | L62: =ROUND(H62+J62+K62,2) -> 258096.69 | M62: 0.05 | N62: =H62*M62 -> 10894.973 | O62: =N62 -> 10894.973 | P62: =IF(Q62=1,"SI","NO") -> SI | Q62: =IF(D62="INCLUIDO",IF(F62<>0,1,0),0) -> 1 | R62: =IF(I62="%o Al Millar",1000,IF(I62="% Al Porciento",100,IF(I62="$ Prima",G62))) -> 1000 | S62: =IF(E62="Excluido",0,IF(D62="NO APLICA",0,1)) -> 1 | W62: ='UB (1)'!H62+'UB (2)'!H62+'UB (3)'!H62+#REF!+#REF!+#REF!+#REF!+#REF!+#REF!+#REF!+#REF!+#REF!+#REF!+#REF!+#REF!+#REF!+#REF!+#REF!+#REF!+#REF!+#REF!+#REF!+#REF!+#REF!+#REF!+#REF!+#REF!+#REF!+#REF!+#REF!+#REF!+#REF!+#REF!+#REF!+#REF!+#REF!+#REF!+#REF!+#REF!+#REF!+#REF!+#REF!+#REF!+#REF!+#REF!+#REF!+#REF!+#REF!+#REF!+#REF!+#REF!+#REF!+#REF!+#REF!+#REF!+#REF!+#REF!+#REF!+#REF!+#REF!+#REF!+#REF!+#REF!+#REF!+#REF!+#REF!+#REF!+#REF!+#REF!+#REF!+#REF!+#REF!+#REF!+#REF!+#REF!+#REF!+#REF!+#REF!+#REF!+#REF!+#REF!+#REF!+#REF!+#REF!+#REF!+#REF!+#REF!+#REF!+#REF!+#REF!+#REF!+#REF!+#REF!+#REF!+#REF!+#REF!+#REF!+#REF!+#REF!+#REF!+#REF!+#REF!+#REF!+#REF!+#REF!+#REF!+#REF!+#REF!+#REF!+#REF!+#REF!+#REF!+#REF!+#REF!+#REF!+#REF!+#REF!+#REF!+#REF!+#REF!+#REF!+#REF!+#REF!+#REF!+#REF!+#REF!+#REF!+#REF!+#REF!+#REF!+#REF!+#REF!+#REF!+#REF!+#REF!+#REF!+#REF!+#REF!+#REF!+#REF!+#REF!+#REF!+#REF!+#REF!+#REF!+#REF!+#REF!+#REF!+#REF!+#REF!+#REF!+#REF!+#REF!+#REF!+#REF!+#REF!+#REF!+#REF!+#REF!+#REF!+#REF!+#REF!+#REF!+#REF!+#REF!+#REF!+#REF!+#REF!+#REF!+#REF!+#REF!+#REF!+#REF!+#REF!+#REF!+#REF!+#REF!+#REF!+#REF!+#REF!+#REF!+#REF!+#REF!+#REF!+#REF!+#REF!+#REF!+#REF!+#REF!+#REF!+#REF!+#REF!+#REF!+#REF!+#REF!+#REF!+#REF!+#REF!+#REF!+#REF!+#REF!+#REF!+#REF!+#REF!+#REF!+#REF!+#REF!+#REF!+#REF!+#REF!+#REF!+#REF!+#REF!+#REF!+#REF!+#REF!+#REF!+#REF!+#REF!+#REF!+#REF!+#REF!+#REF!+#REF!+#REF!+#REF!+#REF!+#REF!+#REF!+#REF!+#REF!+#REF!+#REF!+#REF!+#REF!+#REF!+#REF!+#REF!+#REF!+#REF!+#REF!+#REF!+#REF!+#REF!+#REF!+#REF!+#REF!+#REF!+#REF!+#REF!+#REF!+#REF!+#REF!+#REF!+#REF!+#REF!+#REF!+#REF!+#REF!+#REF!+#REF!+#REF!+#REF!+#REF!+#REF!+#REF!+#REF!+#REF!+#REF!+#REF!+#REF!+#REF!+#REF!+#REF!+#REF!+#REF!+#REF!+#REF!+#REF!+#REF!+#REF!+#REF!+#REF!+#REF!+#REF!+#REF!+#REF!+#REF!+#REF!+#REF!+#REF!+#REF!+#REF!+#REF!+#REF!+#REF!+#REF!+#REF!+#REF!+#REF!+#REF!+#REF!+#REF!+#REF!+#REF!+#REF!+#REF!+#REF!+#REF!+#REF!+#REF!+#REF!+#REF!+#REF!+#REF!+#REF!+#REF!+#REF!+#REF!+#REF!+#REF!+#REF!+#REF!+#REF!+#REF!+#REF!+#REF!+#REF!+#REF!+#REF!+#REF!+#REF!+#REF!+#REF!+#REF!+#REF!+#REF!+#REF!+#REF!+#REF!+#REF!+#REF!+#REF!+#REF!+#REF!+#REF!+#REF!+#REF!+#REF!+#REF!+#REF!+#REF!+#REF!+#REF!+#REF!+#REF!+#REF!+#REF!+#REF!+#REF!+#REF!+#REF!+#REF!+#REF! -> #REF!
A63: FHM | C63: =$O$12 -> 0 | D63: =$D$17 -> INCLUIDO | E63: =E62 -> Sublimite | F63: =(F62*$O$12)*S62 -> 0 | G63: =G62*35% -> 0.0875 | H63: =((IF(I63="$ Prima",G63,G63*F63/R63))*$U$9) -> 0 | I63: %o Al Millar | J63: =H63*$U$7 -> 0 | K63: =(H63+J63)*$K$15 -> 0 | L63: =ROUND(H63+J63+K63,2) -> 0 | M63: =$M$61 -> 0.05 | N63: =H63*M63 -> 0 | O63: =N63 -> 0 | P63: =IF(Q63=1,"SI","NO") -> NO | Q63: =IF(D63="INCLUIDO",IF(F63<>0,1,0),0) -> 0 | R63: =IF(I63="%o Al Millar",1000,IF(I63="% Al Porciento",100,IF(I63="$ Prima",G63))) -> 1000 | S63: =IF(E63="Excluido",0,IF(D63="NO APLICA",0,1)) -> 1
A64: 904 | B64: 2 | C64: TERREMOTO CONTENIDOS | D64: =$D$17 -> INCLUIDO | M64: 0.05 | P64: =IF(Q64=1,"SI","NO") -> SI | Q64: =IF(D64="INCLUIDO",IF(F65<>0,1,0),0) -> 1 | S64: =IF(E64="Excluido",0,IF(D64="NO APLICA",0,1)) -> 1 | W64: ='UB (1)'!H64+'UB (2)'!H64+'UB (3)'!H64+#REF!+#REF!+#REF!+#REF!+#REF!+#REF!+#REF!+#REF!+#REF!+#REF!+#REF!+#REF!+#REF!+#REF!+#REF!+#REF!+#REF!+#REF!+#REF!+#REF!+#REF!+#REF!+#REF!+#REF!+#REF!+#REF!+#REF!+#REF!+#REF!+#REF!+#REF!+#REF!+#REF!+#REF!+#REF!+#REF!+#REF!+#REF!+#REF!+#REF!+#REF!+#REF!+#REF!+#REF!+#REF!+#REF!+#REF!+#REF!+#REF!+#REF!+#REF!+#REF!+#REF!+#REF!+#REF!+#REF!+#REF!+#REF!+#REF!+#REF!+#REF!+#REF!+#REF!+#REF!+#REF!+#REF!+#REF!+#REF!+#REF!+#REF!+#REF!+#REF!+#REF!+#REF!+#REF!+#REF!+#REF!+#REF!+#REF!+#REF!+#REF!+#REF!+#REF!+#REF!+#REF!+#REF!+#REF!+#REF!+#REF!+#REF!+#REF!+#REF!+#REF!+#REF!+#REF!+#REF!+#REF!+#REF!+#REF!+#REF!+#REF!+#REF!+#REF!+#REF!+#REF!+#REF!+#REF!+#REF!+#REF!+#REF!+#REF!+#REF!+#REF!+#REF!+#REF!+#REF!+#REF!+#REF!+#REF!+#REF!+#REF!+#REF!+#REF!+#REF!+#REF!+#REF!+#REF!+#REF!+#REF!+#REF!+#REF!+#REF!+#REF!+#REF!+#REF!+#REF!+#REF!+#REF!+#REF!+#REF!+#REF!+#REF!+#REF!+#REF!+#REF!+#REF!+#REF!+#REF!+#REF!+#REF!+#REF!+#REF!+#REF!+#REF!+#REF!+#REF!+#REF!+#REF!+#REF!+#REF!+#REF!+#REF!+#REF!+#REF!+#REF!+#REF!+#REF!+#REF!+#REF!+#REF!+#REF!+#REF!+#REF!+#REF!+#REF!+#REF!+#REF!+#REF!+#REF!+#REF!+#REF!+#REF!+#REF!+#REF!+#REF!+#REF!+#REF!+#REF!+#REF!+#REF!+#REF!+#REF!+#REF!+#REF!+#REF!+#REF!+#REF!+#REF!+#REF!+#REF!+#REF!+#REF!+#REF!+#REF!+#REF!+#REF!+#REF!+#REF!+#REF!+#REF!+#REF!+#REF!+#REF!+#REF!+#REF!+#REF!+#REF!+#REF!+#REF!+#REF!+#REF!+#REF!+#REF!+#REF!+#REF!+#REF!+#REF!+#REF!+#REF!+#REF!+#REF!+#REF!+#REF!+#REF!+#REF!+#REF!+#REF!+#REF!+#REF!+#REF!+#REF!+#REF!+#REF!+#REF!+#REF!+#REF!+#REF!+#REF!+#REF!+#REF!+#REF!+#REF!+#REF!+#REF!+#REF!+#REF!+#REF!+#REF!+#REF!+#REF!+#REF!+#REF!+#REF!+#REF!+#REF!+#REF!+#REF!+#REF!+#REF!+#REF!+#REF!+#REF!+#REF!+#REF!+#REF!+#REF!+#REF!+#REF!+#REF!+#REF!+#REF!+#REF!+#REF!+#REF!+#REF!+#REF!+#REF!+#REF!+#REF!+#REF!+#REF!+#REF!+#REF!+#REF!+#REF!+#REF!+#REF!+#REF!+#REF!+#REF!+#REF!+#REF!+#REF!+#REF!+#REF!+#REF!+#REF!+#REF!+#REF!+#REF!+#REF!+#REF!+#REF!+#REF!+#REF!+#REF!+#REF!+#REF!+#REF!+#REF!+#REF!+#REF!+#REF!+#REF!+#REF!+#REF!+#REF!+#REF!+#REF!+#REF!+#REF!+#REF!+#REF!+#REF!+#REF!+#REF!+#REF!+#REF!+#REF!+#REF!+#REF!+#REF!+#REF!+#REF!+#REF!+#REF!+#REF!+#REF!+#REF!+#REF!+#REF!+#REF!+#REF!+#REF!+#REF!+#REF!+#REF!+#REF!+#REF!+#REF!+#REF! -> #REF!
